Workbook
Name AmenTabla: Listas!$AJ$5:$AK$141
Name AmenTipo: Listas!$AJ$5:$AJ$141
Name LstActivo: Listas!$AH$5:$AH$238
Name LstCargo: Listas!$C$5:$C$14
Name LstEntorno: Listas!$E$5:$E$8
Name LstEstado: Listas!$G$5:$G$8
Name LstProceso: Listas!$B$5:$B$9
Name LstProcesoTodos: Listas!$AD$5:$AD$10
Name LstProveedor: Listas!$D$5:$D$18
Name LstSiNo: Listas!$F$5:$F$7
Name LstSubtipoTodos: Listas!$AG$5:$AG$142
Name LstTipo: Listas!$I$5:$I$14
Name LstTipoTodos: Listas!$AF$5:$AF$15
Name LstTratamiento: Listas!$H$5:$H$8
Name MgActId: '1. Matriz de Activos'!$B$6:$B$239
Name MgAmenClave: 'Amenazas MAGERIT'!$V$6:$V$62
Name MgAmenCod: 'Amenazas MAGERIT'!$B$6:$B$62
Name MgAmenCtrl: 'Amenazas MAGERIT'!$S$6:$S$62
Name MgAmenDegC: 'Amenazas MAGERIT'!$Q$6:$Q$62
Name MgAmenDegD: 'Amenazas MAGERIT'!$O$6:$O$62
Name MgAmenDegI: 'Amenazas MAGERIT'!$P$6:$P$62
Name MgAmenFrec: 'Amenazas MAGERIT'!$R$6:$R$62
Name MgAmenGrupo: 'Amenazas MAGERIT'!$D$6:$D$62
Name MgAmenNombre: 'Amenazas MAGERIT'!$C$6:$C$62
Name MgDeg: 'Escalas MAGERIT'!$B$20:$C$25
Name MgDegEt: 'Escalas MAGERIT'!$B$20:$B$25
Name MgFrec: 'Escalas MAGERIT'!$B$30:$C$34
Name MgFrecEt: 'Escalas MAGERIT'!$B$30:$B$34
Name MgMad: 'Escalas MAGERIT'!$B$40:$C$45
Name MgMadEt: 'Escalas MAGERIT'!$B$40:$B$45
Name MgNombre: '1. Matriz de Activos'!$C$6:$C$239
Name MgProceso: '1. Matriz de Activos'!$G$6:$G$239
Name MgSubtipo: '1. Matriz de Activos'!$F$6:$F$239
Name MgTipo: '1. Matriz de Activos'!$E$6:$E$239
Name MgValor: 'Escalas MAGERIT'!$B$6:$C$11
Name MgValorAct: '1. Matriz de Activos'!$T$6:$T$239
Name MgValorEt: 'Escalas MAGERIT'!$B$6:$B$11
Name RankProc: 'Amenazas MAGERIT'!$AN$6:$AN$62
Name SUB_AUX: Listas!$Q$5:$Q$16
Name SUB_COM: Listas!$O$5:$O$16
Name SUB_D: Listas!$J$5:$J$15
Name SUB_HW: Listas!$N$5:$N$26
Name SUB_K: Listas!$K$5:$K$18
Name SUB_L: Listas!$R$5:$R$14
Name SUB_Media: Listas!$P$5:$P$19
Name SUB_P: Listas!$S$5:$S$14
Name SUB_S: Listas!$L$5:$L$18
Name SUB_SW: Listas!$M$5:$M$21
Name TotProc: 'Amenazas MAGERIT'!$AO$6:$AO$62
Name LstMadurez: Listas!$AM$5:$AM$10
Name LstAplica: Listas!$AN$5:$AN$6
Name LstCapacidad: Listas!$AO$5:$AO$19
Name CtrlCod: '4. Controles y Madurez'!$B$6:$B$98
Name CtrlDom: '4. Controles y Madurez'!$D$6:$D$98
Name CtrlCap: '4. Controles y Madurez'!$E$6:$E$98
Name CtrlAplica: '4. Controles y Madurez'!$F$6:$F$98
Name CtrlBase: '4. Controles y Madurez'!$G$6:$G$98
Name CtrlActual: '4. Controles y Madurez'!$H$6:$H$98
Name CtrlObjetivo: '4. Controles y Madurez'!$I$6:$I$98
Name CtrlEfic: '4. Controles y Madurez'!$J$6:$J$98

Sheet Dashboard
B1: TABLERO DE RIESGOS — MAGERIT v3.0
B2: Todo responde al proceso elegido en la celda amarilla.
B3: Código de color: | C3: Amarillo = Campo de entrada — se selecciona de una lista | E3: Lila = Calculado automáticamente — no escribir encima | G3: Gris = Dato de la norma MAGERIT — no modificar
B5: Proceso o Área | C5: (Todos los procesos)
B7: INDICADORES DEL PROCESO SELECCIONADO
B8: Activos del proceso | C8: =IF($C$5="(Todos los procesos)",COUNTA('1. Matriz de Activos'!$B$6:$B$239),COUNTIF('1. Matriz de Activos'!$G$6:$G$239,$C$5))
B9: Activos valorados (valor 4 o más) | C9: =IF($C$5="(Todos los procesos)",COUNTIF(MgValorAct,">=4"),COUNTIFS('1. Matriz de Activos'!$G$6:$G$239,$C$5,MgValorAct,">=4"))
B10: Riesgos evaluados | C10: =IF($C$5="(Todos los procesos)",COUNTA('2. Valoración '!$B$6:$B$2261),COUNTIF('2. Valoración '!$E$6:$E$2261,$C$5))
B11: Riesgos Alto o Crítico (inherente) | C11: =IF($C$5="(Todos los procesos)",COUNTIF('2. Valoración '!$Z$6:$Z$2261,"Alto")+COUNTIF('2. Valoración '!$Z$6:$Z$2261,"Crítico"),COUNTIFS('2. Valoración '!$E$6:$E$2261,$C$5,'2. Valoración '!$Z$6:$Z$2261,"Alto")+COUNTIFS('2. Valoración '!$E$6:$E$2261,$C$5,'2. Valoración '!$Z$6:$Z$2261,"Crítico"))
B12: Riesgos Alto o Crítico (residual) | C12: =IF($C$5="(Todos los procesos)",COUNTIF('2. Valoración '!$AG$6:$AG$2261,"Alto")+COUNTIF('2. Valoración '!$AG$6:$AG$2261,"Crítico"),COUNTIFS('2. Valoración '!$E$6:$E$2261,$C$5,'2. Valoración '!$AG$6:$AG$2261,"Alto")+COUNTIFS('2. Valoración '!$E$6:$E$2261,$C$5,'2. Valoración '!$AG$6:$AG$2261,"Crítico"))
B14: ACTIVOS POR TIPO MAGERIT | F14: RIESGO INHERENTE FRENTE A RESIDUAL
B15: Tipo de activo | C15: Activos | D15: Valorados | F15: Nivel de riesgo | G15: Inherente | H15: Residual
B16: [D] Datos / Información | C16: =IF($C$5="(Todos los procesos)",COUNTIF(MgTipo,$B16),COUNTIFS('1. Matriz de Activos'!$G$6:$G$239,$C$5,MgTipo,$B16)) | D16: =IF($C$5="(Todos los procesos)",COUNTIFS(MgTipo,$B16,MgValorAct,">=4"),COUNTIFS('1. Matriz de Activos'!$G$6:$G$239,$C$5,MgTipo,$B16,MgValorAct,">=4")) | F16: Crítico | G16: =IF($C$5="(Todos los procesos)",COUNTIF('2. Valoración '!$Z$6:$Z$2261,$F16),COUNTIFS('2. Valoración '!$E$6:$E$2261,$C$5,'2. Valoración '!$Z$6:$Z$2261,$F16)) | H16: =IF($C$5="(Todos los procesos)",COUNTIF('2. Valoración '!$AG$6:$AG$2261,$F16),COUNTIFS('2. Valoración '!$E$6:$E$2261,$C$5,'2. Valoración '!$AG$6:$AG$2261,$F16))
B17: [K] Claves criptográficas | C17: =IF($C$5="(Todos los procesos)",COUNTIF(MgTipo,$B17),COUNTIFS('1. Matriz de Activos'!$G$6:$G$239,$C$5,MgTipo,$B17)) | D17: =IF($C$5="(Todos los procesos)",COUNTIFS(MgTipo,$B17,MgValorAct,">=4"),COUNTIFS('1. Matriz de Activos'!$G$6:$G$239,$C$5,MgTipo,$B17,MgValorAct,">=4")) | F17: Alto | G17: =IF($C$5="(Todos los procesos)",COUNTIF('2. Valoración '!$Z$6:$Z$2261,$F17),COUNTIFS('2. Valoración '!$E$6:$E$2261,$C$5,'2. Valoración '!$Z$6:$Z$2261,$F17)) | H17: =IF($C$5="(Todos los procesos)",COUNTIF('2. Valoración '!$AG$6:$AG$2261,$F17),COUNTIFS('2. Valoración '!$E$6:$E$2261,$C$5,'2. Valoración '!$AG$6:$AG$2261,$F17))
B18: [S] Servicios | C18: =IF($C$5="(Todos los procesos)",COUNTIF(MgTipo,$B18),COUNTIFS('1. Matriz de Activos'!$G$6:$G$239,$C$5,MgTipo,$B18)) | D18: =IF($C$5="(Todos los procesos)",COUNTIFS(MgTipo,$B18,MgValorAct,">=4"),COUNTIFS('1. Matriz de Activos'!$G$6:$G$239,$C$5,MgTipo,$B18,MgValorAct,">=4")) | F18: Medio | G18: =IF($C$5="(Todos los procesos)",COUNTIF('2. Valoración '!$Z$6:$Z$2261,$F18),COUNTIFS('2. Valoración '!$E$6:$E$2261,$C$5,'2. Valoración '!$Z$6:$Z$2261,$F18)) | H18: =IF($C$5="(Todos los procesos)",COUNTIF('2. Valoración '!$AG$6:$AG$2261,$F18),COUNTIFS('2. Valoración '!$E$6:$E$2261,$C$5,'2. Valoración '!$AG$6:$AG$2261,$F18))
B19: [SW] Aplicaciones (software) | C19: =IF($C$5="(Todos los procesos)",COUNTIF(MgTipo,$B19),COUNTIFS('1. Matriz de Activos'!$G$6:$G$239,$C$5,MgTipo,$B19)) | D19: =IF($C$5="(Todos los procesos)",COUNTIFS(MgTipo,$B19,MgValorAct,">=4"),COUNTIFS('1. Matriz de Activos'!$G$6:$G$239,$C$5,MgTipo,$B19,MgValorAct,">=4")) | F19: Bajo | G19: =IF($C$5="(Todos los procesos)",COUNTIF('2. Valoración '!$Z$6:$Z$2261,$F19),COUNTIFS('2. Valoración '!$E$6:$E$2261,$C$5,'2. Valoración '!$Z$6:$Z$2261,$F19)) | H19: =IF($C$5="(Todos los procesos)",COUNTIF('2. Valoración '!$AG$6:$AG$2261,$F19),COUNTIFS('2. Valoración '!$E$6:$E$2261,$C$5,'2. Valoración '!$AG$6:$AG$2261,$F19))
B20: [HW] Equipamiento informático (hardware) | C20: =IF($C$5="(Todos los procesos)",COUNTIF(MgTipo,$B20),COUNTIFS('1. Matriz de Activos'!$G$6:$G$239,$C$5,MgTipo,$B20)) | D20: =IF($C$5="(Todos los procesos)",COUNTIFS(MgTipo,$B20,MgValorAct,">=4"),COUNTIFS('1. Matriz de Activos'!$G$6:$G$239,$C$5,MgTipo,$B20,MgValorAct,">=4"))
B21: [COM] Redes de comunicaciones | C21: =IF($C$5="(Todos los procesos)",COUNTIF(MgTipo,$B21),COUNTIFS('1. Matriz de Activos'!$G$6:$G$239,$C$5,MgTipo,$B21)) | D21: =IF($C$5="(Todos los procesos)",COUNTIFS(MgTipo,$B21,MgValorAct,">=4"),COUNTIFS('1. Matriz de Activos'!$G$6:$G$239,$C$5,MgTipo,$B21,MgValorAct,">=4"))
B22: [Media] Soportes de información | C22: =IF($C$5="(Todos los procesos)",COUNTIF(MgTipo,$B22),COUNTIFS('1. Matriz de Activos'!$G$6:$G$239,$C$5,MgTipo,$B22)) | D22: =IF($C$5="(Todos los procesos)",COUNTIFS(MgTipo,$B22,MgValorAct,">=4"),COUNTIFS('1. Matriz de Activos'!$G$6:$G$239,$C$5,MgTipo,$B22,MgValorAct,">=4"))
B23: [AUX] Equipamiento auxiliar | C23: =IF($C$5="(Todos los procesos)",COUNTIF(MgTipo,$B23),COUNTIFS('1. Matriz de Activos'!$G$6:$G$239,$C$5,MgTipo,$B23)) | D23: =IF($C$5="(Todos los procesos)",COUNTIFS(MgTipo,$B23,MgValorAct,">=4"),COUNTIFS('1. Matriz de Activos'!$G$6:$G$239,$C$5,MgTipo,$B23,MgValorAct,">=4"))
B24: [L] Instalaciones | C24: =IF($C$5="(Todos los procesos)",COUNTIF(MgTipo,$B24),COUNTIFS('1. Matriz de Activos'!$G$6:$G$239,$C$5,MgTipo,$B24)) | D24: =IF($C$5="(Todos los procesos)",COUNTIFS(MgTipo,$B24,MgValorAct,">=4"),COUNTIFS('1. Matriz de Activos'!$G$6:$G$239,$C$5,MgTipo,$B24,MgValorAct,">=4"))
B25: [P] Personal | C25: =IF($C$5="(Todos los procesos)",COUNTIF(MgTipo,$B25),COUNTIFS('1. Matriz de Activos'!$G$6:$G$239,$C$5,MgTipo,$B25)) | D25: =IF($C$5="(Todos los procesos)",COUNTIFS(MgTipo,$B25,MgValorAct,">=4"),COUNTIFS('1. Matriz de Activos'!$G$6:$G$239,$C$5,MgTipo,$B25,MgValorAct,">=4"))
B28: RIESGOS POR GRUPO DE AMENAZA | F28: MADUREZ DE LOS CONTROLES REGISTRADA
B29: Grupo MAGERIT | C29: Riesgos | D29: Alto o Crítico | F29: Nivel de madurez | G29: Riesgos
B30: [A] Ataques intencionados | C30: =IF($C$5="(Todos los procesos)",COUNTIF('2. Valoración '!$J$6:$J$2261,$B30),COUNTIFS('2. Valoración '!$E$6:$E$2261,$C$5,'2. Valoración '!$J$6:$J$2261,$B30)) | D30: =IF($C$5="(Todos los procesos)",COUNTIFS('2. Valoración '!$J$6:$J$2261,$B30,'2. Valoración '!$Z$6:$Z$2261,"Alto")+COUNTIFS('2. Valoración '!$J$6:$J$2261,$B30,'2. Valoración '!$Z$6:$Z$2261,"Crítico"),COUNTIFS('2. Valoración '!$E$6:$E$2261,$C$5,'2. Valoración '!$J$6:$J$2261,$B30,'2. Valoración '!$Z$6:$Z$2261,"Alto")+COUNTIFS('2. Valoración '!$E$6:$E$2261,$C$5,'2. Valoración '!$J$6:$J$2261,$B30,'2. Valoración '!$Z$6:$Z$2261,"Crítico")) | F30: L0 — Inexistente | G30: =IF($C$5="(Todos los procesos)",COUNTIF('2. Valoración '!$AC$6:$AC$2261,$F30),COUNTIFS('2. Valoración '!$E$6:$E$2261,$C$5,'2. Valoración '!$AC$6:$AC$2261,$F30))
B31: [E] Errores y fallos no intencionados | C31: =IF($C$5="(Todos los procesos)",COUNTIF('2. Valoración '!$J$6:$J$2261,$B31),COUNTIFS('2. Valoración '!$E$6:$E$2261,$C$5,'2. Valoración '!$J$6:$J$2261,$B31)) | D31: =IF($C$5="(Todos los procesos)",COUNTIFS('2. Valoración '!$J$6:$J$2261,$B31,'2. Valoración '!$Z$6:$Z$2261,"Alto")+COUNTIFS('2. Valoración '!$J$6:$J$2261,$B31,'2. Valoración '!$Z$6:$Z$2261,"Crítico"),COUNTIFS('2. Valoración '!$E$6:$E$2261,$C$5,'2. Valoración '!$J$6:$J$2261,$B31,'2. Valoración '!$Z$6:$Z$2261,"Alto")+COUNTIFS('2. Valoración '!$E$6:$E$2261,$C$5,'2. Valoración '!$J$6:$J$2261,$B31,'2. Valoración '!$Z$6:$Z$2261,"Crítico")) | F31: L1 — Inicial / ad hoc | G31: =IF($C$5="(Todos los procesos)",COUNTIF('2. Valoración '!$AC$6:$AC$2261,$F31),COUNTIFS('2. Valoración '!$E$6:$E$2261,$C$5,'2. Valoración '!$AC$6:$AC$2261,$F31))
B32: [I] De origen industrial | C32: =IF($C$5="(Todos los procesos)",COUNTIF('2. Valoración '!$J$6:$J$2261,$B32),COUNTIFS('2. Valoración '!$E$6:$E$2261,$C$5,'2. Valoración '!$J$6:$J$2261,$B32)) | D32: =IF($C$5="(Todos los procesos)",COUNTIFS('2. Valoración '!$J$6:$J$2261,$B32,'2. Valoración '!$Z$6:$Z$2261,"Alto")+COUNTIFS('2. Valoración '!$J$6:$J$2261,$B32,'2. Valoración '!$Z$6:$Z$2261,"Crítico"),COUNTIFS('2. Valoración '!$E$6:$E$2261,$C$5,'2. Valoración '!$J$6:$J$2261,$B32,'2. Valoración '!$Z$6:$Z$2261,"Alto")+COUNTIFS('2. Valoración '!$E$6:$E$2261,$C$5,'2. Valoración '!$J$6:$J$2261,$B32,'2. Valoración '!$Z$6:$Z$2261,"Crítico")) | F32: L2 — Reproducible pero intuitivo | G32: =IF($C$5="(Todos los procesos)",COUNTIF('2. Valoración '!$AC$6:$AC$2261,$F32),COUNTIFS('2. Valoración '!$E$6:$E$2261,$C$5,'2. Valoración '!$AC$6:$AC$2261,$F32))
B33: [N] Desastres naturales | C33: =IF($C$5="(Todos los procesos)",COUNTIF('2. Valoración '!$J$6:$J$2261,$B33),COUNTIFS('2. Valoración '!$E$6:$E$2261,$C$5,'2. Valoración '!$J$6:$J$2261,$B33)) | D33: =IF($C$5="(Todos los procesos)",COUNTIFS('2. Valoración '!$J$6:$J$2261,$B33,'2. Valoración '!$Z$6:$Z$2261,"Alto")+COUNTIFS('2. Valoración '!$J$6:$J$2261,$B33,'2. Valoración '!$Z$6:$Z$2261,"Crítico"),COUNTIFS('2. Valoración '!$E$6:$E$2261,$C$5,'2. Valoración '!$J$6:$J$2261,$B33,'2. Valoración '!$Z$6:$Z$2261,"Alto")+COUNTIFS('2. Valoración '!$E$6:$E$2261,$C$5,'2. Valoración '!$J$6:$J$2261,$B33,'2. Valoración '!$Z$6:$Z$2261,"Crítico")) | F33: L3 — Proceso definido | G33: =IF($C$5="(Todos los procesos)",COUNTIF('2. Valoración '!$AC$6:$AC$2261,$F33),COUNTIFS('2. Valoración '!$E$6:$E$2261,$C$5,'2. Valoración '!$AC$6:$AC$2261,$F33))
F34: L4 — Gestionado y medible | G34: =IF($C$5="(Todos los procesos)",COUNTIF('2. Valoración '!$AC$6:$AC$2261,$F34),COUNTIFS('2. Valoración '!$E$6:$E$2261,$C$5,'2. Valoración '!$AC$6:$AC$2261,$F34))
F35: L5 — Optimizado | G35: =IF($C$5="(Todos los procesos)",COUNTIF('2. Valoración '!$AC$6:$AC$2261,$F35),COUNTIFS('2. Valoración '!$E$6:$E$2261,$C$5,'2. Valoración '!$AC$6:$AC$2261,$F35))
B38: AMENAZAS CON MÁS RIESGOS ALTO O CRÍTICO EN EL PROCESO SELECCIONADO
B39: Código | C39: Amenaza | D39: Riesgos Alto o Crítico | E39: Riesgos totales
B40: =IFERROR(INDEX('Amenazas MAGERIT'!$B$6:$B$62,MATCH(LARGE(RankProc,1),RankProc,0)),"") | C40: =IFERROR(INDEX('Amenazas MAGERIT'!$C$6:$C$62,MATCH(LARGE(RankProc,1),RankProc,0)),"") | D40: =IFERROR(INT(LARGE(RankProc,1)),"") | E40: =IFERROR(INDEX(TotProc,MATCH(LARGE(RankProc,1),RankProc,0)),"")
B41: =IFERROR(INDEX('Amenazas MAGERIT'!$B$6:$B$62,MATCH(LARGE(RankProc,2),RankProc,0)),"") | C41: =IFERROR(INDEX('Amenazas MAGERIT'!$C$6:$C$62,MATCH(LARGE(RankProc,2),RankProc,0)),"") | D41: =IFERROR(INT(LARGE(RankProc,2)),"") | E41: =IFERROR(INDEX(TotProc,MATCH(LARGE(RankProc,2),RankProc,0)),"")
B42: =IFERROR(INDEX('Amenazas MAGERIT'!$B$6:$B$62,MATCH(LARGE(RankProc,3),RankProc,0)),"") | C42: =IFERROR(INDEX('Amenazas MAGERIT'!$C$6:$C$62,MATCH(LARGE(RankProc,3),RankProc,0)),"") | D42: =IFERROR(INT(LARGE(RankProc,3)),"") | E42: =IFERROR(INDEX(TotProc,MATCH(LARGE(RankProc,3),RankProc,0)),"")
B43: =IFERROR(INDEX('Amenazas MAGERIT'!$B$6:$B$62,MATCH(LARGE(RankProc,4),RankProc,0)),"") | C43: =IFERROR(INDEX('Amenazas MAGERIT'!$C$6:$C$62,MATCH(LARGE(RankProc,4),RankProc,0)),"") | D43: =IFERROR(INT(LARGE(RankProc,4)),"") | E43: =IFERROR(INDEX(TotProc,MATCH(LARGE(RankProc,4),RankProc,0)),"")
B44: =IFERROR(INDEX('Amenazas MAGERIT'!$B$6:$B$62,MATCH(LARGE(RankProc,5),RankProc,0)),"") | C44: =IFERROR(INDEX('Amenazas MAGERIT'!$C$6:$C$62,MATCH(LARGE(RankProc,5),RankProc,0)),"") | D44: =IFERROR(INT(LARGE(RankProc,5)),"") | E44: =IFERROR(INDEX(TotProc,MATCH(LARGE(RankProc,5),RankProc,0)),"")
B45: =IFERROR(INDEX('Amenazas MAGERIT'!$B$6:$B$62,MATCH(LARGE(RankProc,6),RankProc,0)),"") | C45: =IFERROR(INDEX('Amenazas MAGERIT'!$C$6:$C$62,MATCH(LARGE(RankProc,6),RankProc,0)),"") | D45: =IFERROR(INT(LARGE(RankProc,6)),"") | E45: =IFERROR(INDEX(TotProc,MATCH(LARGE(RankProc,6),RankProc,0)),"")
B46: =IFERROR(INDEX('Amenazas MAGERIT'!$B$6:$B$62,MATCH(LARGE(RankProc,7),RankProc,0)),"") | C46: =IFERROR(INDEX('Amenazas MAGERIT'!$C$6:$C$62,MATCH(LARGE(RankProc,7),RankProc,0)),"") | D46: =IFERROR(INT(LARGE(RankProc,7)),"") | E46: =IFERROR(INDEX(TotProc,MATCH(LARGE(RankProc,7),RankProc,0)),"")
B47: =IFERROR(INDEX('Amenazas MAGERIT'!$B$6:$B$62,MATCH(LARGE(RankProc,8),RankProc,0)),"") | C47: =IFERROR(INDEX('Amenazas MAGERIT'!$C$6:$C$62,MATCH(LARGE(RankProc,8),RankProc,0)),"") | D47: =IFERROR(INT(LARGE(RankProc,8)),"") | E47: =IFERROR(INDEX(TotProc,MATCH(LARGE(RankProc,8),RankProc,0)),"")
B48: =IFERROR(INDEX('Amenazas MAGERIT'!$B$6:$B$62,MATCH(LARGE(RankProc,9),RankProc,0)),"") | C48: =IFERROR(INDEX('Amenazas MAGERIT'!$C$6:$C$62,MATCH(LARGE(RankProc,9),RankProc,0)),"") | D48: =IFERROR(INT(LARGE(RankProc,9)),"") | E48: =IFERROR(INDEX(TotProc,MATCH(LARGE(RankProc,9),RankProc,0)),"")
B49: =IFERROR(INDEX('Amenazas MAGERIT'!$B$6:$B$62,MATCH(LARGE(RankProc,10),RankProc,0)),"") | C49: =IFERROR(INDEX('Amenazas MAGERIT'!$C$6:$C$62,MATCH(LARGE(RankProc,10),RankProc,0)),"") | D49: =IFERROR(INT(LARGE(RankProc,10)),"") | E49: =IFERROR(INDEX(TotProc,MATCH(LARGE(RankProc,10),RankProc,0)),"")
B69: Todos los indicadores se recalculan al cambiar el proceso en la celda amarilla. Fuentes: MAGERIT v3.0 e ISO/IEC 27001:2022 Anexo A.

Sheet Guía de uso
B1: ANÁLISIS DE RIESGOS SEGÚN MAGERIT v3.0 — GUÍA DE USO
B2: Cuántico adopta MAGERIT de manera integral. Esta hoja explica para qué sirve cada hoja y en qué orden se trabaja.
B3: Código de color: | C3: Amarillo = Campo de entrada — se selecciona de una lista | E3: Lila = Calculado automáticamente — no escribir encima | G3: Gris = Dato de la norma MAGERIT — no modificar
B5: QUÉ CONTIENE ESTE ARCHIVO
B6: Hoja | C6: Para qué sirve | D6: Su papel
B7: Dashboard | C7: Indicadores de riesgo filtrables por proceso. Es la vista de arranque y la que se lleva al Comité. | D7: Ver
B8: Matriz de Activos MAGERIT | C8: El inventario: 234 activos clasificados por tipo MAGERIT y valorados en las tres dimensiones. | D8: Diligenciar
B9: Agregar Activo | C9: Muestra qué activos faltan por valorar y genera, listas para copiar, las filas que hay que crear en la Valoración. | D9: Usar
B10: Valoración MAGERIT | C10: La evaluación de riesgos: impacto por dimensión, riesgo anual y riesgo residual según la madurez de los controles. | D10: Diligenciar
B11: Matrices de Riesgo | C11: Los mapas de calor inherente y residual, con el recuento por nivel. | D11: Ver
B12: Amenazas MAGERIT | C12: Las 57 amenazas con los tipos de activo y dimensiones que la norma les asigna. Aquí se ajusta la degradación y la frecuencia. | D12: Diligenciar
B13: Tipos de Activo MAGERIT | C13: Los 10 tipos y 137 subtipos oficiales, con la cantidad de activos que hay en cada uno. | D13: Referencia
B14: Escalas MAGERIT | C14: Todas las listas y reglas de cálculo. Cambiar un valor aquí recalcula la valoración entera. | D14: Parámetros
B15: Listas | C15: Alimenta los desplegables. No se modifica sin autorización. | D15: Apoyo
B16: Comparativa de Modelos | C16: Registro de la comparación entre el modelo anterior y MAGERIT. Sustenta la decisión ante el auditor. | D16: Evidencia
B18: EN QUÉ ORDEN SE TRABAJA
B19: Paso | C19: Qué se hace
B20: 1 · Mantener el inventario | C20: En «Matriz de Activos MAGERIT» se registra cada activo nuevo, se clasifica con los desplegables de tipo y subtipo, se completan sus atributos y se valora en Disponibilidad, Integridad y Confidencialidad. El valor del activo se calcula solo.
B21: 2 · Ver qué falta por valorar | C21: En «Agregar Activo» se filtra por proceso, tipo y subtipo. La columna «Situación» dice si a cada activo le faltan filas en la Valoración y cuántas.
B22: 3 · Crear las filas de riesgo | C22: En el bloque 3 de esa misma hoja se elige el activo, se filtra «¿Aplica?» por «Sí» y se copian las filas a «Valoración MAGERIT».
B23: 4 · Ajustar degradación y frecuencia | C23: Se hace en «Amenazas MAGERIT», no fila por fila: lo que se cambie ahí se propaga a todos los riesgos de esa amenaza.
B24: 5 · Registrar la madurez de los controles | C24: En «Valoración MAGERIT», columna amarilla. Es lo único que separa el riesgo residual del inherente.
B25: 6 · Revisar y decidir | C25: El Dashboard y las Matrices de Riesgo dan la lectura por proceso y el mapa de calor para llevar al Comité.
B27: RESUMEN NUMÉRICO
B28: Activos inventariados | C28: Tipos MAGERIT en uso | D28: Amenazas del catálogo | E28: Activos valorados | F28: Riesgos evaluados
B29: 234 | C29: 7 | D29: 57 | E29: 122 | F29: 2256
B31: Fuentes: MAGERIT v3.0, Libro I «Método» y Libro II «Catálogo de Elementos» (Ministerio de Hacienda y Administraciones Públicas de España, octubre de 2012), e ISO/IEC 27001:2022 Anexo A.
B33: Novedad de esta versión: la eficacia que reduce el riesgo residual ya no se escribe riesgo por riesgo. Sale de la madurez real de los controles registrada en la hoja «4. Controles y Madurez»: cada amenaza toma la eficacia media de los controles que la mitigan. La columna de madurez en la hoja de Valoración queda como sobrescritura manual para casos puntuales.

Sheet 1. Matriz de Activos
B1: MATRIZ DE ACTIVOS — ESTRUCTURA MAGERIT v3.0
B2: Inventario reorganizado por tipo MAGERIT y valorado en Disponibilidad, Integridad y Confidencialidad (escala 0 a 5).
B3: Código de color: | C3: Amarillo = Campo de entrada — se selecciona de una lista | E3: Lila = Calculado automáticamente — no escribir encima | G3: Gris = Dato de la norma MAGERIT — no modificar
B5: Código | C5: Nombre del activo | D5: Descripción | E5: Tipo | F5: Subtipo | G5: Proceso o Área | H5: Responsable (custodio) | I5: Propietario del activo | J5: Ubicación | K5: Entorno | L5: ¿Contiene datos de cliente? | M5: ¿Contiene datos personales (Ley 1581)? | N5: ¿Está expuesto a Internet? | O5: Proveedor o subencargado | P5: Depende del activo superior | Q5: Valor en Disponibilidad | R5: Valor en Integridad | S5: Valor en Confidencialidad | T5: Valor del activo (0 a 5) | U5: Nivel del activo
B6: TEC-008 | C6: Backups-Diarios | E6: [D] Datos / Información | F6: [backup] Copias de respaldo | G6: Gestión Tecnológica | H6: Gestión Tecnológica | J6: Nube | K6: No aplica | L6: Por definir | M6: Por definir | N6: Por definir | O6: Amazon Web Services | Q6: 3 — Medio | R6: 4 — Alto | S6: 4 — Alto | T6: =MAX(IFERROR(VLOOKUP(Q6,MgValor,2,0),0),IFERROR(VLOOKUP(R6,MgValor,2,0),0),IFERROR(VLOOKUP(S6,MgValor,2,0),0)) | U6: =IFERROR(LOOKUP(T6,{0;1;2;3;4;5},{"Irrelevante";"Muy Bajo";"Bajo";"Medio";"Alto";"Muy Alto"}),"")
B7: GH-057 | C7: rpa-impoconsumo-releases | D7: Repositorio de releases (paquetes y versiones distribuibles) de la aplicación Impoconsumo ILC | E7: [D] Datos / Información | F7: [exe] Código ejecutable | G7: Gestión Tecnológica | H7: Jhon Tamayo | J7: Nube | K7: No aplica | L7: Por definir | M7: Por definir | N7: Por definir | Q7: 3 — Medio | R7: 4 — Alto | S7: 4 — Alto | T7: =MAX(IFERROR(VLOOKUP(Q7,MgValor,2,0),0),IFERROR(VLOOKUP(R7,MgValor,2,0),0),IFERROR(VLOOKUP(S7,MgValor,2,0),0)) | U7: =IFERROR(LOOKUP(T7,{0;1;2;3;4;5},{"Irrelevante";"Muy Bajo";"Bajo";"Medio";"Alto";"Muy Alto"}),"")
B8: TAL-11 | C8: Actas de descargos / procesos disciplinarios | D8: Registro de llamados de atención y procesos disciplinarios | E8: [D] Datos / Información | F8: [files] Archivos | G8: Talento Humano | H8: Finance and Administrative Manager | J8: Nube | K8: No aplica | L8: Por definir | M8: Por definir | N8: Por definir | Q8: 3 — Medio | R8: 4 — Alto | S8: 4 — Alto | T8: =MAX(IFERROR(VLOOKUP(Q8,MgValor,2,0),0),IFERROR(VLOOKUP(R8,MgValor,2,0),0),IFERROR(VLOOKUP(S8,MgValor,2,0),0)) | U8: =IFERROR(LOOKUP(T8,{0;1;2;3;4;5},{"Irrelevante";"Muy Bajo";"Bajo";"Medio";"Alto";"Muy Alto"}),"")
B9: COM-16 | C9: Base de datos de prospectos de MinTrace | D9: Repositorio que contiene la información comercial y de contacto de empresas y personas potencialmente interesadas en los productos y servicios de MinTrace. | E9: [D] Datos / Información | F9: [files] Archivos | G9: Gestión Comercial | H9: Chief Commercial Officer | J9: N.A. | K9: No aplica | L9: Sí | M9: Por definir | N9: Por definir | Q9: 3 — Medio | R9: 4 — Alto | S9: 4 — Alto | T9: =MAX(IFERROR(VLOOKUP(Q9,MgValor,2,0),0),IFERROR(VLOOKUP(R9,MgValor,2,0),0),IFERROR(VLOOKUP(S9,MgValor,2,0),0)) | U9: =IFERROR(LOOKUP(T9,{0;1;2;3;4;5},{"Irrelevante";"Muy Bajo";"Bajo";"Medio";"Alto";"Muy Alto"}),"")
B10: COM-21 | C10: Capacitaciones | D10: Repositorio que contiene los materiales de formación utilizados para entrenar a los nuevos integrantes del equipo comercial en el portafolio de soluciones de Cuantico, los procesos comerciales, las metodologías de venta, el uso de herramientas y demás lineamientos necesarios para el desarrollo de sus funciones. | E10: [D] Datos / Información | F10: [files] Archivos | G10: Gestión Comercial | H10: Chief Commercial Officer | J10: N.A. | K10: Desarrollo | L10: Por definir | M10: Por definir | N10: Por definir | Q10: 3 — Medio | R10: 4 — Alto | S10: 4 — Alto | T10: =MAX(IFERROR(VLOOKUP(Q10,MgValor,2,0),0),IFERROR(VLOOKUP(R10,MgValor,2,0),0),IFERROR(VLOOKUP(S10,MgValor,2,0),0)) | U10: =IFERROR(LOOKUP(T10,{0;1;2;3;4;5},{"Irrelevante";"Muy Bajo";"Bajo";"Medio";"Alto";"Muy Alto"}),"")
B11: TAL-13 | C11: Carpeta de desvinculación | D11: Renuncia/terminación, paz y salvo, liquidación, certificaciones | E11: [D] Datos / Información | F11: [files] Archivos | G11: Talento Humano | H11: Finance and Administrative Manager | J11: Nube | K11: No aplica | L11: Por definir | M11: Sí | N11: Por definir | Q11: 3 — Medio | R11: 4 — Alto | S11: 4 — Alto | T11: =MAX(IFERROR(VLOOKUP(Q11,MgValor,2,0),0),IFERROR(VLOOKUP(R11,MgValor,2,0),0),IFERROR(VLOOKUP(S11,MgValor,2,0),0)) | U11: =IFERROR(LOOKUP(T11,{0;1;2;3;4;5},{"Irrelevante";"Muy Bajo";"Bajo";"Medio";"Alto";"Muy Alto"}),"")
B12: TAL-12 | C12: Carpeta de ingreso de colaborador | D12: RUT, hoja de vida, cédula, EPS, AFP, fondo de cesantías, certificados | E12: [D] Datos / Información | F12: [files] Archivos | G12: Talento Humano | H12: Finance and Administrative Manager | J12: Nube | K12: No aplica | L12: Por definir | M12: Sí | N12: Por definir | Q12: 3 — Medio | R12: 4 — Alto | S12: 4 — Alto | T12: =MAX(IFERROR(VLOOKUP(Q12,MgValor,2,0),0),IFERROR(VLOOKUP(R12,MgValor,2,0),0),IFERROR(VLOOKUP(S12,MgValor,2,0),0)) | U12: =IFERROR(LOOKUP(T12,{0;1;2;3;4;5},{"Irrelevante";"Muy Bajo";"Bajo";"Medio";"Alto";"Muy Alto"}),"")
B13: FIN-06 | C13: Consolidado control financiero Egresos (FOR-FIN-03) | D13: Registro y control de egresos y pagos | E13: [D] Datos / Información | F13: [files] Archivos | G13: Gestión Financiera | H13: Finance and Administrative Manager | J13: Nube | K13: No aplica | L13: Por definir | M13: Por definir | N13: Por definir | Q13: 3 — Medio | R13: 4 — Alto | S13: 4 — Alto | T13: =MAX(IFERROR(VLOOKUP(Q13,MgValor,2,0),0),IFERROR(VLOOKUP(R13,MgValor,2,0),0),IFERROR(VLOOKUP(S13,MgValor,2,0),0)) | U13: =IFERROR(LOOKUP(T13,{0;1;2;3;4;5},{"Irrelevante";"Muy Bajo";"Bajo";"Medio";"Alto";"Muy Alto"}),"")
B14: FIN-07 | C14: Consolidado control financiero Ingresos (FOR-FIN-05) | D14: Registro y control de ingresos y facturación | E14: [D] Datos / Información | F14: [files] Archivos | G14: Gestión Financiera | H14: Finance and Administrative Manager | J14: Nube | K14: No aplica | L14: Por definir | M14: Por definir | N14: Por definir | Q14: 3 — Medio | R14: 4 — Alto | S14: 4 — Alto | T14: =MAX(IFERROR(VLOOKUP(Q14,MgValor,2,0),0),IFERROR(VLOOKUP(R14,MgValor,2,0),0),IFERROR(VLOOKUP(S14,MgValor,2,0),0)) | U14: =IFERROR(LOOKUP(T14,{0;1;2;3;4;5},{"Irrelevante";"Muy Bajo";"Bajo";"Medio";"Alto";"Muy Alto"}),"")
B15: LCO-08 | C15: Documentación de contratistas (hojas de vida, cédula, RUT, certificaciones) | D15: Documentos de identificación y soporte contractual de contratistas personas naturales | E15: [D] Datos / Información | F15: [files] Archivos | G15: Gestión Legal y Compras | H15: Chief Legal Officer | J15: Nube | K15: No aplica | L15: Por definir | M15: Sí | N15: Por definir | Q15: 3 — Medio | R15: 3 — Medio | S15: 4 — Alto | T15: =MAX(IFERROR(VLOOKUP(Q15,MgValor,2,0),0),IFERROR(VLOOKUP(R15,MgValor,2,0),0),IFERROR(VLOOKUP(S15,MgValor,2,0),0)) | U15: =IFERROR(LOOKUP(T15,{0;1;2;3;4;5},{"Irrelevante";"Muy Bajo";"Bajo";"Medio";"Alto";"Muy Alto"}),"")
B16: COM-18 | C16: Equipo de Trabajo | D16: Repositorio consolidado con la información de funcionarios y proveedores de Cuantico, organizada en el formato de hoja de vida corporativa. Se utiliza para validar perfiles, experiencia, formación y cumplimiento de requisitos en procesos de contratación y licitaciones. | E16: [D] Datos / Información | F16: [files] Archivos | G16: Gestión Comercial | H16: Chief Commercial Officer | J16: N.A. | K16: No aplica | L16: Por definir | M16: Sí | N16: Por definir | Q16: 3 — Medio | R16: 4 — Alto | S16: 4 — Alto | T16: =MAX(IFERROR(VLOOKUP(Q16,MgValor,2,0),0),IFERROR(VLOOKUP(R16,MgValor,2,0),0),IFERROR(VLOOKUP(S16,MgValor,2,0),0)) | U16: =IFERROR(LOOKUP(T16,{0;1;2;3;4;5},{"Irrelevante";"Muy Bajo";"Bajo";"Medio";"Alto";"Muy Alto"}),"")
B17: COM-19 | C17: Experiencia | D17: Repositorio que consolida las certificaciones de los clientes, contratos y proyectos en los que ha participado Cuantico, incluyendo las experiencias registradas en el RUP. Se utiliza para acreditar la trayectoria de la empresa y validar el cumplimiento de requisitos de experiencia en procesos de contratación y licitaciones. | E17: [D] Datos / Información | F17: [files] Archivos | G17: Gestión Comercial | H17: Chief Commercial Officer | J17: N.A. | K17: No aplica | L17: Sí | M17: Por definir | N17: Por definir | Q17: 3 — Medio | R17: 4 — Alto | S17: 4 — Alto | T17: =MAX(IFERROR(VLOOKUP(Q17,MgValor,2,0),0),IFERROR(VLOOKUP(R17,MgValor,2,0),0),IFERROR(VLOOKUP(S17,MgValor,2,0),0)) | U17: =IFERROR(LOOKUP(T17,{0;1;2;3;4;5},{"Irrelevante";"Muy Bajo";"Bajo";"Medio";"Alto";"Muy Alto"}),"")
B18: COM-05 | C18: Forecast (FOR-COM-01) | D18: Proyección y seguimiento de oportunidades y ventas | E18: [D] Datos / Información | F18: [files] Archivos | G18: Gestión Comercial | H18: Chief Commercial Officer | J18: Nube | K18: No aplica | L18: Por definir | M18: Por definir | N18: Por definir | Q18: 3 — Medio | R18: 4 — Alto | S18: 4 — Alto | T18: =MAX(IFERROR(VLOOKUP(Q18,MgValor,2,0),0),IFERROR(VLOOKUP(R18,MgValor,2,0),0),IFERROR(VLOOKUP(S18,MgValor,2,0),0)) | U18: =IFERROR(LOOKUP(T18,{0;1;2;3;4;5},{"Irrelevante";"Muy Bajo";"Bajo";"Medio";"Alto";"Muy Alto"}),"")
... B115: FIN-27 | C115: Facturación electrónica DIAN / RADIAN | D115: Emisión/recepción de facturas electrónicas vía Siigo | E115: [S] Servicios | F115: [ext] A usuarios externos bajo una relación contractual | G115: Gestión Financiera | H115: Gestión Tecnológica | J115: Nube | K115: Producción | L115: Por definir | M115: Por definir | N115: Por definir | Q115: 4 — Alto | R115: 4 — Alto | S115: 3 — Medio | T115: =MAX(IFERROR(VLOOKUP(Q115,MgValor,2,0),0),IFERROR(VLOOKUP(R115,MgValor,2,0),0),IFERROR(VLOOKUP(S115,MgValor,2,0),0)) | U115: =IFERROR(LOOKUP(T115,{0;1;2;3;4;5},{"Irrelevante";"Muy Bajo";"Bajo";"Medio";"Alto";"Muy Alto"}),"")
B116: TEC-014 | C116: Hosting-Web | E116: [S] Servicios | F116: [ext] A usuarios externos bajo una relación contractual | G116: Gestión Tecnológica | H116: Gestión Tecnológica | J116: Nube | K116: Producción | L116: Por definir | M116: Por definir | N116: Por definir | Q116: 4 — Alto | R116: 3 — Medio | S116: 2 — Bajo | T116: =MAX(IFERROR(VLOOKUP(Q116,MgValor,2,0),0),IFERROR(VLOOKUP(R116,MgValor,2,0),0),IFERROR(VLOOKUP(S116,MgValor,2,0),0)) | U116: =IFERROR(LOOKUP(T116,{0;1;2;3;4;5},{"Irrelevante";"Muy Bajo";"Bajo";"Medio";"Alto";"Muy Alto"}),"")
B117: MS-02 | C117: Microsoft 365 Business Standard | D117: Suite de ofimática y colaboración (Office, Teams, OneDrive) | E117: [S] Servicios | F117: [ext] A usuarios externos bajo una relación contractual | G117: Gestión Tecnológica | H117: Gestión Tecnológica | J117: Nube | K117: Producción | L117: Por definir | M117: Por definir | N117: Por definir | Q117: 4 — Alto | R117: 4 — Alto | S117: 4 — Alto | T117: =MAX(IFERROR(VLOOKUP(Q117,MgValor,2,0),0),IFERROR(VLOOKUP(R117,MgValor,2,0),0),IFERROR(VLOOKUP(S117,MgValor,2,0),0)) | U117: =IFERROR(LOOKUP(T117,{0;1;2;3;4;5},{"Irrelevante";"Muy Bajo";"Bajo";"Medio";"Alto";"Muy Alto"}),"")
B118: FIN-28 | C118: Plataforma de seguridad social (PILA) | D118: Liquidación y pago de aportes de seguridad social | E118: [S] Servicios | F118: [ext] A usuarios externos bajo una relación contractual | G118: Gestión Financiera | H118: Finance and Administrative Manager | J118: Nube | K118: Producción | L118: Por definir | M118: Por definir | N118: Por definir | Q118: 4 — Alto | R118: 4 — Alto | S118: 4 — Alto | T118: =MAX(IFERROR(VLOOKUP(Q118,MgValor,2,0),0),IFERROR(VLOOKUP(R118,MgValor,2,0),0),IFERROR(VLOOKUP(S118,MgValor,2,0),0)) | U118: =IFERROR(LOOKUP(T118,{0;1;2;3;4;5},{"Irrelevante";"Muy Bajo";"Bajo";"Medio";"Alto";"Muy Alto"}),"")
B119: FIN-23 | C119: Portal bancario (Innovaciencia) | D119: Portal bancario de la entidad Innovaciencia | E119: [S] Servicios | F119: [ext] A usuarios externos bajo una relación contractual | G119: Gestión Financiera | H119: Finance and Administrative Manager | J119: Nube | K119: Producción | L119: Por definir | M119: Por definir | N119: Por definir | Q119: 4 — Alto | R119: 4 — Alto | S119: 4 — Alto | T119: =MAX(IFERROR(VLOOKUP(Q119,MgValor,2,0),0),IFERROR(VLOOKUP(R119,MgValor,2,0),0),IFERROR(VLOOKUP(S119,MgValor,2,0),0)) | U119: =IFERROR(LOOKUP(T119,{0;1;2;3;4;5},{"Irrelevante";"Muy Bajo";"Bajo";"Medio";"Alto";"Muy Alto"}),"")
B120: FIN-22 | C120: Portal bancario Colpatria (Cuantico Corporation) | D120: Portal de tesorería: pagos a proveedores, impuestos y nómina | E120: [S] Servicios | F120: [ext] A usuarios externos bajo una relación contractual | G120: Gestión Financiera | H120: Finance and Administrative Manager | J120: Nube | K120: Producción | L120: Por definir | M120: Sí | N120: Por definir | Q120: 4 — Alto | R120: 4 — Alto | S120: 4 — Alto | T120: =MAX(IFERROR(VLOOKUP(Q120,MgValor,2,0),0),IFERROR(VLOOKUP(R120,MgValor,2,0),0),IFERROR(VLOOKUP(S120,MgValor,2,0),0)) | U120: =IFERROR(LOOKUP(T120,{0;1;2;3;4;5},{"Irrelevante";"Muy Bajo";"Bajo";"Medio";"Alto";"Muy Alto"}),"")
B121: FIN-24 | C121: Portal(es) bancario(s) — GovTech / otras entidades | D121: Portales bancarios de otras entidades del grupo | E121: [S] Servicios | F121: [ext] A usuarios externos bajo una relación contractual | G121: Gestión Financiera | H121: Finance and Administrative Manager | J121: Nube | K121: Producción | L121: Por definir | M121: Por definir | N121: Por definir | Q121: 4 — Alto | R121: 4 — Alto | S121: 4 — Alto | T121: =MAX(IFERROR(VLOOKUP(Q121,MgValor,2,0),0),IFERROR(VLOOKUP(R121,MgValor,2,0),0),IFERROR(VLOOKUP(S121,MgValor,2,0),0)) | U121: =IFERROR(LOOKUP(T121,{0;1;2;3;4;5},{"Irrelevante";"Muy Bajo";"Bajo";"Medio";"Alto";"Muy Alto"}),"")
B122: MS-03 | C122: Power BI Premium Per User Add-On | D122: Complemento de analítica y visualización de datos | E122: [S] Servicios | F122: [ext] A usuarios externos bajo una relación contractual | G122: Gestión Tecnológica | H122: Gestión Tecnológica | J122: Nube | K122: Producción | L122: Por definir | M122: Por definir | N122: Por definir | Q122: 3 — Medio | R122: 3 — Medio | S122: 4 — Alto | T122: =MAX(IFERROR(VLOOKUP(Q122,MgValor,2,0),0),IFERROR(VLOOKUP(R122,MgValor,2,0),0),IFERROR(VLOOKUP(S122,MgValor,2,0),0)) | U122: =IFERROR(LOOKUP(T122,{0;1;2;3;4;5},{"Irrelevante";"Muy Bajo";"Bajo";"Medio";"Alto";"Muy Alto"}),"")
B123: MS-04 | C123: Power BI Pro | D123: Licencia de analítica y publicación de tableros | E123: [S] Servicios | F123: [ext] A usuarios externos bajo una relación contractual | G123: Gestión Tecnológica | H123: Gestión Tecnológica | J123: Nube | K123: Producción | L123: Por definir | M123: Por definir | N123: Por definir | Q123: 3 — Medio | R123: 3 — Medio | S123: 4 — Alto | T123: =MAX(IFERROR(VLOOKUP(Q123,MgValor,2,0),0),IFERROR(VLOOKUP(R123,MgValor,2,0),0),IFERROR(VLOOKUP(S123,MgValor,2,0),0)) | U123: =IFERROR(LOOKUP(T123,{0;1;2;3;4;5},{"Irrelevante";"Muy Bajo";"Bajo";"Medio";"Alto";"Muy Alto"}),"")
B124: SW-01 | C124: Zohodesk | D124: Plataforma SaaS de mesa de ayuda y gestión de tickets de soporte | E124: [S] Servicios | F124: [ext] A usuarios externos bajo una relación contractual | G124: Gestión Tecnológica | H124: Gestión Tecnológica | J124: Nube | K124: Producción | L124: Por definir | M124: Por definir | N124: Por definir | Q124: 3 — Medio | R124: 3 — Medio | S124: 4 — Alto | T124: =MAX(IFERROR(VLOOKUP(Q124,MgValor,2,0),0),IFERROR(VLOOKUP(R124,MgValor,2,0),0),IFERROR(VLOOKUP(S124,MgValor,2,0),0)) | U124: =IFERROR(LOOKUP(T124,{0;1;2;3;4;5},{"Irrelevante";"Muy Bajo";"Bajo";"Medio";"Alto";"Muy Alto"}),"")
B125: FIN-26 | C125: Firma electrónica DIAN (por entidad) | D125: Certificados de firma para declaraciones y trámites DIAN | E125: [S] Servicios | F125: [int] Interno (a usuarios de la organización) | G125: Gestión Financiera | J125: Nube | K125: Producción | L125: Por definir | M125: Por definir | N125: Por definir | Q125: 4 — Alto | R125: 4 — Alto | S125: 4 — Alto | T125: =MAX(IFERROR(VLOOKUP(Q125,MgValor,2,0),0),IFERROR(VLOOKUP(R125,MgValor,2,0),0),IFERROR(VLOOKUP(S125,MgValor,2,0),0)) | U125: =IFERROR(LOOKUP(T125,{0;1;2;3;4;5},{"Irrelevante";"Muy Bajo";"Bajo";"Medio";"Alto";"Muy Alto"}),"")
B126: TEC-029 | C126: grafana-with-postgresql-stt1myj34… | E126: [S] Servicios | F126: [int] Interno (a usuarios de la organización) | G126: Gestión Tecnológica | H126: Gestión Tecnológica | J126: Nube | K126: Producción | L126: Por definir | M126: Por definir | N126: Por definir | Q126: 2 — Bajo | R126: 2 — Bajo | S126: 2 — Bajo | T126: =MAX(IFERROR(VLOOKUP(Q126,MgValor,2,0),0),IFERROR(VLOOKUP(R126,MgValor,2,0),0),IFERROR(VLOOKUP(S126,MgValor,2,0),0)) | U126: =IFERROR(LOOKUP(T126,{0;1;2;3;4;5},{"Irrelevante";"Muy Bajo";"Bajo";"Medio";"Alto";"Muy Alto"}),"")
B127: TEC-037 | C127: n8n-with-postgres-and-worker-o48w… | E127: [S] Servicios | F127: [int] Interno (a usuarios de la organización) | G127: Gestión Tecnológica | H127: Gestión Tecnológica | J127: Nube | K127: Producción | L127: Por definir | M127: Por definir | N127: Por definir | Q127: 3 — Medio | R127: 3 — Medio | S127: 3 — Medio | T127: =MAX(IFERROR(VLOOKUP(Q127,MgValor,2,0),0),IFERROR(VLOOKUP(R127,MgValor,2,0),0),IFERROR(VLOOKUP(S127,MgValor,2,0),0)) | U127: =IFERROR(LOOKUP(T127,{0;1;2;3;4;5},{"Irrelevante";"Muy Bajo";"Bajo";"Medio";"Alto";"Muy Alto"}),"")
B128: TEC-039 | C128: plane-q08s8ccksok44w8k4cs0ow0g | E128: [S] Servicios | F128: [int] Interno (a usuarios de la organización) | G128: Gestión Tecnológica | H128: Gestión Tecnológica | J128: Nube | K128: Producción | L128: Por definir | M128: Por definir | N128: Por definir | Q128: 3 — Medio | R128: 3 — Medio | S128: 3 — Medio | T128: =MAX(IFERROR(VLOOKUP(Q128,MgValor,2,0),0),IFERROR(VLOOKUP(R128,MgValor,2,0),0),IFERROR(VLOOKUP(S128,MgValor,2,0),0)) | U128: =IFERROR(LOOKUP(T128,{0;1;2;3;4;5},{"Irrelevante";"Muy Bajo";"Bajo";"Medio";"Alto";"Muy Alto"}),"")
B129: TEC-041 | C129: service-ucsoggg4w400swcskwsookkw | E129: [S] Servicios | F129: [int] Interno (a usuarios de la organización) | G129: Gestión Tecnológica | H129: Gestión Tecnológica | J129: Nube | K129: Producción | L129: Por definir | M129: Por definir | N129: Por definir | Q129: 3 — Medio | R129: 3 — Medio | S129: 3 — Medio | T129: =MAX(IFERROR(VLOOKUP(Q129,MgValor,2,0),0),IFERROR(VLOOKUP(R129,MgValor,2,0),0),IFERROR(VLOOKUP(S129,MgValor,2,0),0)) | U129: =IFERROR(LOOKUP(T129,{0;1;2;3;4;5},{"Irrelevante";"Muy Bajo";"Bajo";"Medio";"Alto";"Muy Alto"}),"")
B130: TEC-070 | C130: umami-vf22xvxrc2a08lc8nl6vmtyt | E130: [S] Servicios | F130: [int] Interno (a usuarios de la organización) | G130: Gestión Tecnológica | H130: Gestión Tecnológica | J130: Nube | K130: Producción | L130: Por definir | M130: Por definir | N130: Por definir | Q130: 3 — Medio | R130: 3 — Medio | S130: 3 — Medio | T130: =MAX(IFERROR(VLOOKUP(Q130,MgValor,2,0),0),IFERROR(VLOOKUP(R130,MgValor,2,0),0),IFERROR(VLOOKUP(S130,MgValor,2,0),0)) | U130: =IFERROR(LOOKUP(T130,{0;1;2;3;4;5},{"Irrelevante";"Muy Bajo";"Bajo";"Medio";"Alto";"Muy Alto"}),"")
B131: TEC-002 | C131: BD-Postgres-Main | E131: [SW] Aplicaciones (software) | F131: [dbms] Sistema de gestión de bases de datos | G131: Gestión Tecnológica | H131: Gestión Tecnológica | J131: Nube | K131: Producción | L131: Por definir | M131: Por definir | N131: Por definir | Q131: 4 — Alto | R131: 4 — Alto | S131: 4 — Alto | T131: =MAX(IFERROR(VLOOKUP(Q131,MgValor,2,0),0),IFERROR(VLOOKUP(R131,MgValor,2,0),0),IFERROR(VLOOKUP(S131,MgValor,2,0),0)) | U131: =IFERROR(LOOKUP(T131,{0;1;2;3;4;5},{"Irrelevante";"Muy Bajo";"Bajo";"Medio";"Alto";"Muy Alto"}),"")
B132: TEC-001 | C132: API-Gateway | E132: [SW] Aplicaciones (software) | F132: [prp] Desarrollo propio (in house) | G132: Gestión Tecnológica | H132: Gestión Tecnológica | J132: Nube | K132: Producción | L132: Por definir | M132: Por definir | N132: Por definir | Q132: 4 — Alto | R132: 4 — Alto | S132: 3 — Medio | T132: =MAX(IFERROR(VLOOKUP(Q132,MgValor,2,0),0),IFERROR(VLOOKUP(R132,MgValor,2,0),0),IFERROR(VLOOKUP(S132,MgValor,2,0),0)) | U132: =IFERROR(LOOKUP(T132,{0;1;2;3;4;5},{"Irrelevante";"Muy Bajo";"Bajo";"Medio";"Alto";"Muy Alto"}),"")
B133: COM-14 | C133: CRM comercial de MinTrace. | D133: Herramienta utilizada para registrar y gestionar prospectos, clientes, oportunidades comerciales, seguimientos, propuestas, negociaciones y cierres de venta de MinTrace. | E133: [SW] Aplicaciones (software) | F133: [prp] Desarrollo propio (in house) | G133: Gestión Comercial | H133: Chief Commercial Officer | J133: N.A. | K133: Producción | L133: Sí | M133: Por definir | N133: Por definir | Q133: 3 — Medio | R133: 4 — Alto | S133: 4 — Alto | T133: =MAX(IFERROR(VLOOKUP(Q133,MgValor,2,0),0),IFERROR(VLOOKUP(R133,MgValor,2,0),0),IFERROR(VLOOKUP(S133,MgValor,2,0),0)) | U133: =IFERROR(LOOKUP(T133,{0;1;2;3;4;5},{"Irrelevante";"Muy Bajo";"Bajo";"Medio";"Alto";"Muy Alto"}),"")
B134: COM-15 | C134: Cuantico Verify. | D134: Aplicación utilizada para realizar procesos de validación, debida diligencia, consulta en listas restrictivas y verificación de información de clientes, proveedores o terceros. | E134: [SW] Aplicaciones (software) | F134: [prp] Desarrollo propio (in house) | G134: Gestión Comercial | H134: Chief Commercial Officer | J134: N.A. | K134: Producción | L134: Sí | M134: Por definir | N134: Por definir | Q134: 3 — Medio | R134: 4 — Alto | S134: 4 — Alto | T134: =MAX(IFERROR(VLOOKUP(Q134,MgValor,2,0),0),IFERROR(VLOOKUP(R134,MgValor,2,0),0),IFERROR(VLOOKUP(S134,MgValor,2,0),0)) | U134: =IFERROR(LOOKUP(T134,{0;1;2;3;4;5},{"Irrelevante";"Muy Bajo";"Bajo";"Medio";"Alto";"Muy Alto"}),"")
B135: TEC-024 | C135: evolution-api-uehp2jesgnh7cfzl6sy… | E135: [SW] Aplicaciones (software) | F135: [prp] Desarrollo propio (in house) | G135: Gestión Tecnológica | H135: Gestión Tecnológica | J135: Nube | K135: Producción | L135: Por definir | M135: Por definir | N135: Por definir | Q135: 3 — Medio | R135: 3 — Medio | S135: 3 — Medio | T135: =MAX(IFERROR(VLOOKUP(Q135,MgValor,2,0),0),IFERROR(VLOOKUP(R135,MgValor,2,0),0),IFERROR(VLOOKUP(S135,MgValor,2,0),0)) | U135: =IFERROR(LOOKUP(T135,{0;1;2;3;4;5},{"Irrelevante";"Muy Bajo";"Bajo";"Medio";"Alto";"Muy Alto"}),"")
B136: TEC-025 | C136: gateway-admin-dev | E136: [SW] Aplicaciones (software) | F136: [prp] Desarrollo propio (in house) | G136: Gestión Tecnológica | H136: Gestión Tecnológica | J136: Nube | K136: Producción | L136: Por definir | M136: Por definir | N136: Por definir | Q136: 2 — Bajo | R136: 2 — Bajo | S136: 2 — Bajo | T136: =MAX(IFERROR(VLOOKUP(Q136,MgValor,2,0),0),IFERROR(VLOOKUP(R136,MgValor,2,0),0),IFERROR(VLOOKUP(S136,MgValor,2,0),0)) | U136: =IFERROR(LOOKUP(T136,{0;1;2;3;4;5},{"Irrelevante";"Muy Bajo";"Bajo";"Medio";"Alto";"Muy Alto"}),"")
B137: TEC-026 | C137: gateway-admin-staging | E137: [SW] Aplicaciones (software) | F137: [prp] Desarrollo propio (in house) | G137: Gestión Tecnológica | H137: Gestión Tecnológica | J137: Nube | K137: Staging | L137: Por definir | M137: Por definir | N137: Por definir | Q137: 2 — Bajo | R137: 2 — Bajo | S137: 2 — Bajo | T137: =MAX(IFERROR(VLOOKUP(Q137,MgValor,2,0),0),IFERROR(VLOOKUP(R137,MgValor,2,0),0),IFERROR(VLOOKUP(S137,MgValor,2,0),0)) | U137: =IFERROR(LOOKUP(T137,{0;1;2;3;4;5},{"Irrelevante";"Muy Bajo";"Bajo";"Medio";"Alto";"Muy Alto"}),"")
B138: TEC-027 | C138: gateway-api-dev | E138: [SW] Aplicaciones (software) | F138: [prp] Desarrollo propio (in house) | G138: Gestión Tecnológica | H138: Gestión Tecnológica | J138: Nube | K138: Producción | L138: Por definir | M138: Por definir | N138: Por definir | Q138: 2 — Bajo | R138: 2 — Bajo | S138: 2 — Bajo | T138: =MAX(IFERROR(VLOOKUP(Q138,MgValor,2,0),0),IFERROR(VLOOKUP(R138,MgValor,2,0),0),IFERROR(VLOOKUP(S138,MgValor,2,0),0)) | U138: =IFERROR(LOOKUP(T138,{0;1;2;3;4;5},{"Irrelevante";"Muy Bajo";"Bajo";"Medio";"Alto";"Muy Alto"}),"")
B139: TEC-028 | C139: gateway-api-staging | E139: [SW] Aplicaciones (software) | F139: [prp] Desarrollo propio (in house) | G139: Gestión Tecnológica | H139: Gestión Tecnológica | J139: Nube | K139: Staging | L139: Por definir | M139: Por definir | N139: Por definir | Q139: 2 — Bajo | R139: 2 — Bajo | S139: 2 — Bajo | T139: =MAX(IFERROR(VLOOKUP(Q139,MgValor,2,0),0),IFERROR(VLOOKUP(R139,MgValor,2,0),0),IFERROR(VLOOKUP(S139,MgValor,2,0),0)) | U139: =IFERROR(LOOKUP(T139,{0;1;2;3;4;5},{"Irrelevante";"Muy Bajo";"Bajo";"Medio";"Alto";"Muy Alto"}),"")
B140: TEC-032 | C140: monitor-agents | E140: [SW] Aplicaciones (software) | F140: [prp] Desarrollo propio (in house) | G140: Gestión Tecnológica | H140: Gestión Tecnológica | J140: Nube | K140: Producción | L140: Por definir | M140: Por definir | N140: Por definir | Q140: 2 — Bajo | R140: 2 — Bajo | S140: 2 — Bajo | T140: =MAX(IFERROR(VLOOKUP(Q140,MgValor,2,0),0),IFERROR(VLOOKUP(R140,MgValor,2,0),0),IFERROR(VLOOKUP(S140,MgValor,2,0),0)) | U140: =IFERROR(LOOKUP(T140,{0;1;2;3;4;5},{"Irrelevante";"Muy Bajo";"Bajo";"Medio";"Alto";"Muy Alto"}),"")
B141: TEC-033 | C141: monitor-api | E141: [SW] Aplicaciones (software) | F141: [prp] Desarrollo propio (in house) | G141: Gestión Tecnológica | H141: Gestión Tecnológica | J141: Nube | K141: Producción | L141: Por definir | M141: Por definir | N141: Por definir | Q141: 2 — Bajo | R141: 2 — Bajo | S141: 2 — Bajo | T141: =MAX(IFERROR(VLOOKUP(Q141,MgValor,2,0),0),IFERROR(VLOOKUP(R141,MgValor,2,0),0),IFERROR(VLOOKUP(S141,MgValor,2,0),0)) | U141: =IFERROR(LOOKUP(T141,{0;1;2;3;4;5},{"Irrelevante";"Muy Bajo";"Bajo";"Medio";"Alto";"Muy Alto"}),"")
B142: TEC-034 | C142: monitor-celery | E142: [SW] Aplicaciones (software) | F142: [prp] Desarrollo propio (in house) | G142: Gestión Tecnológica | H142: Gestión Tecnológica | J142: Nube | K142: Producción | L142: Por definir | M142: Por definir | N142: Por definir | Q142: 2 — Bajo | R142: 2 — Bajo | S142: 2 — Bajo | T142: =MAX(IFERROR(VLOOKUP(Q142,MgValor,2,0),0),IFERROR(VLOOKUP(R142,MgValor,2,0),0),IFERROR(VLOOKUP(S142,MgValor,2,0),0)) | U142: =IFERROR(LOOKUP(T142,{0;1;2;3;4;5},{"Irrelevante";"Muy Bajo";"Bajo";"Medio";"Alto";"Muy Alto"}),"")
B143: TEC-036 | C143: monitor-frontend | E143: [SW] Aplicaciones (software) | F143: [prp] Desarrollo propio (in house) | G143: Gestión Tecnológica | H143: Gestión Tecnológica | J143: Nube | K143: Producción | L143: Por definir | M143: Por definir | N143: Por definir | Q143: 2 — Bajo | R143: 2 — Bajo | S143: 2 — Bajo | T143: =MAX(IFERROR(VLOOKUP(Q143,MgValor,2,0),0),IFERROR(VLOOKUP(R143,MgValor,2,0),0),IFERROR(VLOOKUP(S143,MgValor,2,0),0)) | U143: =IFERROR(LOOKUP(T143,{0;1;2;3;4;5},{"Irrelevante";"Muy Bajo";"Bajo";"Medio";"Alto";"Muy Alto"}),"")
B144: TEC-040 | C144: projectflow | E144: [SW] Aplicaciones (software) | F144: [prp] Desarrollo propio (in house) | G144: Gestión Tecnológica | H144: Gestión Tecnológica | J144: Nube | K144: Producción | L144: Por definir | M144: Por definir | N144: Por definir | Q144: 3 — Medio | R144: 3 — Medio | S144: 3 — Medio | T144: =MAX(IFERROR(VLOOKUP(Q144,MgValor,2,0),0),IFERROR(VLOOKUP(R144,MgValor,2,0),0),IFERROR(VLOOKUP(S144,MgValor,2,0),0)) | U144: =IFERROR(LOOKUP(T144,{0;1;2;3;4;5},{"Irrelevante";"Muy Bajo";"Bajo";"Medio";"Alto";"Muy Alto"}),"")
B145: TEC-042 | C145: sgi-cuantico | E145: [SW] Aplicaciones (software) | F145: [prp] Desarrollo propio (in house) | G145: Gestión Tecnológica | H145: Gestión Tecnológica | J145: Nube | K145: Producción | L145: Por definir | M145: Por definir | N145: Por definir | Q145: 3 — Medio | R145: 3 — Medio | S145: 3 — Medio | T145: =MAX(IFERROR(VLOOKUP(Q145,MgValor,2,0),0),IFERROR(VLOOKUP(R145,MgValor,2,0),0),IFERROR(VLOOKUP(S145,MgValor,2,0),0)) | U145: =IFERROR(LOOKUP(T145,{0;1;2;3;4;5},{"Irrelevante";"Muy Bajo";"Bajo";"Medio";"Alto";"Muy Alto"}),"")
B146: TEC-058 | C146: territorios-lbd-agro-clima-presen… | E146: [SW] Aplicaciones (software) | F146: [prp] Desarrollo propio (in house) | G146: Gestión Tecnológica | H146: Gestión Tecnológica | J146: Nube | K146: Producción | L146: Por definir | M146: Por definir | N146: Por definir | Q146: 2 — Bajo | R146: 2 — Bajo | S146: 2 — Bajo | T146: =MAX(IFERROR(VLOOKUP(Q146,MgValor,2,0),0),IFERROR(VLOOKUP(R146,MgValor,2,0),0),IFERROR(VLOOKUP(S146,MgValor,2,0),0)) | U146: =IFERROR(LOOKUP(T146,{0;1;2;3;4;5},{"Irrelevante";"Muy Bajo";"Bajo";"Medio";"Alto";"Muy Alto"}),"")
... B160: TEC-003 | C160: ERP-Financiero | E160: [SW] Aplicaciones (software) | F160: [std] Estándar (off the shelf) | G160: Gestión Tecnológica | H160: Gestión Tecnológica | J160: Nube | K160: Producción | L160: Por definir | M160: Por definir | N160: Por definir | Q160: 4 — Alto | R160: 4 — Alto | S160: 4 — Alto | T160: =MAX(IFERROR(VLOOKUP(Q160,MgValor,2,0),0),IFERROR(VLOOKUP(R160,MgValor,2,0),0),IFERROR(VLOOKUP(S160,MgValor,2,0),0)) | U160: =IFERROR(LOOKUP(T160,{0;1;2;3;4;5},{"Irrelevante";"Muy Bajo";"Bajo";"Medio";"Alto";"Muy Alto"}),"")
B161: FIN-20 | C161: Siigo (factura electronica) | D161: Sistema contable en la nube: facturas, causación, balances, factura electrónica | E161: [SW] Aplicaciones (software) | F161: [std] Estándar (off the shelf) | G161: Gestión Financiera | H161: Gestión Tecnológica | J161: Nube | K161: Producción | L161: Por definir | M161: Por definir | N161: Por definir | Q161: 4 — Alto | R161: 4 — Alto | S161: 4 — Alto | T161: =MAX(IFERROR(VLOOKUP(Q161,MgValor,2,0),0),IFERROR(VLOOKUP(R161,MgValor,2,0),0),IFERROR(VLOOKUP(S161,MgValor,2,0),0)) | U161: =IFERROR(LOOKUP(T161,{0;1;2;3;4;5},{"Irrelevante";"Muy Bajo";"Bajo";"Medio";"Alto";"Muy Alto"}),"")
B162: FIN-21 | C162: Usuarios y credenciales de Siigo | D162: Cuentas de acceso al sistema contable | E162: [SW] Aplicaciones (software) | F162: [std] Estándar (off the shelf) | G162: Gestión Financiera | H162: Cada titular | J162: Nube | K162: Producción | L162: Por definir | M162: Por definir | N162: Por definir | Q162: 3 — Medio | R162: 4 — Alto | S162: 4 — Alto | T162: =MAX(IFERROR(VLOOKUP(Q162,MgValor,2,0),0),IFERROR(VLOOKUP(R162,MgValor,2,0),0),IFERROR(VLOOKUP(S162,MgValor,2,0),0)) | U162: =IFERROR(LOOKUP(T162,{0;1;2;3;4;5},{"Irrelevante";"Muy Bajo";"Bajo";"Medio";"Alto";"Muy Alto"}),"")
B163: TEC-018 | C163: crm-app | E163: [SW] Aplicaciones (software) | F163: [std] Estándar (off the shelf) | G163: Gestión Tecnológica | H163: Gestión Tecnológica | J163: Nube | K163: Producción | L163: Sí | M163: Por definir | N163: Por definir | Q163: 2 — Bajo | R163: 2 — Bajo | S163: 2 — Bajo | T163: =MAX(IFERROR(VLOOKUP(Q163,MgValor,2,0),0),IFERROR(VLOOKUP(R163,MgValor,2,0),0),IFERROR(VLOOKUP(S163,MgValor,2,0),0)) | U163: =IFERROR(LOOKUP(T163,{0;1;2;3;4;5},{"Irrelevante";"Muy Bajo";"Bajo";"Medio";"Alto";"Muy Alto"}),"")
B164: TEC-056 | C164: superset-with-postgresql-e0kg480c… | E164: [SW] Aplicaciones (software) | F164: [std] Estándar (off the shelf) | G164: Gestión Tecnológica | H164: Gestión Tecnológica | J164: Nube | K164: Producción | L164: Por definir | M164: Por definir | N164: Por definir | Q164: 3 — Medio | R164: 3 — Medio | S164: 3 — Medio | T164: =MAX(IFERROR(VLOOKUP(Q164,MgValor,2,0),0),IFERROR(VLOOKUP(R164,MgValor,2,0),0),IFERROR(VLOOKUP(S164,MgValor,2,0),0)) | U164: =IFERROR(LOOKUP(T164,{0;1;2;3;4;5},{"Irrelevante";"Muy Bajo";"Bajo";"Medio";"Alto";"Muy Alto"}),"")
B165: TEC-057 | C165: superset-with-postgresql-f0o8co0w… | E165: [SW] Aplicaciones (software) | F165: [std] Estándar (off the shelf) | G165: Gestión Tecnológica | H165: Gestión Tecnológica | J165: Nube | K165: Producción | L165: Por definir | M165: Por definir | N165: Por definir | Q165: 2 — Bajo | R165: 2 — Bajo | S165: 2 — Bajo | T165: =MAX(IFERROR(VLOOKUP(Q165,MgValor,2,0),0),IFERROR(VLOOKUP(R165,MgValor,2,0),0),IFERROR(VLOOKUP(S165,MgValor,2,0),0)) | U165: =IFERROR(LOOKUP(T165,{0;1;2;3;4;5},{"Irrelevante";"Muy Bajo";"Bajo";"Medio";"Alto";"Muy Alto"}),"")
B166: TEC-011 | C166: Portal-Clientes | E166: [SW] Aplicaciones (software) | F166: [www] Servidor de presentación | G166: Gestión Tecnológica | H166: Gestión Tecnológica | J166: Nube | K166: Producción | L166: Sí | M166: Por definir | N166: Sí | Q166: 4 — Alto | R166: 4 — Alto | S166: 3 — Medio | T166: =MAX(IFERROR(VLOOKUP(Q166,MgValor,2,0),0),IFERROR(VLOOKUP(R166,MgValor,2,0),0),IFERROR(VLOOKUP(S166,MgValor,2,0),0)) | U166: =IFERROR(LOOKUP(T166,{0;1;2;3;4;5},{"Irrelevante";"Muy Bajo";"Bajo";"Medio";"Alto";"Muy Alto"}),"")
B167: TEC-074 | C167: wordpress-qa-junta | E167: [SW] Aplicaciones (software) | F167: [www] Servidor de presentación | G167: Gestión Tecnológica | H167: Gestión Tecnológica | J167: Nube | K167: Producción | L167: Por definir | M167: Por definir | N167: Sí | Q167: 3 — Medio | R167: 3 — Medio | S167: 3 — Medio | T167: =MAX(IFERROR(VLOOKUP(Q167,MgValor,2,0),0),IFERROR(VLOOKUP(R167,MgValor,2,0),0),IFERROR(VLOOKUP(S167,MgValor,2,0),0)) | U167: =IFERROR(LOOKUP(T167,{0;1;2;3;4;5},{"Irrelevante";"Muy Bajo";"Bajo";"Medio";"Alto";"Muy Alto"}),"")
B168: TEC-075 | C168: wordpress-with-mysql-n0o08kw0004c… | E168: [SW] Aplicaciones (software) | F168: [www] Servidor de presentación | G168: Gestión Tecnológica | H168: Gestión Tecnológica | J168: Nube | K168: Producción | L168: Por definir | M168: Por definir | N168: Sí | Q168: 3 — Medio | R168: 3 — Medio | S168: 3 — Medio | T168: =MAX(IFERROR(VLOOKUP(Q168,MgValor,2,0),0),IFERROR(VLOOKUP(R168,MgValor,2,0),0),IFERROR(VLOOKUP(S168,MgValor,2,0),0)) | U168: =IFERROR(LOOKUP(T168,{0;1;2;3;4;5},{"Irrelevante";"Muy Bajo";"Bajo";"Medio";"Alto";"Muy Alto"}),"")
B169: FIN-25 | C169: Tokens/dispositivos de autorización bancaria | D169: Dispositivos y claves de autorización de transferencias | E169: [HW] Equipamiento informático (hardware) | F169: [crypto] Dispositivos criptográficos | G169: Gestión Financiera | J169: Física | K169: Producción | L169: Por definir | M169: Por definir | N169: Por definir | Q169: 4 — Alto | R169: 4 — Alto | S169: 4 — Alto | T169: =MAX(IFERROR(VLOOKUP(Q169,MgValor,2,0),0),IFERROR(VLOOKUP(R169,MgValor,2,0),0),IFERROR(VLOOKUP(S169,MgValor,2,0),0)) | U169: =IFERROR(LOOKUP(T169,{0;1;2;3;4;5},{"Irrelevante";"Muy Bajo";"Bajo";"Medio";"Alto";"Muy Alto"}),"")
B170: TEC-004 | C170: FW-CORE-01 | E170: [HW] Equipamiento informático (hardware) | F170: [firewall] Cortafuegos | G170: Gestión Tecnológica | H170: Gestión Tecnológica | J170: Nube | K170: Producción | L170: Por definir | M170: Por definir | N170: Por definir | Q170: 4 — Alto | R170: 3 — Medio | S170: 3 — Medio | T170: =MAX(IFERROR(VLOOKUP(Q170,MgValor,2,0),0),IFERROR(VLOOKUP(R170,MgValor,2,0),0),IFERROR(VLOOKUP(S170,MgValor,2,0),0)) | U170: =IFERROR(LOOKUP(T170,{0;1;2;3;4;5},{"Irrelevante";"Muy Bajo";"Bajo";"Medio";"Alto";"Muy Alto"}),"")
B171: TEC-015 | C171: LAP-JT-001 | E171: [HW] Equipamiento informático (hardware) | F171: [pc] Informática personal | G171: Gestión Tecnológica | H171: Gestión Tecnológica | J171: Nube | K171: Producción | L171: Por definir | M171: Por definir | N171: Por definir | Q171: 2 — Bajo | R171: 3 — Medio | S171: 4 — Alto | T171: =MAX(IFERROR(VLOOKUP(Q171,MgValor,2,0),0),IFERROR(VLOOKUP(R171,MgValor,2,0),0),IFERROR(VLOOKUP(S171,MgValor,2,0),0)) | U171: =IFERROR(LOOKUP(T171,{0;1;2;3;4;5},{"Irrelevante";"Muy Bajo";"Bajo";"Medio";"Alto";"Muy Alto"}),"")
B172: TEC-007 | C172: AWS-Prod | E172: [HW] Equipamiento informático (hardware) | F172: [vhost] Equipo virtual | G172: Gestión Tecnológica | H172: Gestión Tecnológica | J172: Nube | K172: Producción | L172: Por definir | M172: Por definir | N172: Por definir | Q172: 4 — Alto | R172: 4 — Alto | S172: 4 — Alto | T172: =MAX(IFERROR(VLOOKUP(Q172,MgValor,2,0),0),IFERROR(VLOOKUP(R172,MgValor,2,0),0),IFERROR(VLOOKUP(S172,MgValor,2,0),0)) | U172: =IFERROR(LOOKUP(T172,{0;1;2;3;4;5},{"Irrelevante";"Muy Bajo";"Bajo";"Medio";"Alto";"Muy Alto"}),"")
B173: TEC-005 | C173: SRV-DB-01 | E173: [HW] Equipamiento informático (hardware) | F173: [vhost] Equipo virtual | G173: Gestión Tecnológica | H173: Gestión Tecnológica | J173: Nube | K173: Producción | L173: Por definir | M173: Por definir | N173: Por definir | Q173: 4 — Alto | R173: 4 — Alto | S173: 4 — Alto | T173: =MAX(IFERROR(VLOOKUP(Q173,MgValor,2,0),0),IFERROR(VLOOKUP(R173,MgValor,2,0),0),IFERROR(VLOOKUP(S173,MgValor,2,0),0)) | U173: =IFERROR(LOOKUP(T173,{0;1;2;3;4;5},{"Irrelevante";"Muy Bajo";"Bajo";"Medio";"Alto";"Muy Alto"}),"")
B174: TEC-006 | C174: SRV-PROD-01 | E174: [HW] Equipamiento informático (hardware) | F174: [vhost] Equipo virtual | G174: Gestión Tecnológica | H174: Gestión Tecnológica | J174: Nube | K174: Producción | L174: Por definir | M174: Por definir | N174: Por definir | Q174: 4 — Alto | R174: 4 — Alto | S174: 4 — Alto | T174: =MAX(IFERROR(VLOOKUP(Q174,MgValor,2,0),0),IFERROR(VLOOKUP(R174,MgValor,2,0),0),IFERROR(VLOOKUP(S174,MgValor,2,0),0)) | U174: =IFERROR(LOOKUP(T174,{0;1;2;3;4;5},{"Irrelevante";"Muy Bajo";"Bajo";"Medio";"Alto";"Muy Alto"}),"")
B175: TEC-030 | C175: localhost | E175: [HW] Equipamiento informático (hardware) | F175: [vhost] Equipo virtual | G175: Gestión Tecnológica | H175: Gestión Tecnológica | J175: Nube | K175: Producción | L175: Por definir | M175: Por definir | N175: Por definir | Q175: 2 — Bajo | R175: 2 — Bajo | S175: 2 — Bajo | T175: =MAX(IFERROR(VLOOKUP(Q175,MgValor,2,0),0),IFERROR(VLOOKUP(R175,MgValor,2,0),0),IFERROR(VLOOKUP(S175,MgValor,2,0),0)) | U175: =IFERROR(LOOKUP(T175,{0;1;2;3;4;5},{"Irrelevante";"Muy Bajo";"Bajo";"Medio";"Alto";"Muy Alto"}),"")
B176: TEC-043 | C176: srv-cuantaia-front | E176: [HW] Equipamiento informático (hardware) | F176: [vhost] Equipo virtual | G176: Gestión Tecnológica | H176: Gestión Tecnológica | J176: Nube | K176: Producción | L176: Por definir | M176: Por definir | N176: Por definir | Q176: 3 — Medio | R176: 3 — Medio | S176: 3 — Medio | T176: =MAX(IFERROR(VLOOKUP(Q176,MgValor,2,0),0),IFERROR(VLOOKUP(R176,MgValor,2,0),0),IFERROR(VLOOKUP(S176,MgValor,2,0),0)) | U176: =IFERROR(LOOKUP(T176,{0;1;2;3;4;5},{"Irrelevante";"Muy Bajo";"Bajo";"Medio";"Alto";"Muy Alto"}),"")
B177: TEC-044 | C177: srv-cuantaia-front | E177: [HW] Equipamiento informático (hardware) | F177: [vhost] Equipo virtual | G177: Gestión Tecnológica | H177: Gestión Tecnológica | J177: Nube | K177: Producción | L177: Por definir | M177: Por definir | N177: Por definir | Q177: 2 — Bajo | R177: 2 — Bajo | S177: 2 — Bajo | T177: =MAX(IFERROR(VLOOKUP(Q177,MgValor,2,0),0),IFERROR(VLOOKUP(R177,MgValor,2,0),0),IFERROR(VLOOKUP(S177,MgValor,2,0),0)) | U177: =IFERROR(LOOKUP(T177,{0;1;2;3;4;5},{"Irrelevante";"Muy Bajo";"Bajo";"Medio";"Alto";"Muy Alto"}),"")
B178: TEC-045 | C178: srv-cuantico-bots-n8n-a | E178: [HW] Equipamiento informático (hardware) | F178: [vhost] Equipo virtual | G178: Gestión Tecnológica | H178: Gestión Tecnológica | J178: Nube | K178: Producción | L178: Por definir | M178: Por definir | N178: Por definir | Q178: 2 — Bajo | R178: 2 — Bajo | S178: 2 — Bajo | T178: =MAX(IFERROR(VLOOKUP(Q178,MgValor,2,0),0),IFERROR(VLOOKUP(R178,MgValor,2,0),0),IFERROR(VLOOKUP(S178,MgValor,2,0),0)) | U178: =IFERROR(LOOKUP(T178,{0;1;2;3;4;5},{"Irrelevante";"Muy Bajo";"Bajo";"Medio";"Alto";"Muy Alto"}),"")
B179: TEC-046 | C179: srv-cuantico-bots-n8n-a | E179: [HW] Equipamiento informático (hardware) | F179: [vhost] Equipo virtual | G179: Gestión Tecnológica | H179: Gestión Tecnológica | J179: Nube | K179: Producción | L179: Por definir | M179: Por definir | N179: Por definir | Q179: 2 — Bajo | R179: 2 — Bajo | S179: 2 — Bajo | T179: =MAX(IFERROR(VLOOKUP(Q179,MgValor,2,0),0),IFERROR(VLOOKUP(R179,MgValor,2,0),0),IFERROR(VLOOKUP(S179,MgValor,2,0),0)) | U179: =IFERROR(LOOKUP(T179,{0;1;2;3;4;5},{"Irrelevante";"Muy Bajo";"Bajo";"Medio";"Alto";"Muy Alto"}),"")
B180: TEC-047 | C180: srv-cuantico-stack | E180: [HW] Equipamiento informático (hardware) | F180: [vhost] Equipo virtual | G180: Gestión Tecnológica | H180: Gestión Tecnológica | J180: Nube | K180: Producción | L180: Por definir | M180: Por definir | N180: Por definir | Q180: 2 — Bajo | R180: 2 — Bajo | S180: 2 — Bajo | T180: =MAX(IFERROR(VLOOKUP(Q180,MgValor,2,0),0),IFERROR(VLOOKUP(R180,MgValor,2,0),0),IFERROR(VLOOKUP(S180,MgValor,2,0),0)) | U180: =IFERROR(LOOKUP(T180,{0;1;2;3;4;5},{"Irrelevante";"Muy Bajo";"Bajo";"Medio";"Alto";"Muy Alto"}),"")
B181: TEC-048 | C181: srv-cuantico-stack | E181: [HW] Equipamiento informático (hardware) | F181: [vhost] Equipo virtual | G181: Gestión Tecnológica | H181: Gestión Tecnológica | J181: Nube | K181: Producción | L181: Por definir | M181: Por definir | N181: Por definir | Q181: 2 — Bajo | R181: 2 — Bajo | S181: 2 — Bajo | T181: =MAX(IFERROR(VLOOKUP(Q181,MgValor,2,0),0),IFERROR(VLOOKUP(R181,MgValor,2,0),0),IFERROR(VLOOKUP(S181,MgValor,2,0),0)) | U181: =IFERROR(LOOKUP(T181,{0;1;2;3;4;5},{"Irrelevante";"Muy Bajo";"Bajo";"Medio";"Alto";"Muy Alto"}),"")
... B187: TEC-054 | C187: srv-sicov-matcher-facial | E187: [HW] Equipamiento informático (hardware) | F187: [vhost] Equipo virtual | G187: Gestión Tecnológica | H187: Gestión Tecnológica | J187: Nube | K187: Producción | L187: Por definir | M187: Por definir | N187: Por definir | Q187: 2 — Bajo | R187: 2 — Bajo | S187: 2 — Bajo | T187: =MAX(IFERROR(VLOOKUP(Q187,MgValor,2,0),0),IFERROR(VLOOKUP(R187,MgValor,2,0),0),IFERROR(VLOOKUP(S187,MgValor,2,0),0)) | U187: =IFERROR(LOOKUP(T187,{0;1;2;3;4;5},{"Irrelevante";"Muy Bajo";"Bajo";"Medio";"Alto";"Muy Alto"}),"")
B188: DO-14 | C188: Conduce.pro | D188: Dominio .pro de ConducePro; registro defensivo de marca que redirige a la plataforma | E188: [COM] Redes de comunicaciones | F188: [Internet] Internet | G188: Gestión Tecnológica | H188: Gestión Tecnológica | J188: Nube | K188: Producción | L188: Por definir | M188: Por definir | N188: Sí | Q188: 4 — Alto | R188: 4 — Alto | S188: 2 — Bajo | T188: =MAX(IFERROR(VLOOKUP(Q188,MgValor,2,0),0),IFERROR(VLOOKUP(R188,MgValor,2,0),0),IFERROR(VLOOKUP(S188,MgValor,2,0),0)) | U188: =IFERROR(LOOKUP(T188,{0;1;2;3;4;5},{"Irrelevante";"Muy Bajo";"Bajo";"Medio";"Alto";"Muy Alto"}),"")
B189: DO-13 | C189: ConducePro.com | D189: Dominio .com de la plataforma ConducePro; registro principal de la marca | E189: [COM] Redes de comunicaciones | F189: [Internet] Internet | G189: Gestión Tecnológica | H189: Gestión Tecnológica | J189: Nube | K189: Producción | L189: Por definir | M189: Por definir | N189: Sí | Q189: 4 — Alto | R189: 4 — Alto | S189: 2 — Bajo | T189: =MAX(IFERROR(VLOOKUP(Q189,MgValor,2,0),0),IFERROR(VLOOKUP(R189,MgValor,2,0),0),IFERROR(VLOOKUP(S189,MgValor,2,0),0)) | U189: =IFERROR(LOOKUP(T189,{0;1;2;3;4;5},{"Irrelevante";"Muy Bajo";"Bajo";"Medio";"Alto";"Muy Alto"}),"")
B190: DO-15 | C190: ConducePro.com.co | D190: Dominio .com.co de ConducePro; registro defensivo de marca para Colombia | E190: [COM] Redes de comunicaciones | F190: [Internet] Internet | G190: Gestión Tecnológica | H190: Gestión Tecnológica | J190: Nube | K190: Producción | L190: Por definir | M190: Por definir | N190: Sí | Q190: 4 — Alto | R190: 4 — Alto | S190: 2 — Bajo | T190: =MAX(IFERROR(VLOOKUP(Q190,MgValor,2,0),0),IFERROR(VLOOKUP(R190,MgValor,2,0),0),IFERROR(VLOOKUP(S190,MgValor,2,0),0)) | U190: =IFERROR(LOOKUP(T190,{0;1;2;3;4;5},{"Irrelevante";"Muy Bajo";"Bajo";"Medio";"Alto";"Muy Alto"}),"")
B191: TEC-010 | C191: DNS-Cuántico | E191: [COM] Redes de comunicaciones | F191: [Internet] Internet | G191: Gestión Tecnológica | H191: Gestión Tecnológica | J191: Nube | K191: Producción | L191: Por definir | M191: Por definir | N191: Sí | Q191: 4 — Alto | R191: 3 — Medio | S191: 2 — Bajo | T191: =MAX(IFERROR(VLOOKUP(Q191,MgValor,2,0),0),IFERROR(VLOOKUP(R191,MgValor,2,0),0),IFERROR(VLOOKUP(S191,MgValor,2,0),0)) | U191: =IFERROR(LOOKUP(T191,{0;1;2;3;4;5},{"Irrelevante";"Muy Bajo";"Bajo";"Medio";"Alto";"Muy Alto"}),"")
B192: DO-09 | C192: Mauriciolizcano.co | D192: Dominio .co personal/institucional de Mauricio Lizcano; sitio web público | E192: [COM] Redes de comunicaciones | F192: [Internet] Internet | G192: Gestión Tecnológica | H192: Gestión Tecnológica | J192: Nube | K192: Producción | L192: Por definir | M192: Sí | N192: Sí | Q192: 4 — Alto | R192: 4 — Alto | S192: 2 — Bajo | T192: =MAX(IFERROR(VLOOKUP(Q192,MgValor,2,0),0),IFERROR(VLOOKUP(R192,MgValor,2,0),0),IFERROR(VLOOKUP(S192,MgValor,2,0),0)) | U192: =IFERROR(LOOKUP(T192,{0;1;2;3;4;5},{"Irrelevante";"Muy Bajo";"Bajo";"Medio";"Alto";"Muy Alto"}),"")
B193: DO-12 | C193: Mauriciolizcano.co | D193: Dominio .co de Mauricio Lizcano (registro duplicado en el inventario; validar si corresponde a otra extensión) | E193: [COM] Redes de comunicaciones | F193: [Internet] Internet | G193: Gestión Tecnológica | H193: Gestión Tecnológica | J193: Nube | K193: Producción | L193: Por definir | M193: Por definir | N193: Sí | Q193: 4 — Alto | R193: 4 — Alto | S193: 2 — Bajo | T193: =MAX(IFERROR(VLOOKUP(Q193,MgValor,2,0),0),IFERROR(VLOOKUP(R193,MgValor,2,0),0),IFERROR(VLOOKUP(S193,MgValor,2,0),0)) | U193: =IFERROR(LOOKUP(T193,{0;1;2;3;4;5},{"Irrelevante";"Muy Bajo";"Bajo";"Medio";"Alto";"Muy Alto"}),"")
B194: DO-11 | C194: Mauriciolizcano.com | D194: Dominio .com de Mauricio Lizcano; registro principal de la marca personal | E194: [COM] Redes de comunicaciones | F194: [Internet] Internet | G194: Gestión Tecnológica | H194: Gestión Tecnológica | J194: Nube | K194: Producción | L194: Por definir | M194: Sí | N194: Sí | Q194: 4 — Alto | R194: 4 — Alto | S194: 2 — Bajo | T194: =MAX(IFERROR(VLOOKUP(Q194,MgValor,2,0),0),IFERROR(VLOOKUP(R194,MgValor,2,0),0),IFERROR(VLOOKUP(S194,MgValor,2,0),0)) | U194: =IFERROR(LOOKUP(T194,{0;1;2;3;4;5},{"Irrelevante";"Muy Bajo";"Bajo";"Medio";"Alto";"Muy Alto"}),"")
B195: DO-08 | C195: Mintrace.co | D195: Dominio .co de la plataforma Mintrace; apunta a los servicios de trazabilidad minera | E195: [COM] Redes de comunicaciones | F195: [Internet] Internet | G195: Gestión Tecnológica | H195: Gestión Tecnológica | J195: Nube | K195: Producción | L195: Sí | M195: Por definir | N195: Sí | Q195: 4 — Alto | R195: 4 — Alto | S195: 2 — Bajo | T195: =MAX(IFERROR(VLOOKUP(Q195,MgValor,2,0),0),IFERROR(VLOOKUP(R195,MgValor,2,0),0),IFERROR(VLOOKUP(S195,MgValor,2,0),0)) | U195: =IFERROR(LOOKUP(T195,{0;1;2;3;4;5},{"Irrelevante";"Muy Bajo";"Bajo";"Medio";"Alto";"Muy Alto"}),"")
B196: DO-10 | C196: Mintrace.com | D196: Dominio .com de la plataforma Mintrace; registro principal de la marca de trazabilidad minera | E196: [COM] Redes de comunicaciones | F196: [Internet] Internet | G196: Gestión Tecnológica | H196: Gestión Tecnológica | J196: Nube | K196: Producción | L196: Sí | M196: Por definir | N196: Sí | Q196: 4 — Alto | R196: 4 — Alto | S196: 2 — Bajo | T196: =MAX(IFERROR(VLOOKUP(Q196,MgValor,2,0),0),IFERROR(VLOOKUP(R196,MgValor,2,0),0),IFERROR(VLOOKUP(S196,MgValor,2,0),0)) | U196: =IFERROR(LOOKUP(T196,{0;1;2;3;4;5},{"Irrelevante";"Muy Bajo";"Bajo";"Medio";"Alto";"Muy Alto"}),"")
B197: DO-16 | C197: Rapivolt.com | D197: Dominio de la marca Rapivolt; sitio web de la línea de movilidad eléctrica | E197: [COM] Redes de comunicaciones | F197: [Internet] Internet | G197: Gestión Tecnológica | H197: Gestión Tecnológica | J197: Nube | K197: Producción | L197: Por definir | M197: Por definir | N197: Sí | Q197: 4 — Alto | R197: 4 — Alto | S197: 2 — Bajo | T197: =MAX(IFERROR(VLOOKUP(Q197,MgValor,2,0),0),IFERROR(VLOOKUP(R197,MgValor,2,0),0),IFERROR(VLOOKUP(S197,MgValor,2,0),0)) | U197: =IFERROR(LOOKUP(T197,{0;1;2;3;4;5},{"Irrelevante";"Muy Bajo";"Bajo";"Medio";"Alto";"Muy Alto"}),"")
B198: DO-06 | C198: Territoriosia.com | D198: Dominio de la marca CuantAIA; sitio web | E198: [COM] Redes de comunicaciones | F198: [Internet] Internet | G198: Gestión Tecnológica | H198: Gestión Tecnológica | J198: Nube | K198: Producción | L198: Por definir | M198: Por definir | N198: Sí | Q198: 4 — Alto | R198: 4 — Alto | S198: 2 — Bajo | T198: =MAX(IFERROR(VLOOKUP(Q198,MgValor,2,0),0),IFERROR(VLOOKUP(R198,MgValor,2,0),0),IFERROR(VLOOKUP(S198,MgValor,2,0),0)) | U198: =IFERROR(LOOKUP(T198,{0;1;2;3;4;5},{"Irrelevante";"Muy Bajo";"Bajo";"Medio";"Alto";"Muy Alto"}),"")
B199: DO-05 | C199: cuantaia.com | D199: Dominio de la marca CuantAIA; sitio web | E199: [COM] Redes de comunicaciones | F199: [Internet] Internet | G199: Gestión Tecnológica | H199: Gestión Tecnológica | J199: Nube | K199: Producción | L199: Por definir | M199: Por definir | N199: Sí | Q199: 4 — Alto | R199: 4 — Alto | S199: 2 — Bajo | T199: =MAX(IFERROR(VLOOKUP(Q199,MgValor,2,0),0),IFERROR(VLOOKUP(R199,MgValor,2,0),0),IFERROR(VLOOKUP(S199,MgValor,2,0),0)) | U199: =IFERROR(LOOKUP(T199,{0;1;2;3;4;5},{"Irrelevante";"Muy Bajo";"Bajo";"Medio";"Alto";"Muy Alto"}),"")
B200: DO-01 | C200: cuantico.com | D200: Dominio corporativo principal de Cuántico; soporta el sitio web institucional y el correo corporativo | E200: [COM] Redes de comunicaciones | F200: [Internet] Internet | G200: Gestión Tecnológica | H200: Gestión Tecnológica | J200: Nube | K200: Producción | L200: Por definir | M200: Por definir | N200: Sí | Q200: 4 — Alto | R200: 4 — Alto | S200: 2 — Bajo | T200: =MAX(IFERROR(VLOOKUP(Q200,MgValor,2,0),0),IFERROR(VLOOKUP(R200,MgValor,2,0),0),IFERROR(VLOOKUP(S200,MgValor,2,0),0)) | U200: =IFERROR(LOOKUP(T200,{0;1;2;3;4;5},{"Irrelevante";"Muy Bajo";"Bajo";"Medio";"Alto";"Muy Alto"}),"")
B201: DO-02 | C201: cuanticore.com | D201: Dominio de la organización Cuanticore; usado en repositorios, servicios técnicos y correo del equipo de desarrollo | E201: [COM] Redes de comunicaciones | F201: [Internet] Internet | G201: Gestión Tecnológica | H201: Gestión Tecnológica | J201: Nube | K201: Desarrollo | L201: Por definir | M201: Por definir | N201: Sí | Q201: 4 — Alto | R201: 4 — Alto | S201: 2 — Bajo | T201: =MAX(IFERROR(VLOOKUP(Q201,MgValor,2,0),0),IFERROR(VLOOKUP(R201,MgValor,2,0),0),IFERROR(VLOOKUP(S201,MgValor,2,0),0)) | U201: =IFERROR(LOOKUP(T201,{0;1;2;3;4;5},{"Irrelevante";"Muy Bajo";"Bajo";"Medio";"Alto";"Muy Alto"}),"")
B202: DO-07 | C202: gerenciapublicatic.com | D202: Dominio de la marca CuantAIA; sitio web | E202: [COM] Redes de comunicaciones | F202: [Internet] Internet | G202: Gestión Tecnológica | H202: Gestión Tecnológica | J202: Nube | K202: Producción | L202: Por definir | M202: Por definir | N202: Sí | Q202: 4 — Alto | R202: 4 — Alto | S202: 2 — Bajo | T202: =MAX(IFERROR(VLOOKUP(Q202,MgValor,2,0),0),IFERROR(VLOOKUP(R202,MgValor,2,0),0),IFERROR(VLOOKUP(S202,MgValor,2,0),0)) | U202: =IFERROR(LOOKUP(T202,{0;1;2;3;4;5},{"Irrelevante";"Muy Bajo";"Bajo";"Medio";"Alto";"Muy Alto"}),"")
B203: DO-04 | C203: govtechcolombia.com | D203: Dominio de la marca GovTech Colombia; sitio web | E203: [COM] Redes de comunicaciones | F203: [Internet] Internet | G203: Gestión Tecnológica | H203: Gestión Tecnológica | J203: Nube | K203: Producción | L203: Por definir | M203: Por definir | N203: Sí | Q203: 4 — Alto | R203: 4 — Alto | S203: 2 — Bajo | T203: =MAX(IFERROR(VLOOKUP(Q203,MgValor,2,0),0),IFERROR(VLOOKUP(R203,MgValor,2,0),0),IFERROR(VLOOKUP(S203,MgValor,2,0),0)) | U203: =IFERROR(LOOKUP(T203,{0;1;2;3;4;5},{"Irrelevante";"Muy Bajo";"Bajo";"Medio";"Alto";"Muy Alto"}),"")
B204: DO-03 | C204: innovaciencia.com | D204: Dominio de la marca Innovaciencia; sitio web | E204: [COM] Redes de comunicaciones | F204: [Internet] Internet | G204: Gestión Tecnológica | H204: Gestión Tecnológica | J204: Nube | K204: Producción | L204: Por definir | M204: Por definir | N204: Sí | Q204: 4 — Alto | R204: 4 — Alto | S204: 2 — Bajo | T204: =MAX(IFERROR(VLOOKUP(Q204,MgValor,2,0),0),IFERROR(VLOOKUP(R204,MgValor,2,0),0),IFERROR(VLOOKUP(S204,MgValor,2,0),0)) | U204: =IFERROR(LOOKUP(T204,{0;1;2;3;4;5},{"Irrelevante";"Muy Bajo";"Bajo";"Medio";"Alto";"Muy Alto"}),"")
B205: TEC-013 | C205: SW-CORE-01 | E205: [COM] Redes de comunicaciones | F205: [LAN] Red local | G205: Gestión Tecnológica | H205: Gestión Tecnológica | J205: Nube | K205: Producción | L205: Por definir | M205: Por definir | N205: Por definir | Q205: 4 — Alto | R205: 2 — Bajo | S205: 2 — Bajo | T205: =MAX(IFERROR(VLOOKUP(Q205,MgValor,2,0),0),IFERROR(VLOOKUP(R205,MgValor,2,0),0),IFERROR(VLOOKUP(S205,MgValor,2,0),0)) | U205: =IFERROR(LOOKUP(T205,{0;1;2;3;4;5},{"Irrelevante";"Muy Bajo";"Bajo";"Medio";"Alto";"Muy Alto"}),"")
B206: TEC-072 | C206: vpc-055a42a5c0e126779 | E206: [COM] Redes de comunicaciones | F206: [LAN] Red local | G206: Gestión Tecnológica | H206: Gestión Tecnológica | J206: Nube | K206: Producción | L206: Por definir | M206: Por definir | N206: Por definir | Q206: 2 — Bajo | R206: 2 — Bajo | S206: 2 — Bajo | T206: =MAX(IFERROR(VLOOKUP(Q206,MgValor,2,0),0),IFERROR(VLOOKUP(R206,MgValor,2,0),0),IFERROR(VLOOKUP(S206,MgValor,2,0),0)) | U206: =IFERROR(LOOKUP(T206,{0;1;2;3;4;5},{"Irrelevante";"Muy Bajo";"Bajo";"Medio";"Alto";"Muy Alto"}),"")
B207: TEC-073 | C207: vpc-055a42a5c0e126779 | E207: [COM] Redes de comunicaciones | F207: [LAN] Red local | G207: Gestión Tecnológica | H207: Gestión Tecnológica | J207: Nube | K207: Producción | L207: Por definir | M207: Por definir | N207: Por definir | Q207: 2 — Bajo | R207: 2 — Bajo | S207: 2 — Bajo | T207: =MAX(IFERROR(VLOOKUP(Q207,MgValor,2,0),0),IFERROR(VLOOKUP(R207,MgValor,2,0),0),IFERROR(VLOOKUP(S207,MgValor,2,0),0)) | U207: =IFERROR(LOOKUP(T207,{0;1;2;3;4;5},{"Irrelevante";"Muy Bajo";"Bajo";"Medio";"Alto";"Muy Alto"}),"")
B208: FIN-13 | C208: Repositorios documentales | D208: Soportes en papel: facturas, contratos, comprobantes | E208: [Media] Soportes de información | F208: [printed] Material impreso | G208: Gestión Financiera | H208: Finance and Administrative Manager | J208: Física | K208: Producción | L208: Sí | M208: Por definir | N208: Por definir | Q208: 3 — Medio | R208: 4 — Alto | S208: 3 — Medio | T208: =MAX(IFERROR(VLOOKUP(Q208,MgValor,2,0),0),IFERROR(VLOOKUP(R208,MgValor,2,0),0),IFERROR(VLOOKUP(S208,MgValor,2,0),0)) | U208: =IFERROR(LOOKUP(T208,{0;1;2;3;4;5},{"Irrelevante";"Muy Bajo";"Bajo";"Medio";"Alto";"Muy Alto"}),"")
B209: TEC-012 | C209: S3-Backups | E209: [Media] Soportes de información | F209: [vdisk] Discos virtuales | G209: Gestión Tecnológica | H209: Gestión Tecnológica | J209: Nube | K209: Producción | L209: Por definir | M209: Por definir | N209: Por definir | Q209: 3 — Medio | R209: 3 — Medio | S209: 4 — Alto | T209: =MAX(IFERROR(VLOOKUP(Q209,MgValor,2,0),0),IFERROR(VLOOKUP(R209,MgValor,2,0),0),IFERROR(VLOOKUP(S209,MgValor,2,0),0)) | U209: =IFERROR(LOOKUP(T209,{0;1;2;3;4;5},{"Irrelevante";"Muy Bajo";"Bajo";"Medio";"Alto";"Muy Alto"}),"")
B210: TEC-016 | C210: aws-cost-reports-cuantico | E210: [Media] Soportes de información | F210: [vdisk] Discos virtuales | G210: Gestión Tecnológica | H210: Gestión Tecnológica | J210: Nube | K210: Producción | L210: Por definir | M210: Por definir | N210: Por definir | Q210: 2 — Bajo | R210: 2 — Bajo | S210: 2 — Bajo | T210: =MAX(IFERROR(VLOOKUP(Q210,MgValor,2,0),0),IFERROR(VLOOKUP(R210,MgValor,2,0),0),IFERROR(VLOOKUP(S210,MgValor,2,0),0)) | U210: =IFERROR(LOOKUP(T210,{0;1;2;3;4;5},{"Irrelevante";"Muy Bajo";"Bajo";"Medio";"Alto";"Muy Alto"}),"")
B211: TEC-017 | C211: bck-ml-sftp-space | E211: [Media] Soportes de información | F211: [vdisk] Discos virtuales | G211: Gestión Tecnológica | H211: Gestión Tecnológica | J211: Nube | K211: Producción | L211: Por definir | M211: Por definir | N211: Por definir | Q211: 2 — Bajo | R211: 2 — Bajo | S211: 2 — Bajo | T211: =MAX(IFERROR(VLOOKUP(Q211,MgValor,2,0),0),IFERROR(VLOOKUP(R211,MgValor,2,0),0),IFERROR(VLOOKUP(S211,MgValor,2,0),0)) | U211: =IFERROR(LOOKUP(T211,{0;1;2;3;4;5},{"Irrelevante";"Muy Bajo";"Bajo";"Medio";"Alto";"Muy Alto"}),"")
B212: TEC-019 | C212: cuantai-bck-cluster | E212: [Media] Soportes de información | F212: [vdisk] Discos virtuales | G212: Gestión Tecnológica | H212: Gestión Tecnológica | J212: Nube | K212: Producción | L212: Por definir | M212: Por definir | N212: Por definir | Q212: 2 — Bajo | R212: 2 — Bajo | S212: 2 — Bajo | T212: =MAX(IFERROR(VLOOKUP(Q212,MgValor,2,0),0),IFERROR(VLOOKUP(R212,MgValor,2,0),0),IFERROR(VLOOKUP(S212,MgValor,2,0),0)) | U212: =IFERROR(LOOKUP(T212,{0;1;2;3;4;5},{"Irrelevante";"Muy Bajo";"Bajo";"Medio";"Alto";"Muy Alto"}),"")
B213: TEC-020 | C213: cuantaia-bck-ec2 | E213: [Media] Soportes de información | F213: [vdisk] Discos virtuales | G213: Gestión Tecnológica | H213: Gestión Tecnológica | J213: Nube | K213: Producción | L213: Por definir | M213: Por definir | N213: Por definir | Q213: 2 — Bajo | R213: 2 — Bajo | S213: 2 — Bajo | T213: =MAX(IFERROR(VLOOKUP(Q213,MgValor,2,0),0),IFERROR(VLOOKUP(R213,MgValor,2,0),0),IFERROR(VLOOKUP(S213,MgValor,2,0),0)) | U213: =IFERROR(LOOKUP(T213,{0;1;2;3;4;5},{"Irrelevante";"Muy Bajo";"Bajo";"Medio";"Alto";"Muy Alto"}),"")
B214: TEC-021 | C214: cuantico-backup-sharepoint | E214: [Media] Soportes de información | F214: [vdisk] Discos virtuales | G214: Gestión Tecnológica | H214: Gestión Tecnológica | J214: Nube | K214: Producción | L214: Por definir | M214: Por definir | N214: Por definir | Q214: 2 — Bajo | R214: 2 — Bajo | S214: 2 — Bajo | T214: =MAX(IFERROR(VLOOKUP(Q214,MgValor,2,0),0),IFERROR(VLOOKUP(R214,MgValor,2,0),0),IFERROR(VLOOKUP(S214,MgValor,2,0),0)) | U214: =IFERROR(LOOKUP(T214,{0;1;2;3;4;5},{"Irrelevante";"Muy Bajo";"Bajo";"Medio";"Alto";"Muy Alto"}),"")
B215: TEC-022 | C215: cuantico-ilc-backup | E215: [Media] Soportes de información | F215: [vdisk] Discos virtuales | G215: Gestión Tecnológica | H215: Gestión Tecnológica | J215: Nube | K215: Producción | L215: Por definir | M215: Por definir | N215: Por definir | Q215: 2 — Bajo | R215: 2 — Bajo | S215: 2 — Bajo | T215: =MAX(IFERROR(VLOOKUP(Q215,MgValor,2,0),0),IFERROR(VLOOKUP(R215,MgValor,2,0),0),IFERROR(VLOOKUP(S215,MgValor,2,0),0)) | U215: =IFERROR(LOOKUP(T215,{0;1;2;3;4;5},{"Irrelevante";"Muy Bajo";"Bajo";"Medio";"Alto";"Muy Alto"}),"")
...

Sheet 1.1 Agregar Activo
B1: AGREGAR ACTIVO — QUÉ FALTA POR VALORAR Y QUÉ FILAS HAY QUE CREAR
B2: Arriba: filtre por proceso, tipo y subtipo para ver qué activos faltan por valorar. Abajo: elija un activo y obtenga, listas para copiar, las filas que le corresponden en la hoja de Valoración.
B3: Código de color: | C3: Amarillo = Campo de entrada — se selecciona de una lista | E3: Lila = Calculado automáticamente — no escribir encima | G3: Gris = Dato de la norma MAGERIT — no modificar
B5: 1 · FILTRE PARA VER QUÉ ACTIVOS FALTAN
B6: Proceso o Área | C6: Gestión Tecnológica | G6: Activos que cumplen el filtro | I6: =COUNTIF($B$11:$B$244,"Sí")
B7: Tipo MAGERIT | C7: [HW] Equipamiento informático (hardware) | G7: De ellos, requieren valoración (valor 4 o más) | I7: =COUNTIFS($B$11:$B$244,"Sí",$I$11:$I$244,"Sí")
B8: Subtipo MAGERIT | C8: (Todos los subtipos)
B9: 2 · ACTIVOS Y ESTADO DE SU VALORACIÓN (filtre la columna «Cumple el filtro» por «Sí»)
B10: Cumple el filtro | C10: Código | D10: Nombre del activo | E10: Proceso o Área | F10: Tipo MAGERIT | G10: Subtipo MAGERIT | H10: Valor del activo | I10: ¿Requiere valoración? | J10: Filas que le corresponden | K10: Filas ya registradas | L10: Situación
B11: =IF(AND(OR($C$6="(Todos los procesos)",$C$6='1. Matriz de Activos'!$G$6),OR($C$7="(Todos los tipos)",$C$7='1. Matriz de Activos'!$E$6),OR($C$8="(Todos los subtipos)",$C$8='1. Matriz de Activos'!$F$6)),"Sí","No") | C11: ='1. Matriz de Activos'!$B$6 | D11: ='1. Matriz de Activos'!$C$6 | E11: ='1. Matriz de Activos'!$G$6 | F11: ='1. Matriz de Activos'!$E$6 | G11: ='1. Matriz de Activos'!$F$6 | H11: ='1. Matriz de Activos'!$T$6 | I11: =IF($H11>=4,"Sí","No") | J11: =IF($H11>=4,IFERROR(VLOOKUP($G11,AmenTabla,2,0),0),0) | K11: =COUNTIF('2. Valoración '!$C$6:$C$2261,$C11) | L11: =IF($I11="No","No requiere valoración",IF($K11=0,"FALTA POR COMPLETO — agregar "&$J11&" filas",IF($K11<$J11,"INCOMPLETO — faltan "&($J11-$K11)&" filas",IF($K11>$J11,"REVISAR — hay filas de más","Completo"))))
B12: =IF(AND(OR($C$6="(Todos los procesos)",$C$6='1. Matriz de Activos'!$G$7),OR($C$7="(Todos los tipos)",$C$7='1. Matriz de Activos'!$E$7),OR($C$8="(Todos los subtipos)",$C$8='1. Matriz de Activos'!$F$7)),"Sí","No") | C12: ='1. Matriz de Activos'!$B$7 | D12: ='1. Matriz de Activos'!$C$7 | E12: ='1. Matriz de Activos'!$G$7 | F12: ='1. Matriz de Activos'!$E$7 | G12: ='1. Matriz de Activos'!$F$7 | H12: ='1. Matriz de Activos'!$T$7 | I12: =IF($H12>=4,"Sí","No") | J12: =IF($H12>=4,IFERROR(VLOOKUP($G12,AmenTabla,2,0),0),0) | K12: =COUNTIF('2. Valoración '!$C$6:$C$2261,$C12) | L12: =IF($I12="No","No requiere valoración",IF($K12=0,"FALTA POR COMPLETO — agregar "&$J12&" filas",IF($K12<$J12,"INCOMPLETO — faltan "&($J12-$K12)&" filas",IF($K12>$J12,"REVISAR — hay filas de más","Completo"))))
B13: =IF(AND(OR($C$6="(Todos los procesos)",$C$6='1. Matriz de Activos'!$G$8),OR($C$7="(Todos los tipos)",$C$7='1. Matriz de Activos'!$E$8),OR($C$8="(Todos los subtipos)",$C$8='1. Matriz de Activos'!$F$8)),"Sí","No") | C13: ='1. Matriz de Activos'!$B$8 | D13: ='1. Matriz de Activos'!$C$8 | E13: ='1. Matriz de Activos'!$G$8 | F13: ='1. Matriz de Activos'!$E$8 | G13: ='1. Matriz de Activos'!$F$8 | H13: ='1. Matriz de Activos'!$T$8 | I13: =IF($H13>=4,"Sí","No") | J13: =IF($H13>=4,IFERROR(VLOOKUP($G13,AmenTabla,2,0),0),0) | K13: =COUNTIF('2. Valoración '!$C$6:$C$2261,$C13) | L13: =IF($I13="No","No requiere valoración",IF($K13=0,"FALTA POR COMPLETO — agregar "&$J13&" filas",IF($K13<$J13,"INCOMPLETO — faltan "&($J13-$K13)&" filas",IF($K13>$J13,"REVISAR — hay filas de más","Completo"))))
B14: =IF(AND(OR($C$6="(Todos los procesos)",$C$6='1. Matriz de Activos'!$G$9),OR($C$7="(Todos los tipos)",$C$7='1. Matriz de Activos'!$E$9),OR($C$8="(Todos los subtipos)",$C$8='1. Matriz de Activos'!$F$9)),"Sí","No") | C14: ='1. Matriz de Activos'!$B$9 | D14: ='1. Matriz de Activos'!$C$9 | E14: ='1. Matriz de Activos'!$G$9 | F14: ='1. Matriz de Activos'!$E$9 | G14: ='1. Matriz de Activos'!$F$9 | H14: ='1. Matriz de Activos'!$T$9 | I14: =IF($H14>=4,"Sí","No") | J14: =IF($H14>=4,IFERROR(VLOOKUP($G14,AmenTabla,2,0),0),0) | K14: =COUNTIF('2. Valoración '!$C$6:$C$2261,$C14) | L14: =IF($I14="No","No requiere valoración",IF($K14=0,"FALTA POR COMPLETO — agregar "&$J14&" filas",IF($K14<$J14,"INCOMPLETO — faltan "&($J14-$K14)&" filas",IF($K14>$J14,"REVISAR — hay filas de más","Completo"))))
B15: =IF(AND(OR($C$6="(Todos los procesos)",$C$6='1. Matriz de Activos'!$G$10),OR($C$7="(Todos los tipos)",$C$7='1. Matriz de Activos'!$E$10),OR($C$8="(Todos los subtipos)",$C$8='1. Matriz de Activos'!$F$10)),"Sí","No") | C15: ='1. Matriz de Activos'!$B$10 | D15: ='1. Matriz de Activos'!$C$10 | E15: ='1. Matriz de Activos'!$G$10 | F15: ='1. Matriz de Activos'!$E$10 | G15: ='1. Matriz de Activos'!$F$10 | H15: ='1. Matriz de Activos'!$T$10 | I15: =IF($H15>=4,"Sí","No") | J15: =IF($H15>=4,IFERROR(VLOOKUP($G15,AmenTabla,2,0),0),0) | K15: =COUNTIF('2. Valoración '!$C$6:$C$2261,$C15) | L15: =IF($I15="No","No requiere valoración",IF($K15=0,"FALTA POR COMPLETO — agregar "&$J15&" filas",IF($K15<$J15,"INCOMPLETO — faltan "&($J15-$K15)&" filas",IF($K15>$J15,"REVISAR — hay filas de más","Completo"))))
B16: =IF(AND(OR($C$6="(Todos los procesos)",$C$6='1. Matriz de Activos'!$G$11),OR($C$7="(Todos los tipos)",$C$7='1. Matriz de Activos'!$E$11),OR($C$8="(Todos los subtipos)",$C$8='1. Matriz de Activos'!$F$11)),"Sí","No") | C16: ='1. Matriz de Activos'!$B$11 | D16: ='1. Matriz de Activos'!$C$11 | E16: ='1. Matriz de Activos'!$G$11 | F16: ='1. Matriz de Activos'!$E$11 | G16: ='1. Matriz de Activos'!$F$11 | H16: ='1. Matriz de Activos'!$T$11 | I16: =IF($H16>=4,"Sí","No") | J16: =IF($H16>=4,IFERROR(VLOOKUP($G16,AmenTabla,2,0),0),0) | K16: =COUNTIF('2. Valoración '!$C$6:$C$2261,$C16) | L16: =IF($I16="No","No requiere valoración",IF($K16=0,"FALTA POR COMPLETO — agregar "&$J16&" filas",IF($K16<$J16,"INCOMPLETO — faltan "&($J16-$K16)&" filas",IF($K16>$J16,"REVISAR — hay filas de más","Completo"))))
B17: =IF(AND(OR($C$6="(Todos los procesos)",$C$6='1. Matriz de Activos'!$G$12),OR($C$7="(Todos los tipos)",$C$7='1. Matriz de Activos'!$E$12),OR($C$8="(Todos los subtipos)",$C$8='1. Matriz de Activos'!$F$12)),"Sí","No") | C17: ='1. Matriz de Activos'!$B$12 | D17: ='1. Matriz de Activos'!$C$12 | E17: ='1. Matriz de Activos'!$G$12 | F17: ='1. Matriz de Activos'!$E$12 | G17: ='1. Matriz de Activos'!$F$12 | H17: ='1. Matriz de Activos'!$T$12 | I17: =IF($H17>=4,"Sí","No") | J17: =IF($H17>=4,IFERROR(VLOOKUP($G17,AmenTabla,2,0),0),0) | K17: =COUNTIF('2. Valoración '!$C$6:$C$2261,$C17) | L17: =IF($I17="No","No requiere valoración",IF($K17=0,"FALTA POR COMPLETO — agregar "&$J17&" filas",IF($K17<$J17,"INCOMPLETO — faltan "&($J17-$K17)&" filas",IF($K17>$J17,"REVISAR — hay filas de más","Completo"))))
B18: =IF(AND(OR($C$6="(Todos los procesos)",$C$6='1. Matriz de Activos'!$G$13),OR($C$7="(Todos los tipos)",$C$7='1. Matriz de Activos'!$E$13),OR($C$8="(Todos los subtipos)",$C$8='1. Matriz de Activos'!$F$13)),"Sí","No") | C18: ='1. Matriz de Activos'!$B$13 | D18: ='1. Matriz de Activos'!$C$13 | E18: ='1. Matriz de Activos'!$G$13 | F18: ='1. Matriz de Activos'!$E$13 | G18: ='1. Matriz de Activos'!$F$13 | H18: ='1. Matriz de Activos'!$T$13 | I18: =IF($H18>=4,"Sí","No") | J18: =IF($H18>=4,IFERROR(VLOOKUP($G18,AmenTabla,2,0),0),0) | K18: =COUNTIF('2. Valoración '!$C$6:$C$2261,$C18) | L18: =IF($I18="No","No requiere valoración",IF($K18=0,"FALTA POR COMPLETO — agregar "&$J18&" filas",IF($K18<$J18,"INCOMPLETO — faltan "&($J18-$K18)&" filas",IF($K18>$J18,"REVISAR — hay filas de más","Completo"))))
B19: =IF(AND(OR($C$6="(Todos los procesos)",$C$6='1. Matriz de Activos'!$G$14),OR($C$7="(Todos los tipos)",$C$7='1. Matriz de Activos'!$E$14),OR($C$8="(Todos los subtipos)",$C$8='1. Matriz de Activos'!$F$14)),"Sí","No") | C19: ='1. Matriz de Activos'!$B$14 | D19: ='1. Matriz de Activos'!$C$14 | E19: ='1. Matriz de Activos'!$G$14 | F19: ='1. Matriz de Activos'!$E$14 | G19: ='1. Matriz de Activos'!$F$14 | H19: ='1. Matriz de Activos'!$T$14 | I19: =IF($H19>=4,"Sí","No") | J19: =IF($H19>=4,IFERROR(VLOOKUP($G19,AmenTabla,2,0),0),0) | K19: =COUNTIF('2. Valoración '!$C$6:$C$2261,$C19) | L19: =IF($I19="No","No requiere valoración",IF($K19=0,"FALTA POR COMPLETO — agregar "&$J19&" filas",IF($K19<$J19,"INCOMPLETO — faltan "&($J19-$K19)&" filas",IF($K19>$J19,"REVISAR — hay filas de más","Completo"))))
B20: =IF(AND(OR($C$6="(Todos los procesos)",$C$6='1. Matriz de Activos'!$G$15),OR($C$7="(Todos los tipos)",$C$7='1. Matriz de Activos'!$E$15),OR($C$8="(Todos los subtipos)",$C$8='1. Matriz de Activos'!$F$15)),"Sí","No") | C20: ='1. Matriz de Activos'!$B$15 | D20: ='1. Matriz de Activos'!$C$15 | E20: ='1. Matriz de Activos'!$G$15 | F20: ='1. Matriz de Activos'!$E$15 | G20: ='1. Matriz de Activos'!$F$15 | H20: ='1. Matriz de Activos'!$T$15 | I20: =IF($H20>=4,"Sí","No") | J20: =IF($H20>=4,IFERROR(VLOOKUP($G20,AmenTabla,2,0),0),0) | K20: =COUNTIF('2. Valoración '!$C$6:$C$2261,$C20) | L20: =IF($I20="No","No requiere valoración",IF($K20=0,"FALTA POR COMPLETO — agregar "&$J20&" filas",IF($K20<$J20,"INCOMPLETO — faltan "&($J20-$K20)&" filas",IF($K20>$J20,"REVISAR — hay filas de más","Completo"))))
B21: =IF(AND(OR($C$6="(Todos los procesos)",$C$6='1. Matriz de Activos'!$G$16),OR($C$7="(Todos los tipos)",$C$7='1. Matriz de Activos'!$E$16),OR($C$8="(Todos los subtipos)",$C$8='1. Matriz de Activos'!$F$16)),"Sí","No") | C21: ='1. Matriz de Activos'!$B$16 | D21: ='1. Matriz de Activos'!$C$16 | E21: ='1. Matriz de Activos'!$G$16 | F21: ='1. Matriz de Activos'!$E$16 | G21: ='1. Matriz de Activos'!$F$16 | H21: ='1. Matriz de Activos'!$T$16 | I21: =IF($H21>=4,"Sí","No") | J21: =IF($H21>=4,IFERROR(VLOOKUP($G21,AmenTabla,2,0),0),0) | K21: =COUNTIF('2. Valoración '!$C$6:$C$2261,$C21) | L21: =IF($I21="No","No requiere valoración",IF($K21=0,"FALTA POR COMPLETO — agregar "&$J21&" filas",IF($K21<$J21,"INCOMPLETO — faltan "&($J21-$K21)&" filas",IF($K21>$J21,"REVISAR — hay filas de más","Completo"))))
B22: =IF(AND(OR($C$6="(Todos los procesos)",$C$6='1. Matriz de Activos'!$G$17),OR($C$7="(Todos los tipos)",$C$7='1. Matriz de Activos'!$E$17),OR($C$8="(Todos los subtipos)",$C$8='1. Matriz de Activos'!$F$17)),"Sí","No") | C22: ='1. Matriz de Activos'!$B$17 | D22: ='1. Matriz de Activos'!$C$17 | E22: ='1. Matriz de Activos'!$G$17 | F22: ='1. Matriz de Activos'!$E$17 | G22: ='1. Matriz de Activos'!$F$17 | H22: ='1. Matriz de Activos'!$T$17 | I22: =IF($H22>=4,"Sí","No") | J22: =IF($H22>=4,IFERROR(VLOOKUP($G22,AmenTabla,2,0),0),0) | K22: =COUNTIF('2. Valoración '!$C$6:$C$2261,$C22) | L22: =IF($I22="No","No requiere valoración",IF($K22=0,"FALTA POR COMPLETO — agregar "&$J22&" filas",IF($K22<$J22,"INCOMPLETO — faltan "&($J22-$K22)&" filas",IF($K22>$J22,"REVISAR — hay filas de más","Completo"))))
B23: =IF(AND(OR($C$6="(Todos los procesos)",$C$6='1. Matriz de Activos'!$G$18),OR($C$7="(Todos los tipos)",$C$7='1. Matriz de Activos'!$E$18),OR($C$8="(Todos los subtipos)",$C$8='1. Matriz de Activos'!$F$18)),"Sí","No") | C23: ='1. Matriz de Activos'!$B$18 | D23: ='1. Matriz de Activos'!$C$18 | E23: ='1. Matriz de Activos'!$G$18 | F23: ='1. Matriz de Activos'!$E$18 | G23: ='1. Matriz de Activos'!$F$18 | H23: ='1. Matriz de Activos'!$T$18 | I23: =IF($H23>=4,"Sí","No") | J23: =IF($H23>=4,IFERROR(VLOOKUP($G23,AmenTabla,2,0),0),0) | K23: =COUNTIF('2. Valoración '!$C$6:$C$2261,$C23) | L23: =IF($I23="No","No requiere valoración",IF($K23=0,"FALTA POR COMPLETO — agregar "&$J23&" filas",IF($K23<$J23,"INCOMPLETO — faltan "&($J23-$K23)&" filas",IF($K23>$J23,"REVISAR — hay filas de más","Completo"))))
B24: =IF(AND(OR($C$6="(Todos los procesos)",$C$6='1. Matriz de Activos'!$G$19),OR($C$7="(Todos los tipos)",$C$7='1. Matriz de Activos'!$E$19),OR($C$8="(Todos los subtipos)",$C$8='1. Matriz de Activos'!$F$19)),"Sí","No") | C24: ='1. Matriz de Activos'!$B$19 | D24: ='1. Matriz de Activos'!$C$19 | E24: ='1. Matriz de Activos'!$G$19 | F24: ='1. Matriz de Activos'!$E$19 | G24: ='1. Matriz de Activos'!$F$19 | H24: ='1. Matriz de Activos'!$T$19 | I24: =IF($H24>=4,"Sí","No") | J24: =IF($H24>=4,IFERROR(VLOOKUP($G24,AmenTabla,2,0),0),0) | K24: =COUNTIF('2. Valoración '!$C$6:$C$2261,$C24) | L24: =IF($I24="No","No requiere valoración",IF($K24=0,"FALTA POR COMPLETO — agregar "&$J24&" filas",IF($K24<$J24,"INCOMPLETO — faltan "&($J24-$K24)&" filas",IF($K24>$J24,"REVISAR — hay filas de más","Completo"))))
B25: =IF(AND(OR($C$6="(Todos los procesos)",$C$6='1. Matriz de Activos'!$G$20),OR($C$7="(Todos los tipos)",$C$7='1. Matriz de Activos'!$E$20),OR($C$8="(Todos los subtipos)",$C$8='1. Matriz de Activos'!$F$20)),"Sí","No") | C25: ='1. Matriz de Activos'!$B$20 | D25: ='1. Matriz de Activos'!$C$20 | E25: ='1. Matriz de Activos'!$G$20 | F25: ='1. Matriz de Activos'!$E$20 | G25: ='1. Matriz de Activos'!$F$20 | H25: ='1. Matriz de Activos'!$T$20 | I25: =IF($H25>=4,"Sí","No") | J25: =IF($H25>=4,IFERROR(VLOOKUP($G25,AmenTabla,2,0),0),0) | K25: =COUNTIF('2. Valoración '!$C$6:$C$2261,$C25) | L25: =IF($I25="No","No requiere valoración",IF($K25=0,"FALTA POR COMPLETO — agregar "&$J25&" filas",IF($K25<$J25,"INCOMPLETO — faltan "&($J25-$K25)&" filas",IF($K25>$J25,"REVISAR — hay filas de más","Completo"))))
B26: =IF(AND(OR($C$6="(Todos los procesos)",$C$6='1. Matriz de Activos'!$G$21),OR($C$7="(Todos los tipos)",$C$7='1. Matriz de Activos'!$E$21),OR($C$8="(Todos los subtipos)",$C$8='1. Matriz de Activos'!$F$21)),"Sí","No") | C26: ='1. Matriz de Activos'!$B$21 | D26: ='1. Matriz de Activos'!$C$21 | E26: ='1. Matriz de Activos'!$G$21 | F26: ='1. Matriz de Activos'!$E$21 | G26: ='1. Matriz de Activos'!$F$21 | H26: ='1. Matriz de Activos'!$T$21 | I26: =IF($H26>=4,"Sí","No") | J26: =IF($H26>=4,IFERROR(VLOOKUP($G26,AmenTabla,2,0),0),0) | K26: =COUNTIF('2. Valoración '!$C$6:$C$2261,$C26) | L26: =IF($I26="No","No requiere valoración",IF($K26=0,"FALTA POR COMPLETO — agregar "&$J26&" filas",IF($K26<$J26,"INCOMPLETO — faltan "&($J26-$K26)&" filas",IF($K26>$J26,"REVISAR — hay filas de más","Completo"))))
B27: =IF(AND(OR($C$6="(Todos los procesos)",$C$6='1. Matriz de Activos'!$G$22),OR($C$7="(Todos los tipos)",$C$7='1. Matriz de Activos'!$E$22),OR($C$8="(Todos los subtipos)",$C$8='1. Matriz de Activos'!$F$22)),"Sí","No") | C27: ='1. Matriz de Activos'!$B$22 | D27: ='1. Matriz de Activos'!$C$22 | E27: ='1. Matriz de Activos'!$G$22 | F27: ='1. Matriz de Activos'!$E$22 | G27: ='1. Matriz de Activos'!$F$22 | H27: ='1. Matriz de Activos'!$T$22 | I27: =IF($H27>=4,"Sí","No") | J27: =IF($H27>=4,IFERROR(VLOOKUP($G27,AmenTabla,2,0),0),0) | K27: =COUNTIF('2. Valoración '!$C$6:$C$2261,$C27) | L27: =IF($I27="No","No requiere valoración",IF($K27=0,"FALTA POR COMPLETO — agregar "&$J27&" filas",IF($K27<$J27,"INCOMPLETO — faltan "&($J27-$K27)&" filas",IF($K27>$J27,"REVISAR — hay filas de más","Completo"))))
B28: =IF(AND(OR($C$6="(Todos los procesos)",$C$6='1. Matriz de Activos'!$G$23),OR($C$7="(Todos los tipos)",$C$7='1. Matriz de Activos'!$E$23),OR($C$8="(Todos los subtipos)",$C$8='1. Matriz de Activos'!$F$23)),"Sí","No") | C28: ='1. Matriz de Activos'!$B$23 | D28: ='1. Matriz de Activos'!$C$23 | E28: ='1. Matriz de Activos'!$G$23 | F28: ='1. Matriz de Activos'!$E$23 | G28: ='1. Matriz de Activos'!$F$23 | H28: ='1. Matriz de Activos'!$T$23 | I28: =IF($H28>=4,"Sí","No") | J28: =IF($H28>=4,IFERROR(VLOOKUP($G28,AmenTabla,2,0),0),0) | K28: =COUNTIF('2. Valoración '!$C$6:$C$2261,$C28) | L28: =IF($I28="No","No requiere valoración",IF($K28=0,"FALTA POR COMPLETO — agregar "&$J28&" filas",IF($K28<$J28,"INCOMPLETO — faltan "&($J28-$K28)&" filas",IF($K28>$J28,"REVISAR — hay filas de más","Completo"))))
B29: =IF(AND(OR($C$6="(Todos los procesos)",$C$6='1. Matriz de Activos'!$G$24),OR($C$7="(Todos los tipos)",$C$7='1. Matriz de Activos'!$E$24),OR($C$8="(Todos los subtipos)",$C$8='1. Matriz de Activos'!$F$24)),"Sí","No") | C29: ='1. Matriz de Activos'!$B$24 | D29: ='1. Matriz de Activos'!$C$24 | E29: ='1. Matriz de Activos'!$G$24 | F29: ='1. Matriz de Activos'!$E$24 | G29: ='1. Matriz de Activos'!$F$24 | H29: ='1. Matriz de Activos'!$T$24 | I29: =IF($H29>=4,"Sí","No") | J29: =IF($H29>=4,IFERROR(VLOOKUP($G29,AmenTabla,2,0),0),0) | K29: =COUNTIF('2. Valoración '!$C$6:$C$2261,$C29) | L29: =IF($I29="No","No requiere valoración",IF($K29=0,"FALTA POR COMPLETO — agregar "&$J29&" filas",IF($K29<$J29,"INCOMPLETO — faltan "&($J29-$K29)&" filas",IF($K29>$J29,"REVISAR — hay filas de más","Completo"))))
B30: =IF(AND(OR($C$6="(Todos los procesos)",$C$6='1. Matriz de Activos'!$G$25),OR($C$7="(Todos los tipos)",$C$7='1. Matriz de Activos'!$E$25),OR($C$8="(Todos los subtipos)",$C$8='1. Matriz de Activos'!$F$25)),"Sí","No") | C30: ='1. Matriz de Activos'!$B$25 | D30: ='1. Matriz de Activos'!$C$25 | E30: ='1. Matriz de Activos'!$G$25 | F30: ='1. Matriz de Activos'!$E$25 | G30: ='1. Matriz de Activos'!$F$25 | H30: ='1. Matriz de Activos'!$T$25 | I30: =IF($H30>=4,"Sí","No") | J30: =IF($H30>=4,IFERROR(VLOOKUP($G30,AmenTabla,2,0),0),0) | K30: =COUNTIF('2. Valoración '!$C$6:$C$2261,$C30) | L30: =IF($I30="No","No requiere valoración",IF($K30=0,"FALTA POR COMPLETO — agregar "&$J30&" filas",IF($K30<$J30,"INCOMPLETO — faltan "&($J30-$K30)&" filas",IF($K30>$J30,"REVISAR — hay filas de más","Completo"))))
B31: =IF(AND(OR($C$6="(Todos los procesos)",$C$6='1. Matriz de Activos'!$G$26),OR($C$7="(Todos los tipos)",$C$7='1. Matriz de Activos'!$E$26),OR($C$8="(Todos los subtipos)",$C$8='1. Matriz de Activos'!$F$26)),"Sí","No") | C31: ='1. Matriz de Activos'!$B$26 | D31: ='1. Matriz de Activos'!$C$26 | E31: ='1. Matriz de Activos'!$G$26 | F31: ='1. Matriz de Activos'!$E$26 | G31: ='1. Matriz de Activos'!$F$26 | H31: ='1. Matriz de Activos'!$T$26 | I31: =IF($H31>=4,"Sí","No") | J31: =IF($H31>=4,IFERROR(VLOOKUP($G31,AmenTabla,2,0),0),0) | K31: =COUNTIF('2. Valoración '!$C$6:$C$2261,$C31) | L31: =IF($I31="No","No requiere valoración",IF($K31=0,"FALTA POR COMPLETO — agregar "&$J31&" filas",IF($K31<$J31,"INCOMPLETO — faltan "&($J31-$K31)&" filas",IF($K31>$J31,"REVISAR — hay filas de más","Completo"))))
B32: =IF(AND(OR($C$6="(Todos los procesos)",$C$6='1. Matriz de Activos'!$G$27),OR($C$7="(Todos los tipos)",$C$7='1. Matriz de Activos'!$E$27),OR($C$8="(Todos los subtipos)",$C$8='1. Matriz de Activos'!$F$27)),"Sí","No") | C32: ='1. Matriz de Activos'!$B$27 | D32: ='1. Matriz de Activos'!$C$27 | E32: ='1. Matriz de Activos'!$G$27 | F32: ='1. Matriz de Activos'!$E$27 | G32: ='1. Matriz de Activos'!$F$27 | H32: ='1. Matriz de Activos'!$T$27 | I32: =IF($H32>=4,"Sí","No") | J32: =IF($H32>=4,IFERROR(VLOOKUP($G32,AmenTabla,2,0),0),0) | K32: =COUNTIF('2. Valoración '!$C$6:$C$2261,$C32) | L32: =IF($I32="No","No requiere valoración",IF($K32=0,"FALTA POR COMPLETO — agregar "&$J32&" filas",IF($K32<$J32,"INCOMPLETO — faltan "&($J32-$K32)&" filas",IF($K32>$J32,"REVISAR — hay filas de más","Completo"))))
B33: =IF(AND(OR($C$6="(Todos los procesos)",$C$6='1. Matriz de Activos'!$G$28),OR($C$7="(Todos los tipos)",$C$7='1. Matriz de Activos'!$E$28),OR($C$8="(Todos los subtipos)",$C$8='1. Matriz de Activos'!$F$28)),"Sí","No") | C33: ='1. Matriz de Activos'!$B$28 | D33: ='1. Matriz de Activos'!$C$28 | E33: ='1. Matriz de Activos'!$G$28 | F33: ='1. Matriz de Activos'!$E$28 | G33: ='1. Matriz de Activos'!$F$28 | H33: ='1. Matriz de Activos'!$T$28 | I33: =IF($H33>=4,"Sí","No") | J33: =IF($H33>=4,IFERROR(VLOOKUP($G33,AmenTabla,2,0),0),0) | K33: =COUNTIF('2. Valoración '!$C$6:$C$2261,$C33) | L33: =IF($I33="No","No requiere valoración",IF($K33=0,"FALTA POR COMPLETO — agregar "&$J33&" filas",IF($K33<$J33,"INCOMPLETO — faltan "&($J33-$K33)&" filas",IF($K33>$J33,"REVISAR — hay filas de más","Completo"))))
B34: =IF(AND(OR($C$6="(Todos los procesos)",$C$6='1. Matriz de Activos'!$G$29),OR($C$7="(Todos los tipos)",$C$7='1. Matriz de Activos'!$E$29),OR($C$8="(Todos los subtipos)",$C$8='1. Matriz de Activos'!$F$29)),"Sí","No") | C34: ='1. Matriz de Activos'!$B$29 | D34: ='1. Matriz de Activos'!$C$29 | E34: ='1. Matriz de Activos'!$G$29 | F34: ='1. Matriz de Activos'!$E$29 | G34: ='1. Matriz de Activos'!$F$29 | H34: ='1. Matriz de Activos'!$T$29 | I34: =IF($H34>=4,"Sí","No") | J34: =IF($H34>=4,IFERROR(VLOOKUP($G34,AmenTabla,2,0),0),0) | K34: =COUNTIF('2. Valoración '!$C$6:$C$2261,$C34) | L34: =IF($I34="No","No requiere valoración",IF($K34=0,"FALTA POR COMPLETO — agregar "&$J34&" filas",IF($K34<$J34,"INCOMPLETO — faltan "&($J34-$K34)&" filas",IF($K34>$J34,"REVISAR — hay filas de más","Completo"))))
B35: =IF(AND(OR($C$6="(Todos los procesos)",$C$6='1. Matriz de Activos'!$G$30),OR($C$7="(Todos los tipos)",$C$7='1. Matriz de Activos'!$E$30),OR($C$8="(Todos los subtipos)",$C$8='1. Matriz de Activos'!$F$30)),"Sí","No") | C35: ='1. Matriz de Activos'!$B$30 | D35: ='1. Matriz de Activos'!$C$30 | E35: ='1. Matriz de Activos'!$G$30 | F35: ='1. Matriz de Activos'!$E$30 | G35: ='1. Matriz de Activos'!$F$30 | H35: ='1. Matriz de Activos'!$T$30 | I35: =IF($H35>=4,"Sí","No") | J35: =IF($H35>=4,IFERROR(VLOOKUP($G35,AmenTabla,2,0),0),0) | K35: =COUNTIF('2. Valoración '!$C$6:$C$2261,$C35) | L35: =IF($I35="No","No requiere valoración",IF($K35=0,"FALTA POR COMPLETO — agregar "&$J35&" filas",IF($K35<$J35,"INCOMPLETO — faltan "&($J35-$K35)&" filas",IF($K35>$J35,"REVISAR — hay filas de más","Completo"))))
B36: =IF(AND(OR($C$6="(Todos los procesos)",$C$6='1. Matriz de Activos'!$G$31),OR($C$7="(Todos los tipos)",$C$7='1. Matriz de Activos'!$E$31),OR($C$8="(Todos los subtipos)",$C$8='1. Matriz de Activos'!$F$31)),"Sí","No") | C36: ='1. Matriz de Activos'!$B$31 | D36: ='1. Matriz de Activos'!$C$31 | E36: ='1. Matriz de Activos'!$G$31 | F36: ='1. Matriz de Activos'!$E$31 | G36: ='1. Matriz de Activos'!$F$31 | H36: ='1. Matriz de Activos'!$T$31 | I36: =IF($H36>=4,"Sí","No") | J36: =IF($H36>=4,IFERROR(VLOOKUP($G36,AmenTabla,2,0),0),0) | K36: =COUNTIF('2. Valoración '!$C$6:$C$2261,$C36) | L36: =IF($I36="No","No requiere valoración",IF($K36=0,"FALTA POR COMPLETO — agregar "&$J36&" filas",IF($K36<$J36,"INCOMPLETO — faltan "&($J36-$K36)&" filas",IF($K36>$J36,"REVISAR — hay filas de más","Completo"))))
B37: =IF(AND(OR($C$6="(Todos los procesos)",$C$6='1. Matriz de Activos'!$G$32),OR($C$7="(Todos los tipos)",$C$7='1. Matriz de Activos'!$E$32),OR($C$8="(Todos los subtipos)",$C$8='1. Matriz de Activos'!$F$32)),"Sí","No") | C37: ='1. Matriz de Activos'!$B$32 | D37: ='1. Matriz de Activos'!$C$32 | E37: ='1. Matriz de Activos'!$G$32 | F37: ='1. Matriz de Activos'!$E$32 | G37: ='1. Matriz de Activos'!$F$32 | H37: ='1. Matriz de Activos'!$T$32 | I37: =IF($H37>=4,"Sí","No") | J37: =IF($H37>=4,IFERROR(VLOOKUP($G37,AmenTabla,2,0),0),0) | K37: =COUNTIF('2. Valoración '!$C$6:$C$2261,$C37) | L37: =IF($I37="No","No requiere valoración",IF($K37=0,"FALTA POR COMPLETO — agregar "&$J37&" filas",IF($K37<$J37,"INCOMPLETO — faltan "&($J37-$K37)&" filas",IF($K37>$J37,"REVISAR — hay filas de más","Completo"))))
B38: =IF(AND(OR($C$6="(Todos los procesos)",$C$6='1. Matriz de Activos'!$G$33),OR($C$7="(Todos los tipos)",$C$7='1. Matriz de Activos'!$E$33),OR($C$8="(Todos los subtipos)",$C$8='1. Matriz de Activos'!$F$33)),"Sí","No") | C38: ='1. Matriz de Activos'!$B$33 | D38: ='1. Matriz de Activos'!$C$33 | E38: ='1. Matriz de Activos'!$G$33 | F38: ='1. Matriz de Activos'!$E$33 | G38: ='1. Matriz de Activos'!$F$33 | H38: ='1. Matriz de Activos'!$T$33 | I38: =IF($H38>=4,"Sí","No") | J38: =IF($H38>=4,IFERROR(VLOOKUP($G38,AmenTabla,2,0),0),0) | K38: =COUNTIF('2. Valoración '!$C$6:$C$2261,$C38) | L38: =IF($I38="No","No requiere valoración",IF($K38=0,"FALTA POR COMPLETO — agregar "&$J38&" filas",IF($K38<$J38,"INCOMPLETO — faltan "&($J38-$K38)&" filas",IF($K38>$J38,"REVISAR — hay filas de más","Completo"))))
B39: =IF(AND(OR($C$6="(Todos los procesos)",$C$6='1. Matriz de Activos'!$G$34),OR($C$7="(Todos los tipos)",$C$7='1. Matriz de Activos'!$E$34),OR($C$8="(Todos los subtipos)",$C$8='1. Matriz de Activos'!$F$34)),"Sí","No") | C39: ='1. Matriz de Activos'!$B$34 | D39: ='1. Matriz de Activos'!$C$34 | E39: ='1. Matriz de Activos'!$G$34 | F39: ='1. Matriz de Activos'!$E$34 | G39: ='1. Matriz de Activos'!$F$34 | H39: ='1. Matriz de Activos'!$T$34 | I39: =IF($H39>=4,"Sí","No") | J39: =IF($H39>=4,IFERROR(VLOOKUP($G39,AmenTabla,2,0),0),0) | K39: =COUNTIF('2. Valoración '!$C$6:$C$2261,$C39) | L39: =IF($I39="No","No requiere valoración",IF($K39=0,"FALTA POR COMPLETO — agregar "&$J39&" filas",IF($K39<$J39,"INCOMPLETO — faltan "&($J39-$K39)&" filas",IF($K39>$J39,"REVISAR — hay filas de más","Completo"))))
B40: =IF(AND(OR($C$6="(Todos los procesos)",$C$6='1. Matriz de Activos'!$G$35),OR($C$7="(Todos los tipos)",$C$7='1. Matriz de Activos'!$E$35),OR($C$8="(Todos los subtipos)",$C$8='1. Matriz de Activos'!$F$35)),"Sí","No") | C40: ='1. Matriz de Activos'!$B$35 | D40: ='1. Matriz de Activos'!$C$35 | E40: ='1. Matriz de Activos'!$G$35 | F40: ='1. Matriz de Activos'!$E$35 | G40: ='1. Matriz de Activos'!$F$35 | H40: ='1. Matriz de Activos'!$T$35 | I40: =IF($H40>=4,"Sí","No") | J40: =IF($H40>=4,IFERROR(VLOOKUP($G40,AmenTabla,2,0),0),0) | K40: =COUNTIF('2. Valoración '!$C$6:$C$2261,$C40) | L40: =IF($I40="No","No requiere valoración",IF($K40=0,"FALTA POR COMPLETO — agregar "&$J40&" filas",IF($K40<$J40,"INCOMPLETO — faltan "&($J40-$K40)&" filas",IF($K40>$J40,"REVISAR — hay filas de más","Completo"))))
B41: =IF(AND(OR($C$6="(Todos los procesos)",$C$6='1. Matriz de Activos'!$G$36),OR($C$7="(Todos los tipos)",$C$7='1. Matriz de Activos'!$E$36),OR($C$8="(Todos los subtipos)",$C$8='1. Matriz de Activos'!$F$36)),"Sí","No") | C41: ='1. Matriz de Activos'!$B$36 | D41: ='1. Matriz de Activos'!$C$36 | E41: ='1. Matriz de Activos'!$G$36 | F41: ='1. Matriz de Activos'!$E$36 | G41: ='1. Matriz de Activos'!$F$36 | H41: ='1. Matriz de Activos'!$T$36 | I41: =IF($H41>=4,"Sí","No") | J41: =IF($H41>=4,IFERROR(VLOOKUP($G41,AmenTabla,2,0),0),0) | K41: =COUNTIF('2. Valoración '!$C$6:$C$2261,$C41) | L41: =IF($I41="No","No requiere valoración",IF($K41=0,"FALTA POR COMPLETO — agregar "&$J41&" filas",IF($K41<$J41,"INCOMPLETO — faltan "&($J41-$K41)&" filas",IF($K41>$J41,"REVISAR — hay filas de más","Completo"))))
B42: =IF(AND(OR($C$6="(Todos los procesos)",$C$6='1. Matriz de Activos'!$G$37),OR($C$7="(Todos los tipos)",$C$7='1. Matriz de Activos'!$E$37),OR($C$8="(Todos los subtipos)",$C$8='1. Matriz de Activos'!$F$37)),"Sí","No") | C42: ='1. Matriz de Activos'!$B$37 | D42: ='1. Matriz de Activos'!$C$37 | E42: ='1. Matriz de Activos'!$G$37 | F42: ='1. Matriz de Activos'!$E$37 | G42: ='1. Matriz de Activos'!$F$37 | H42: ='1. Matriz de Activos'!$T$37 | I42: =IF($H42>=4,"Sí","No") | J42: =IF($H42>=4,IFERROR(VLOOKUP($G42,AmenTabla,2,0),0),0) | K42: =COUNTIF('2. Valoración '!$C$6:$C$2261,$C42) | L42: =IF($I42="No","No requiere valoración",IF($K42=0,"FALTA POR COMPLETO — agregar "&$J42&" filas",IF($K42<$J42,"INCOMPLETO — faltan "&($J42-$K42)&" filas",IF($K42>$J42,"REVISAR — hay filas de más","Completo"))))
B43: =IF(AND(OR($C$6="(Todos los procesos)",$C$6='1. Matriz de Activos'!$G$38),OR($C$7="(Todos los tipos)",$C$7='1. Matriz de Activos'!$E$38),OR($C$8="(Todos los subtipos)",$C$8='1. Matriz de Activos'!$F$38)),"Sí","No") | C43: ='1. Matriz de Activos'!$B$38 | D43: ='1. Matriz de Activos'!$C$38 | E43: ='1. Matriz de Activos'!$G$38 | F43: ='1. Matriz de Activos'!$E$38 | G43: ='1. Matriz de Activos'!$F$38 | H43: ='1. Matriz de Activos'!$T$38 | I43: =IF($H43>=4,"Sí","No") | J43: =IF($H43>=4,IFERROR(VLOOKUP($G43,AmenTabla,2,0),0),0) | K43: =COUNTIF('2. Valoración '!$C$6:$C$2261,$C43) | L43: =IF($I43="No","No requiere valoración",IF($K43=0,"FALTA POR COMPLETO — agregar "&$J43&" filas",IF($K43<$J43,"INCOMPLETO — faltan "&($J43-$K43)&" filas",IF($K43>$J43,"REVISAR — hay filas de más","Completo"))))
B44: =IF(AND(OR($C$6="(Todos los procesos)",$C$6='1. Matriz de Activos'!$G$39),OR($C$7="(Todos los tipos)",$C$7='1. Matriz de Activos'!$E$39),OR($C$8="(Todos los subtipos)",$C$8='1. Matriz de Activos'!$F$39)),"Sí","No") | C44: ='1. Matriz de Activos'!$B$39 | D44: ='1. Matriz de Activos'!$C$39 | E44: ='1. Matriz de Activos'!$G$39 | F44: ='1. Matriz de Activos'!$E$39 | G44: ='1. Matriz de Activos'!$F$39 | H44: ='1. Matriz de Activos'!$T$39 | I44: =IF($H44>=4,"Sí","No") | J44: =IF($H44>=4,IFERROR(VLOOKUP($G44,AmenTabla,2,0),0),0) | K44: =COUNTIF('2. Valoración '!$C$6:$C$2261,$C44) | L44: =IF($I44="No","No requiere valoración",IF($K44=0,"FALTA POR COMPLETO — agregar "&$J44&" filas",IF($K44<$J44,"INCOMPLETO — faltan "&($J44-$K44)&" filas",IF($K44>$J44,"REVISAR — hay filas de más","Completo"))))
B45: =IF(AND(OR($C$6="(Todos los procesos)",$C$6='1. Matriz de Activos'!$G$40),OR($C$7="(Todos los tipos)",$C$7='1. Matriz de Activos'!$E$40),OR($C$8="(Todos los subtipos)",$C$8='1. Matriz de Activos'!$F$40)),"Sí","No") | C45: ='1. Matriz de Activos'!$B$40 | D45: ='1. Matriz de Activos'!$C$40 | E45: ='1. Matriz de Activos'!$G$40 | F45: ='1. Matriz de Activos'!$E$40 | G45: ='1. Matriz de Activos'!$F$40 | H45: ='1. Matriz de Activos'!$T$40 | I45: =IF($H45>=4,"Sí","No") | J45: =IF($H45>=4,IFERROR(VLOOKUP($G45,AmenTabla,2,0),0),0) | K45: =COUNTIF('2. Valoración '!$C$6:$C$2261,$C45) | L45: =IF($I45="No","No requiere valoración",IF($K45=0,"FALTA POR COMPLETO — agregar "&$J45&" filas",IF($K45<$J45,"INCOMPLETO — faltan "&($J45-$K45)&" filas",IF($K45>$J45,"REVISAR — hay filas de más","Completo"))))
B46: =IF(AND(OR($C$6="(Todos los procesos)",$C$6='1. Matriz de Activos'!$G$41),OR($C$7="(Todos los tipos)",$C$7='1. Matriz de Activos'!$E$41),OR($C$8="(Todos los subtipos)",$C$8='1. Matriz de Activos'!$F$41)),"Sí","No") | C46: ='1. Matriz de Activos'!$B$41 | D46: ='1. Matriz de Activos'!$C$41 | E46: ='1. Matriz de Activos'!$G$41 | F46: ='1. Matriz de Activos'!$E$41 | G46: ='1. Matriz de Activos'!$F$41 | H46: ='1. Matriz de Activos'!$T$41 | I46: =IF($H46>=4,"Sí","No") | J46: =IF($H46>=4,IFERROR(VLOOKUP($G46,AmenTabla,2,0),0),0) | K46: =COUNTIF('2. Valoración '!$C$6:$C$2261,$C46) | L46: =IF($I46="No","No requiere valoración",IF($K46=0,"FALTA POR COMPLETO — agregar "&$J46&" filas",IF($K46<$J46,"INCOMPLETO — faltan "&($J46-$K46)&" filas",IF($K46>$J46,"REVISAR — hay filas de más","Completo"))))
B47: =IF(AND(OR($C$6="(Todos los procesos)",$C$6='1. Matriz de Activos'!$G$42),OR($C$7="(Todos los tipos)",$C$7='1. Matriz de Activos'!$E$42),OR($C$8="(Todos los subtipos)",$C$8='1. Matriz de Activos'!$F$42)),"Sí","No") | C47: ='1. Matriz de Activos'!$B$42 | D47: ='1. Matriz de Activos'!$C$42 | E47: ='1. Matriz de Activos'!$G$42 | F47: ='1. Matriz de Activos'!$E$42 | G47: ='1. Matriz de Activos'!$F$42 | H47: ='1. Matriz de Activos'!$T$42 | I47: =IF($H47>=4,"Sí","No") | J47: =IF($H47>=4,IFERROR(VLOOKUP($G47,AmenTabla,2,0),0),0) | K47: =COUNTIF('2. Valoración '!$C$6:$C$2261,$C47) | L47: =IF($I47="No","No requiere valoración",IF($K47=0,"FALTA POR COMPLETO — agregar "&$J47&" filas",IF($K47<$J47,"INCOMPLETO — faltan "&($J47-$K47)&" filas",IF($K47>$J47,"REVISAR — hay filas de más","Completo"))))
B48: =IF(AND(OR($C$6="(Todos los procesos)",$C$6='1. Matriz de Activos'!$G$43),OR($C$7="(Todos los tipos)",$C$7='1. Matriz de Activos'!$E$43),OR($C$8="(Todos los subtipos)",$C$8='1. Matriz de Activos'!$F$43)),"Sí","No") | C48: ='1. Matriz de Activos'!$B$43 | D48: ='1. Matriz de Activos'!$C$43 | E48: ='1. Matriz de Activos'!$G$43 | F48: ='1. Matriz de Activos'!$E$43 | G48: ='1. Matriz de Activos'!$F$43 | H48: ='1. Matriz de Activos'!$T$43 | I48: =IF($H48>=4,"Sí","No") | J48: =IF($H48>=4,IFERROR(VLOOKUP($G48,AmenTabla,2,0),0),0) | K48: =COUNTIF('2. Valoración '!$C$6:$C$2261,$C48) | L48: =IF($I48="No","No requiere valoración",IF($K48=0,"FALTA POR COMPLETO — agregar "&$J48&" filas",IF($K48<$J48,"INCOMPLETO — faltan "&($J48-$K48)&" filas",IF($K48>$J48,"REVISAR — hay filas de más","Completo"))))
B49: =IF(AND(OR($C$6="(Todos los procesos)",$C$6='1. Matriz de Activos'!$G$44),OR($C$7="(Todos los tipos)",$C$7='1. Matriz de Activos'!$E$44),OR($C$8="(Todos los subtipos)",$C$8='1. Matriz de Activos'!$F$44)),"Sí","No") | C49: ='1. Matriz de Activos'!$B$44 | D49: ='1. Matriz de Activos'!$C$44 | E49: ='1. Matriz de Activos'!$G$44 | F49: ='1. Matriz de Activos'!$E$44 | G49: ='1. Matriz de Activos'!$F$44 | H49: ='1. Matriz de Activos'!$T$44 | I49: =IF($H49>=4,"Sí","No") | J49: =IF($H49>=4,IFERROR(VLOOKUP($G49,AmenTabla,2,0),0),0) | K49: =COUNTIF('2. Valoración '!$C$6:$C$2261,$C49) | L49: =IF($I49="No","No requiere valoración",IF($K49=0,"FALTA POR COMPLETO — agregar "&$J49&" filas",IF($K49<$J49,"INCOMPLETO — faltan "&($J49-$K49)&" filas",IF($K49>$J49,"REVISAR — hay filas de más","Completo"))))
B50: =IF(AND(OR($C$6="(Todos los procesos)",$C$6='1. Matriz de Activos'!$G$45),OR($C$7="(Todos los tipos)",$C$7='1. Matriz de Activos'!$E$45),OR($C$8="(Todos los subtipos)",$C$8='1. Matriz de Activos'!$F$45)),"Sí","No") | C50: ='1. Matriz de Activos'!$B$45 | D50: ='1. Matriz de Activos'!$C$45 | E50: ='1. Matriz de Activos'!$G$45 | F50: ='1. Matriz de Activos'!$E$45 | G50: ='1. Matriz de Activos'!$F$45 | H50: ='1. Matriz de Activos'!$T$45 | I50: =IF($H50>=4,"Sí","No") | J50: =IF($H50>=4,IFERROR(VLOOKUP($G50,AmenTabla,2,0),0),0) | K50: =COUNTIF('2. Valoración '!$C$6:$C$2261,$C50) | L50: =IF($I50="No","No requiere valoración",IF($K50=0,"FALTA POR COMPLETO — agregar "&$J50&" filas",IF($K50<$J50,"INCOMPLETO — faltan "&($J50-$K50)&" filas",IF($K50>$J50,"REVISAR — hay filas de más","Completo"))))
B51: =IF(AND(OR($C$6="(Todos los procesos)",$C$6='1. Matriz de Activos'!$G$46),OR($C$7="(Todos los tipos)",$C$7='1. Matriz de Activos'!$E$46),OR($C$8="(Todos los subtipos)",$C$8='1. Matriz de Activos'!$F$46)),"Sí","No") | C51: ='1. Matriz de Activos'!$B$46 | D51: ='1. Matriz de Activos'!$C$46 | E51: ='1. Matriz de Activos'!$G$46 | F51: ='1. Matriz de Activos'!$E$46 | G51: ='1. Matriz de Activos'!$F$46 | H51: ='1. Matriz de Activos'!$T$46 | I51: =IF($H51>=4,"Sí","No") | J51: =IF($H51>=4,IFERROR(VLOOKUP($G51,AmenTabla,2,0),0),0) | K51: =COUNTIF('2. Valoración '!$C$6:$C$2261,$C51) | L51: =IF($I51="No","No requiere valoración",IF($K51=0,"FALTA POR COMPLETO — agregar "&$J51&" filas",IF($K51<$J51,"INCOMPLETO — faltan "&($J51-$K51)&" filas",IF($K51>$J51,"REVISAR — hay filas de más","Completo"))))
B52: =IF(AND(OR($C$6="(Todos los procesos)",$C$6='1. Matriz de Activos'!$G$47),OR($C$7="(Todos los tipos)",$C$7='1. Matriz de Activos'!$E$47),OR($C$8="(Todos los subtipos)",$C$8='1. Matriz de Activos'!$F$47)),"Sí","No") | C52: ='1. Matriz de Activos'!$B$47 | D52: ='1. Matriz de Activos'!$C$47 | E52: ='1. Matriz de Activos'!$G$47 | F52: ='1. Matriz de Activos'!$E$47 | G52: ='1. Matriz de Activos'!$F$47 | H52: ='1. Matriz de Activos'!$T$47 | I52: =IF($H52>=4,"Sí","No") | J52: =IF($H52>=4,IFERROR(VLOOKUP($G52,AmenTabla,2,0),0),0) | K52: =COUNTIF('2. Valoración '!$C$6:$C$2261,$C52) | L52: =IF($I52="No","No requiere valoración",IF($K52=0,"FALTA POR COMPLETO — agregar "&$J52&" filas",IF($K52<$J52,"INCOMPLETO — faltan "&($J52-$K52)&" filas",IF($K52>$J52,"REVISAR — hay filas de más","Completo"))))
B53: =IF(AND(OR($C$6="(Todos los procesos)",$C$6='1. Matriz de Activos'!$G$48),OR($C$7="(Todos los tipos)",$C$7='1. Matriz de Activos'!$E$48),OR($C$8="(Todos los subtipos)",$C$8='1. Matriz de Activos'!$F$48)),"Sí","No") | C53: ='1. Matriz de Activos'!$B$48 | D53: ='1. Matriz de Activos'!$C$48 | E53: ='1. Matriz de Activos'!$G$48 | F53: ='1. Matriz de Activos'!$E$48 | G53: ='1. Matriz de Activos'!$F$48 | H53: ='1. Matriz de Activos'!$T$48 | I53: =IF($H53>=4,"Sí","No") | J53: =IF($H53>=4,IFERROR(VLOOKUP($G53,AmenTabla,2,0),0),0) | K53: =COUNTIF('2. Valoración '!$C$6:$C$2261,$C53) | L53: =IF($I53="No","No requiere valoración",IF($K53=0,"FALTA POR COMPLETO — agregar "&$J53&" filas",IF($K53<$J53,"INCOMPLETO — faltan "&($J53-$K53)&" filas",IF($K53>$J53,"REVISAR — hay filas de más","Completo"))))
B54: =IF(AND(OR($C$6="(Todos los procesos)",$C$6='1. Matriz de Activos'!$G$49),OR($C$7="(Todos los tipos)",$C$7='1. Matriz de Activos'!$E$49),OR($C$8="(Todos los subtipos)",$C$8='1. Matriz de Activos'!$F$49)),"Sí","No") | C54: ='1. Matriz de Activos'!$B$49 | D54: ='1. Matriz de Activos'!$C$49 | E54: ='1. Matriz de Activos'!$G$49 | F54: ='1. Matriz de Activos'!$E$49 | G54: ='1. Matriz de Activos'!$F$49 | H54: ='1. Matriz de Activos'!$T$49 | I54: =IF($H54>=4,"Sí","No") | J54: =IF($H54>=4,IFERROR(VLOOKUP($G54,AmenTabla,2,0),0),0) | K54: =COUNTIF('2. Valoración '!$C$6:$C$2261,$C54) | L54: =IF($I54="No","No requiere valoración",IF($K54=0,"FALTA POR COMPLETO — agregar "&$J54&" filas",IF($K54<$J54,"INCOMPLETO — faltan "&($J54-$K54)&" filas",IF($K54>$J54,"REVISAR — hay filas de más","Completo"))))
B55: =IF(AND(OR($C$6="(Todos los procesos)",$C$6='1. Matriz de Activos'!$G$50),OR($C$7="(Todos los tipos)",$C$7='1. Matriz de Activos'!$E$50),OR($C$8="(Todos los subtipos)",$C$8='1. Matriz de Activos'!$F$50)),"Sí","No") | C55: ='1. Matriz de Activos'!$B$50 | D55: ='1. Matriz de Activos'!$C$50 | E55: ='1. Matriz de Activos'!$G$50 | F55: ='1. Matriz de Activos'!$E$50 | G55: ='1. Matriz de Activos'!$F$50 | H55: ='1. Matriz de Activos'!$T$50 | I55: =IF($H55>=4,"Sí","No") | J55: =IF($H55>=4,IFERROR(VLOOKUP($G55,AmenTabla,2,0),0),0) | K55: =COUNTIF('2. Valoración '!$C$6:$C$2261,$C55) | L55: =IF($I55="No","No requiere valoración",IF($K55=0,"FALTA POR COMPLETO — agregar "&$J55&" filas",IF($K55<$J55,"INCOMPLETO — faltan "&($J55-$K55)&" filas",IF($K55>$J55,"REVISAR — hay filas de más","Completo"))))
B56: =IF(AND(OR($C$6="(Todos los procesos)",$C$6='1. Matriz de Activos'!$G$51),OR($C$7="(Todos los tipos)",$C$7='1. Matriz de Activos'!$E$51),OR($C$8="(Todos los subtipos)",$C$8='1. Matriz de Activos'!$F$51)),"Sí","No") | C56: ='1. Matriz de Activos'!$B$51 | D56: ='1. Matriz de Activos'!$C$51 | E56: ='1. Matriz de Activos'!$G$51 | F56: ='1. Matriz de Activos'!$E$51 | G56: ='1. Matriz de Activos'!$F$51 | H56: ='1. Matriz de Activos'!$T$51 | I56: =IF($H56>=4,"Sí","No") | J56: =IF($H56>=4,IFERROR(VLOOKUP($G56,AmenTabla,2,0),0),0) | K56: =COUNTIF('2. Valoración '!$C$6:$C$2261,$C56) | L56: =IF($I56="No","No requiere valoración",IF($K56=0,"FALTA POR COMPLETO — agregar "&$J56&" filas",IF($K56<$J56,"INCOMPLETO — faltan "&($J56-$K56)&" filas",IF($K56>$J56,"REVISAR — hay filas de más","Completo"))))
B57: =IF(AND(OR($C$6="(Todos los procesos)",$C$6='1. Matriz de Activos'!$G$52),OR($C$7="(Todos los tipos)",$C$7='1. Matriz de Activos'!$E$52),OR($C$8="(Todos los subtipos)",$C$8='1. Matriz de Activos'!$F$52)),"Sí","No") | C57: ='1. Matriz de Activos'!$B$52 | D57: ='1. Matriz de Activos'!$C$52 | E57: ='1. Matriz de Activos'!$G$52 | F57: ='1. Matriz de Activos'!$E$52 | G57: ='1. Matriz de Activos'!$F$52 | H57: ='1. Matriz de Activos'!$T$52 | I57: =IF($H57>=4,"Sí","No") | J57: =IF($H57>=4,IFERROR(VLOOKUP($G57,AmenTabla,2,0),0),0) | K57: =COUNTIF('2. Valoración '!$C$6:$C$2261,$C57) | L57: =IF($I57="No","No requiere valoración",IF($K57=0,"FALTA POR COMPLETO — agregar "&$J57&" filas",IF($K57<$J57,"INCOMPLETO — faltan "&($J57-$K57)&" filas",IF($K57>$J57,"REVISAR — hay filas de más","Completo"))))
B58: =IF(AND(OR($C$6="(Todos los procesos)",$C$6='1. Matriz de Activos'!$G$53),OR($C$7="(Todos los tipos)",$C$7='1. Matriz de Activos'!$E$53),OR($C$8="(Todos los subtipos)",$C$8='1. Matriz de Activos'!$F$53)),"Sí","No") | C58: ='1. Matriz de Activos'!$B$53 | D58: ='1. Matriz de Activos'!$C$53 | E58: ='1. Matriz de Activos'!$G$53 | F58: ='1. Matriz de Activos'!$E$53 | G58: ='1. Matriz de Activos'!$F$53 | H58: ='1. Matriz de Activos'!$T$53 | I58: =IF($H58>=4,"Sí","No") | J58: =IF($H58>=4,IFERROR(VLOOKUP($G58,AmenTabla,2,0),0),0) | K58: =COUNTIF('2. Valoración '!$C$6:$C$2261,$C58) | L58: =IF($I58="No","No requiere valoración",IF($K58=0,"FALTA POR COMPLETO — agregar "&$J58&" filas",IF($K58<$J58,"INCOMPLETO — faltan "&($J58-$K58)&" filas",IF($K58>$J58,"REVISAR — hay filas de más","Completo"))))
B59: =IF(AND(OR($C$6="(Todos los procesos)",$C$6='1. Matriz de Activos'!$G$54),OR($C$7="(Todos los tipos)",$C$7='1. Matriz de Activos'!$E$54),OR($C$8="(Todos los subtipos)",$C$8='1. Matriz de Activos'!$F$54)),"Sí","No") | C59: ='1. Matriz de Activos'!$B$54 | D59: ='1. Matriz de Activos'!$C$54 | E59: ='1. Matriz de Activos'!$G$54 | F59: ='1. Matriz de Activos'!$E$54 | G59: ='1. Matriz de Activos'!$F$54 | H59: ='1. Matriz de Activos'!$T$54 | I59: =IF($H59>=4,"Sí","No") | J59: =IF($H59>=4,IFERROR(VLOOKUP($G59,AmenTabla,2,0),0),0) | K59: =COUNTIF('2. Valoración '!$C$6:$C$2261,$C59) | L59: =IF($I59="No","No requiere valoración",IF($K59=0,"FALTA POR COMPLETO — agregar "&$J59&" filas",IF($K59<$J59,"INCOMPLETO — faltan "&($J59-$K59)&" filas",IF($K59>$J59,"REVISAR — hay filas de más","Completo"))))
B60: =IF(AND(OR($C$6="(Todos los procesos)",$C$6='1. Matriz de Activos'!$G$55),OR($C$7="(Todos los tipos)",$C$7='1. Matriz de Activos'!$E$55),OR($C$8="(Todos los subtipos)",$C$8='1. Matriz de Activos'!$F$55)),"Sí","No") | C60: ='1. Matriz de Activos'!$B$55 | D60: ='1. Matriz de Activos'!$C$55 | E60: ='1. Matriz de Activos'!$G$55 | F60: ='1. Matriz de Activos'!$E$55 | G60: ='1. Matriz de Activos'!$F$55 | H60: ='1. Matriz de Activos'!$T$55 | I60: =IF($H60>=4,"Sí","No") | J60: =IF($H60>=4,IFERROR(VLOOKUP($G60,AmenTabla,2,0),0),0) | K60: =COUNTIF('2. Valoración '!$C$6:$C$2261,$C60) | L60: =IF($I60="No","No requiere valoración",IF($K60=0,"FALTA POR COMPLETO — agregar "&$J60&" filas",IF($K60<$J60,"INCOMPLETO — faltan "&($J60-$K60)&" filas",IF($K60>$J60,"REVISAR — hay filas de más","Completo"))))
B61: =IF(AND(OR($C$6="(Todos los procesos)",$C$6='1. Matriz de Activos'!$G$56),OR($C$7="(Todos los tipos)",$C$7='1. Matriz de Activos'!$E$56),OR($C$8="(Todos los subtipos)",$C$8='1. Matriz de Activos'!$F$56)),"Sí","No") | C61: ='1. Matriz de Activos'!$B$56 | D61: ='1. Matriz de Activos'!$C$56 | E61: ='1. Matriz de Activos'!$G$56 | F61: ='1. Matriz de Activos'!$E$56 | G61: ='1. Matriz de Activos'!$F$56 | H61: ='1. Matriz de Activos'!$T$56 | I61: =IF($H61>=4,"Sí","No") | J61: =IF($H61>=4,IFERROR(VLOOKUP($G61,AmenTabla,2,0),0),0) | K61: =COUNTIF('2. Valoración '!$C$6:$C$2261,$C61) | L61: =IF($I61="No","No requiere valoración",IF($K61=0,"FALTA POR COMPLETO — agregar "&$J61&" filas",IF($K61<$J61,"INCOMPLETO — faltan "&($J61-$K61)&" filas",IF($K61>$J61,"REVISAR — hay filas de más","Completo"))))
B62: =IF(AND(OR($C$6="(Todos los procesos)",$C$6='1. Matriz de Activos'!$G$57),OR($C$7="(Todos los tipos)",$C$7='1. Matriz de Activos'!$E$57),OR($C$8="(Todos los subtipos)",$C$8='1. Matriz de Activos'!$F$57)),"Sí","No") | C62: ='1. Matriz de Activos'!$B$57 | D62: ='1. Matriz de Activos'!$C$57 | E62: ='1. Matriz de Activos'!$G$57 | F62: ='1. Matriz de Activos'!$E$57 | G62: ='1. Matriz de Activos'!$F$57 | H62: ='1. Matriz de Activos'!$T$57 | I62: =IF($H62>=4,"Sí","No") | J62: =IF($H62>=4,IFERROR(VLOOKUP($G62,AmenTabla,2,0),0),0) | K62: =COUNTIF('2. Valoración '!$C$6:$C$2261,$C62) | L62: =IF($I62="No","No requiere valoración",IF($K62=0,"FALTA POR COMPLETO — agregar "&$J62&" filas",IF($K62<$J62,"INCOMPLETO — faltan "&($J62-$K62)&" filas",IF($K62>$J62,"REVISAR — hay filas de más","Completo"))))
B63: =IF(AND(OR($C$6="(Todos los procesos)",$C$6='1. Matriz de Activos'!$G$58),OR($C$7="(Todos los tipos)",$C$7='1. Matriz de Activos'!$E$58),OR($C$8="(Todos los subtipos)",$C$8='1. Matriz de Activos'!$F$58)),"Sí","No") | C63: ='1. Matriz de Activos'!$B$58 | D63: ='1. Matriz de Activos'!$C$58 | E63: ='1. Matriz de Activos'!$G$58 | F63: ='1. Matriz de Activos'!$E$58 | G63: ='1. Matriz de Activos'!$F$58 | H63: ='1. Matriz de Activos'!$T$58 | I63: =IF($H63>=4,"Sí","No") | J63: =IF($H63>=4,IFERROR(VLOOKUP($G63,AmenTabla,2,0),0),0) | K63: =COUNTIF('2. Valoración '!$C$6:$C$2261,$C63) | L63: =IF($I63="No","No requiere valoración",IF($K63=0,"FALTA POR COMPLETO — agregar "&$J63&" filas",IF($K63<$J63,"INCOMPLETO — faltan "&($J63-$K63)&" filas",IF($K63>$J63,"REVISAR — hay filas de más","Completo"))))
B64: =IF(AND(OR($C$6="(Todos los procesos)",$C$6='1. Matriz de Activos'!$G$59),OR($C$7="(Todos los tipos)",$C$7='1. Matriz de Activos'!$E$59),OR($C$8="(Todos los subtipos)",$C$8='1. Matriz de Activos'!$F$59)),"Sí","No") | C64: ='1. Matriz de Activos'!$B$59 | D64: ='1. Matriz de Activos'!$C$59 | E64: ='1. Matriz de Activos'!$G$59 | F64: ='1. Matriz de Activos'!$E$59 | G64: ='1. Matriz de Activos'!$F$59 | H64: ='1. Matriz de Activos'!$T$59 | I64: =IF($H64>=4,"Sí","No") | J64: =IF($H64>=4,IFERROR(VLOOKUP($G64,AmenTabla,2,0),0),0) | K64: =COUNTIF('2. Valoración '!$C$6:$C$2261,$C64) | L64: =IF($I64="No","No requiere valoración",IF($K64=0,"FALTA POR COMPLETO — agregar "&$J64&" filas",IF($K64<$J64,"INCOMPLETO — faltan "&($J64-$K64)&" filas",IF($K64>$J64,"REVISAR — hay filas de más","Completo"))))
B65: =IF(AND(OR($C$6="(Todos los procesos)",$C$6='1. Matriz de Activos'!$G$60),OR($C$7="(Todos los tipos)",$C$7='1. Matriz de Activos'!$E$60),OR($C$8="(Todos los subtipos)",$C$8='1. Matriz de Activos'!$F$60)),"Sí","No") | C65: ='1. Matriz de Activos'!$B$60 | D65: ='1. Matriz de Activos'!$C$60 | E65: ='1. Matriz de Activos'!$G$60 | F65: ='1. Matriz de Activos'!$E$60 | G65: ='1. Matriz de Activos'!$F$60 | H65: ='1. Matriz de Activos'!$T$60 | I65: =IF($H65>=4,"Sí","No") | J65: =IF($H65>=4,IFERROR(VLOOKUP($G65,AmenTabla,2,0),0),0) | K65: =COUNTIF('2. Valoración '!$C$6:$C$2261,$C65) | L65: =IF($I65="No","No requiere valoración",IF($K65=0,"FALTA POR COMPLETO — agregar "&$J65&" filas",IF($K65<$J65,"INCOMPLETO — faltan "&($J65-$K65)&" filas",IF($K65>$J65,"REVISAR — hay filas de más","Completo"))))
B66: =IF(AND(OR($C$6="(Todos los procesos)",$C$6='1. Matriz de Activos'!$G$61),OR($C$7="(Todos los tipos)",$C$7='1. Matriz de Activos'!$E$61),OR($C$8="(Todos los subtipos)",$C$8='1. Matriz de Activos'!$F$61)),"Sí","No") | C66: ='1. Matriz de Activos'!$B$61 | D66: ='1. Matriz de Activos'!$C$61 | E66: ='1. Matriz de Activos'!$G$61 | F66: ='1. Matriz de Activos'!$E$61 | G66: ='1. Matriz de Activos'!$F$61 | H66: ='1. Matriz de Activos'!$T$61 | I66: =IF($H66>=4,"Sí","No") | J66: =IF($H66>=4,IFERROR(VLOOKUP($G66,AmenTabla,2,0),0),0) | K66: =COUNTIF('2. Valoración '!$C$6:$C$2261,$C66) | L66: =IF($I66="No","No requiere valoración",IF($K66=0,"FALTA POR COMPLETO — agregar "&$J66&" filas",IF($K66<$J66,"INCOMPLETO — faltan "&($J66-$K66)&" filas",IF($K66>$J66,"REVISAR — hay filas de más","Completo"))))
B67: =IF(AND(OR($C$6="(Todos los procesos)",$C$6='1. Matriz de Activos'!$G$62),OR($C$7="(Todos los tipos)",$C$7='1. Matriz de Activos'!$E$62),OR($C$8="(Todos los subtipos)",$C$8='1. Matriz de Activos'!$F$62)),"Sí","No") | C67: ='1. Matriz de Activos'!$B$62 | D67: ='1. Matriz de Activos'!$C$62 | E67: ='1. Matriz de Activos'!$G$62 | F67: ='1. Matriz de Activos'!$E$62 | G67: ='1. Matriz de Activos'!$F$62 | H67: ='1. Matriz de Activos'!$T$62 | I67: =IF($H67>=4,"Sí","No") | J67: =IF($H67>=4,IFERROR(VLOOKUP($G67,AmenTabla,2,0),0),0) | K67: =COUNTIF('2. Valoración '!$C$6:$C$2261,$C67) | L67: =IF($I67="No","No requiere valoración",IF($K67=0,"FALTA POR COMPLETO — agregar "&$J67&" filas",IF($K67<$J67,"INCOMPLETO — faltan "&($J67-$K67)&" filas",IF($K67>$J67,"REVISAR — hay filas de más","Completo"))))
B68: =IF(AND(OR($C$6="(Todos los procesos)",$C$6='1. Matriz de Activos'!$G$63),OR($C$7="(Todos los tipos)",$C$7='1. Matriz de Activos'!$E$63),OR($C$8="(Todos los subtipos)",$C$8='1. Matriz de Activos'!$F$63)),"Sí","No") | C68: ='1. Matriz de Activos'!$B$63 | D68: ='1. Matriz de Activos'!$C$63 | E68: ='1. Matriz de Activos'!$G$63 | F68: ='1. Matriz de Activos'!$E$63 | G68: ='1. Matriz de Activos'!$F$63 | H68: ='1. Matriz de Activos'!$T$63 | I68: =IF($H68>=4,"Sí","No") | J68: =IF($H68>=4,IFERROR(VLOOKUP($G68,AmenTabla,2,0),0),0) | K68: =COUNTIF('2. Valoración '!$C$6:$C$2261,$C68) | L68: =IF($I68="No","No requiere valoración",IF($K68=0,"FALTA POR COMPLETO — agregar "&$J68&" filas",IF($K68<$J68,"INCOMPLETO — faltan "&($J68-$K68)&" filas",IF($K68>$J68,"REVISAR — hay filas de más","Completo"))))
B69: =IF(AND(OR($C$6="(Todos los procesos)",$C$6='1. Matriz de Activos'!$G$64),OR($C$7="(Todos los tipos)",$C$7='1. Matriz de Activos'!$E$64),OR($C$8="(Todos los subtipos)",$C$8='1. Matriz de Activos'!$F$64)),"Sí","No") | C69: ='1. Matriz de Activos'!$B$64 | D69: ='1. Matriz de Activos'!$C$64 | E69: ='1. Matriz de Activos'!$G$64 | F69: ='1. Matriz de Activos'!$E$64 | G69: ='1. Matriz de Activos'!$F$64 | H69: ='1. Matriz de Activos'!$T$64 | I69: =IF($H69>=4,"Sí","No") | J69: =IF($H69>=4,IFERROR(VLOOKUP($G69,AmenTabla,2,0),0),0) | K69: =COUNTIF('2. Valoración '!$C$6:$C$2261,$C69) | L69: =IF($I69="No","No requiere valoración",IF($K69=0,"FALTA POR COMPLETO — agregar "&$J69&" filas",IF($K69<$J69,"INCOMPLETO — faltan "&($J69-$K69)&" filas",IF($K69>$J69,"REVISAR — hay filas de más","Completo"))))
B70: =IF(AND(OR($C$6="(Todos los procesos)",$C$6='1. Matriz de Activos'!$G$65),OR($C$7="(Todos los tipos)",$C$7='1. Matriz de Activos'!$E$65),OR($C$8="(Todos los subtipos)",$C$8='1. Matriz de Activos'!$F$65)),"Sí","No") | C70: ='1. Matriz de Activos'!$B$65 | D70: ='1. Matriz de Activos'!$C$65 | E70: ='1. Matriz de Activos'!$G$65 | F70: ='1. Matriz de Activos'!$E$65 | G70: ='1. Matriz de Activos'!$F$65 | H70: ='1. Matriz de Activos'!$T$65 | I70: =IF($H70>=4,"Sí","No") | J70: =IF($H70>=4,IFERROR(VLOOKUP($G70,AmenTabla,2,0),0),0) | K70: =COUNTIF('2. Valoración '!$C$6:$C$2261,$C70) | L70: =IF($I70="No","No requiere valoración",IF($K70=0,"FALTA POR COMPLETO — agregar "&$J70&" filas",IF($K70<$J70,"INCOMPLETO — faltan "&($J70-$K70)&" filas",IF($K70>$J70,"REVISAR — hay filas de más","Completo"))))
B71: =IF(AND(OR($C$6="(Todos los procesos)",$C$6='1. Matriz de Activos'!$G$66),OR($C$7="(Todos los tipos)",$C$7='1. Matriz de Activos'!$E$66),OR($C$8="(Todos los subtipos)",$C$8='1. Matriz de Activos'!$F$66)),"Sí","No") | C71: ='1. Matriz de Activos'!$B$66 | D71: ='1. Matriz de Activos'!$C$66 | E71: ='1. Matriz de Activos'!$G$66 | F71: ='1. Matriz de Activos'!$E$66 | G71: ='1. Matriz de Activos'!$F$66 | H71: ='1. Matriz de Activos'!$T$66 | I71: =IF($H71>=4,"Sí","No") | J71: =IF($H71>=4,IFERROR(VLOOKUP($G71,AmenTabla,2,0),0),0) | K71: =COUNTIF('2. Valoración '!$C$6:$C$2261,$C71) | L71: =IF($I71="No","No requiere valoración",IF($K71=0,"FALTA POR COMPLETO — agregar "&$J71&" filas",IF($K71<$J71,"INCOMPLETO — faltan "&($J71-$K71)&" filas",IF($K71>$J71,"REVISAR — hay filas de más","Completo"))))
B72: =IF(AND(OR($C$6="(Todos los procesos)",$C$6='1. Matriz de Activos'!$G$67),OR($C$7="(Todos los tipos)",$C$7='1. Matriz de Activos'!$E$67),OR($C$8="(Todos los subtipos)",$C$8='1. Matriz de Activos'!$F$67)),"Sí","No") | C72: ='1. Matriz de Activos'!$B$67 | D72: ='1. Matriz de Activos'!$C$67 | E72: ='1. Matriz de Activos'!$G$67 | F72: ='1. Matriz de Activos'!$E$67 | G72: ='1. Matriz de Activos'!$F$67 | H72: ='1. Matriz de Activos'!$T$67 | I72: =IF($H72>=4,"Sí","No") | J72: =IF($H72>=4,IFERROR(VLOOKUP($G72,AmenTabla,2,0),0),0) | K72: =COUNTIF('2. Valoración '!$C$6:$C$2261,$C72) | L72: =IF($I72="No","No requiere valoración",IF($K72=0,"FALTA POR COMPLETO — agregar "&$J72&" filas",IF($K72<$J72,"INCOMPLETO — faltan "&($J72-$K72)&" filas",IF($K72>$J72,"REVISAR — hay filas de más","Completo"))))
B73: =IF(AND(OR($C$6="(Todos los procesos)",$C$6='1. Matriz de Activos'!$G$68),OR($C$7="(Todos los tipos)",$C$7='1. Matriz de Activos'!$E$68),OR($C$8="(Todos los subtipos)",$C$8='1. Matriz de Activos'!$F$68)),"Sí","No") | C73: ='1. Matriz de Activos'!$B$68 | D73: ='1. Matriz de Activos'!$C$68 | E73: ='1. Matriz de Activos'!$G$68 | F73: ='1. Matriz de Activos'!$E$68 | G73: ='1. Matriz de Activos'!$F$68 | H73: ='1. Matriz de Activos'!$T$68 | I73: =IF($H73>=4,"Sí","No") | J73: =IF($H73>=4,IFERROR(VLOOKUP($G73,AmenTabla,2,0),0),0) | K73: =COUNTIF('2. Valoración '!$C$6:$C$2261,$C73) | L73: =IF($I73="No","No requiere valoración",IF($K73=0,"FALTA POR COMPLETO — agregar "&$J73&" filas",IF($K73<$J73,"INCOMPLETO — faltan "&($J73-$K73)&" filas",IF($K73>$J73,"REVISAR — hay filas de más","Completo"))))
B74: =IF(AND(OR($C$6="(Todos los procesos)",$C$6='1. Matriz de Activos'!$G$69),OR($C$7="(Todos los tipos)",$C$7='1. Matriz de Activos'!$E$69),OR($C$8="(Todos los subtipos)",$C$8='1. Matriz de Activos'!$F$69)),"Sí","No") | C74: ='1. Matriz de Activos'!$B$69 | D74: ='1. Matriz de Activos'!$C$69 | E74: ='1. Matriz de Activos'!$G$69 | F74: ='1. Matriz de Activos'!$E$69 | G74: ='1. Matriz de Activos'!$F$69 | H74: ='1. Matriz de Activos'!$T$69 | I74: =IF($H74>=4,"Sí","No") | J74: =IF($H74>=4,IFERROR(VLOOKUP($G74,AmenTabla,2,0),0),0) | K74: =COUNTIF('2. Valoración '!$C$6:$C$2261,$C74) | L74: =IF($I74="No","No requiere valoración",IF($K74=0,"FALTA POR COMPLETO — agregar "&$J74&" filas",IF($K74<$J74,"INCOMPLETO — faltan "&($J74-$K74)&" filas",IF($K74>$J74,"REVISAR — hay filas de más","Completo"))))
B75: =IF(AND(OR($C$6="(Todos los procesos)",$C$6='1. Matriz de Activos'!$G$70),OR($C$7="(Todos los tipos)",$C$7='1. Matriz de Activos'!$E$70),OR($C$8="(Todos los subtipos)",$C$8='1. Matriz de Activos'!$F$70)),"Sí","No") | C75: ='1. Matriz de Activos'!$B$70 | D75: ='1. Matriz de Activos'!$C$70 | E75: ='1. Matriz de Activos'!$G$70 | F75: ='1. Matriz de Activos'!$E$70 | G75: ='1. Matriz de Activos'!$F$70 | H75: ='1. Matriz de Activos'!$T$70 | I75: =IF($H75>=4,"Sí","No") | J75: =IF($H75>=4,IFERROR(VLOOKUP($G75,AmenTabla,2,0),0),0) | K75: =COUNTIF('2. Valoración '!$C$6:$C$2261,$C75) | L75: =IF($I75="No","No requiere valoración",IF($K75=0,"FALTA POR COMPLETO — agregar "&$J75&" filas",IF($K75<$J75,"INCOMPLETO — faltan "&($J75-$K75)&" filas",IF($K75>$J75,"REVISAR — hay filas de más","Completo"))))
B76: =IF(AND(OR($C$6="(Todos los procesos)",$C$6='1. Matriz de Activos'!$G$71),OR($C$7="(Todos los tipos)",$C$7='1. Matriz de Activos'!$E$71),OR($C$8="(Todos los subtipos)",$C$8='1. Matriz de Activos'!$F$71)),"Sí","No") | C76: ='1. Matriz de Activos'!$B$71 | D76: ='1. Matriz de Activos'!$C$71 | E76: ='1. Matriz de Activos'!$G$71 | F76: ='1. Matriz de Activos'!$E$71 | G76: ='1. Matriz de Activos'!$F$71 | H76: ='1. Matriz de Activos'!$T$71 | I76: =IF($H76>=4,"Sí","No") | J76: =IF($H76>=4,IFERROR(VLOOKUP($G76,AmenTabla,2,0),0),0) | K76: =COUNTIF('2. Valoración '!$C$6:$C$2261,$C76) | L76: =IF($I76="No","No requiere valoración",IF($K76=0,"FALTA POR COMPLETO — agregar "&$J76&" filas",IF($K76<$J76,"INCOMPLETO — faltan "&($J76-$K76)&" filas",IF($K76>$J76,"REVISAR — hay filas de más","Completo"))))
B77: =IF(AND(OR($C$6="(Todos los procesos)",$C$6='1. Matriz de Activos'!$G$72),OR($C$7="(Todos los tipos)",$C$7='1. Matriz de Activos'!$E$72),OR($C$8="(Todos los subtipos)",$C$8='1. Matriz de Activos'!$F$72)),"Sí","No") | C77: ='1. Matriz de Activos'!$B$72 | D77: ='1. Matriz de Activos'!$C$72 | E77: ='1. Matriz de Activos'!$G$72 | F77: ='1. Matriz de Activos'!$E$72 | G77: ='1. Matriz de Activos'!$F$72 | H77: ='1. Matriz de Activos'!$T$72 | I77: =IF($H77>=4,"Sí","No") | J77: =IF($H77>=4,IFERROR(VLOOKUP($G77,AmenTabla,2,0),0),0) | K77: =COUNTIF('2. Valoración '!$C$6:$C$2261,$C77) | L77: =IF($I77="No","No requiere valoración",IF($K77=0,"FALTA POR COMPLETO — agregar "&$J77&" filas",IF($K77<$J77,"INCOMPLETO — faltan "&($J77-$K77)&" filas",IF($K77>$J77,"REVISAR — hay filas de más","Completo"))))
B78: =IF(AND(OR($C$6="(Todos los procesos)",$C$6='1. Matriz de Activos'!$G$73),OR($C$7="(Todos los tipos)",$C$7='1. Matriz de Activos'!$E$73),OR($C$8="(Todos los subtipos)",$C$8='1. Matriz de Activos'!$F$73)),"Sí","No") | C78: ='1. Matriz de Activos'!$B$73 | D78: ='1. Matriz de Activos'!$C$73 | E78: ='1. Matriz de Activos'!$G$73 | F78: ='1. Matriz de Activos'!$E$73 | G78: ='1. Matriz de Activos'!$F$73 | H78: ='1. Matriz de Activos'!$T$73 | I78: =IF($H78>=4,"Sí","No") | J78: =IF($H78>=4,IFERROR(VLOOKUP($G78,AmenTabla,2,0),0),0) | K78: =COUNTIF('2. Valoración '!$C$6:$C$2261,$C78) | L78: =IF($I78="No","No requiere valoración",IF($K78=0,"FALTA POR COMPLETO — agregar "&$J78&" filas",IF($K78<$J78,"INCOMPLETO — faltan "&($J78-$K78)&" filas",IF($K78>$J78,"REVISAR — hay filas de más","Completo"))))
B79: =IF(AND(OR($C$6="(Todos los procesos)",$C$6='1. Matriz de Activos'!$G$74),OR($C$7="(Todos los tipos)",$C$7='1. Matriz de Activos'!$E$74),OR($C$8="(Todos los subtipos)",$C$8='1. Matriz de Activos'!$F$74)),"Sí","No") | C79: ='1. Matriz de Activos'!$B$74 | D79: ='1. Matriz de Activos'!$C$74 | E79: ='1. Matriz de Activos'!$G$74 | F79: ='1. Matriz de Activos'!$E$74 | G79: ='1. Matriz de Activos'!$F$74 | H79: ='1. Matriz de Activos'!$T$74 | I79: =IF($H79>=4,"Sí","No") | J79: =IF($H79>=4,IFERROR(VLOOKUP($G79,AmenTabla,2,0),0),0) | K79: =COUNTIF('2. Valoración '!$C$6:$C$2261,$C79) | L79: =IF($I79="No","No requiere valoración",IF($K79=0,"FALTA POR COMPLETO — agregar "&$J79&" filas",IF($K79<$J79,"INCOMPLETO — faltan "&($J79-$K79)&" filas",IF($K79>$J79,"REVISAR — hay filas de más","Completo"))))
B80: =IF(AND(OR($C$6="(Todos los procesos)",$C$6='1. Matriz de Activos'!$G$75),OR($C$7="(Todos los tipos)",$C$7='1. Matriz de Activos'!$E$75),OR($C$8="(Todos los subtipos)",$C$8='1. Matriz de Activos'!$F$75)),"Sí","No") | C80: ='1. Matriz de Activos'!$B$75 | D80: ='1. Matriz de Activos'!$C$75 | E80: ='1. Matriz de Activos'!$G$75 | F80: ='1. Matriz de Activos'!$E$75 | G80: ='1. Matriz de Activos'!$F$75 | H80: ='1. Matriz de Activos'!$T$75 | I80: =IF($H80>=4,"Sí","No") | J80: =IF($H80>=4,IFERROR(VLOOKUP($G80,AmenTabla,2,0),0),0) | K80: =COUNTIF('2. Valoración '!$C$6:$C$2261,$C80) | L80: =IF($I80="No","No requiere valoración",IF($K80=0,"FALTA POR COMPLETO — agregar "&$J80&" filas",IF($K80<$J80,"INCOMPLETO — faltan "&($J80-$K80)&" filas",IF($K80>$J80,"REVISAR — hay filas de más","Completo"))))
B81: =IF(AND(OR($C$6="(Todos los procesos)",$C$6='1. Matriz de Activos'!$G$76),OR($C$7="(Todos los tipos)",$C$7='1. Matriz de Activos'!$E$76),OR($C$8="(Todos los subtipos)",$C$8='1. Matriz de Activos'!$F$76)),"Sí","No") | C81: ='1. Matriz de Activos'!$B$76 | D81: ='1. Matriz de Activos'!$C$76 | E81: ='1. Matriz de Activos'!$G$76 | F81: ='1. Matriz de Activos'!$E$76 | G81: ='1. Matriz de Activos'!$F$76 | H81: ='1. Matriz de Activos'!$T$76 | I81: =IF($H81>=4,"Sí","No") | J81: =IF($H81>=4,IFERROR(VLOOKUP($G81,AmenTabla,2,0),0),0) | K81: =COUNTIF('2. Valoración '!$C$6:$C$2261,$C81) | L81: =IF($I81="No","No requiere valoración",IF($K81=0,"FALTA POR COMPLETO — agregar "&$J81&" filas",IF($K81<$J81,"INCOMPLETO — faltan "&($J81-$K81)&" filas",IF($K81>$J81,"REVISAR — hay filas de más","Completo"))))
B82: =IF(AND(OR($C$6="(Todos los procesos)",$C$6='1. Matriz de Activos'!$G$77),OR($C$7="(Todos los tipos)",$C$7='1. Matriz de Activos'!$E$77),OR($C$8="(Todos los subtipos)",$C$8='1. Matriz de Activos'!$F$77)),"Sí","No") | C82: ='1. Matriz de Activos'!$B$77 | D82: ='1. Matriz de Activos'!$C$77 | E82: ='1. Matriz de Activos'!$G$77 | F82: ='1. Matriz de Activos'!$E$77 | G82: ='1. Matriz de Activos'!$F$77 | H82: ='1. Matriz de Activos'!$T$77 | I82: =IF($H82>=4,"Sí","No") | J82: =IF($H82>=4,IFERROR(VLOOKUP($G82,AmenTabla,2,0),0),0) | K82: =COUNTIF('2. Valoración '!$C$6:$C$2261,$C82) | L82: =IF($I82="No","No requiere valoración",IF($K82=0,"FALTA POR COMPLETO — agregar "&$J82&" filas",IF($K82<$J82,"INCOMPLETO — faltan "&($J82-$K82)&" filas",IF($K82>$J82,"REVISAR — hay filas de más","Completo"))))
B83: =IF(AND(OR($C$6="(Todos los procesos)",$C$6='1. Matriz de Activos'!$G$78),OR($C$7="(Todos los tipos)",$C$7='1. Matriz de Activos'!$E$78),OR($C$8="(Todos los subtipos)",$C$8='1. Matriz de Activos'!$F$78)),"Sí","No") | C83: ='1. Matriz de Activos'!$B$78 | D83: ='1. Matriz de Activos'!$C$78 | E83: ='1. Matriz de Activos'!$G$78 | F83: ='1. Matriz de Activos'!$E$78 | G83: ='1. Matriz de Activos'!$F$78 | H83: ='1. Matriz de Activos'!$T$78 | I83: =IF($H83>=4,"Sí","No") | J83: =IF($H83>=4,IFERROR(VLOOKUP($G83,AmenTabla,2,0),0),0) | K83: =COUNTIF('2. Valoración '!$C$6:$C$2261,$C83) | L83: =IF($I83="No","No requiere valoración",IF($K83=0,"FALTA POR COMPLETO — agregar "&$J83&" filas",IF($K83<$J83,"INCOMPLETO — faltan "&($J83-$K83)&" filas",IF($K83>$J83,"REVISAR — hay filas de más","Completo"))))
B84: =IF(AND(OR($C$6="(Todos los procesos)",$C$6='1. Matriz de Activos'!$G$79),OR($C$7="(Todos los tipos)",$C$7='1. Matriz de Activos'!$E$79),OR($C$8="(Todos los subtipos)",$C$8='1. Matriz de Activos'!$F$79)),"Sí","No") | C84: ='1. Matriz de Activos'!$B$79 | D84: ='1. Matriz de Activos'!$C$79 | E84: ='1. Matriz de Activos'!$G$79 | F84: ='1. Matriz de Activos'!$E$79 | G84: ='1. Matriz de Activos'!$F$79 | H84: ='1. Matriz de Activos'!$T$79 | I84: =IF($H84>=4,"Sí","No") | J84: =IF($H84>=4,IFERROR(VLOOKUP($G84,AmenTabla,2,0),0),0) | K84: =COUNTIF('2. Valoración '!$C$6:$C$2261,$C84) | L84: =IF($I84="No","No requiere valoración",IF($K84=0,"FALTA POR COMPLETO — agregar "&$J84&" filas",IF($K84<$J84,"INCOMPLETO — faltan "&($J84-$K84)&" filas",IF($K84>$J84,"REVISAR — hay filas de más","Completo"))))
B85: =IF(AND(OR($C$6="(Todos los procesos)",$C$6='1. Matriz de Activos'!$G$80),OR($C$7="(Todos los tipos)",$C$7='1. Matriz de Activos'!$E$80),OR($C$8="(Todos los subtipos)",$C$8='1. Matriz de Activos'!$F$80)),"Sí","No") | C85: ='1. Matriz de Activos'!$B$80 | D85: ='1. Matriz de Activos'!$C$80 | E85: ='1. Matriz de Activos'!$G$80 | F85: ='1. Matriz de Activos'!$E$80 | G85: ='1. Matriz de Activos'!$F$80 | H85: ='1. Matriz de Activos'!$T$80 | I85: =IF($H85>=4,"Sí","No") | J85: =IF($H85>=4,IFERROR(VLOOKUP($G85,AmenTabla,2,0),0),0) | K85: =COUNTIF('2. Valoración '!$C$6:$C$2261,$C85) | L85: =IF($I85="No","No requiere valoración",IF($K85=0,"FALTA POR COMPLETO — agregar "&$J85&" filas",IF($K85<$J85,"INCOMPLETO — faltan "&($J85-$K85)&" filas",IF($K85>$J85,"REVISAR — hay filas de más","Completo"))))
B86: =IF(AND(OR($C$6="(Todos los procesos)",$C$6='1. Matriz de Activos'!$G$81),OR($C$7="(Todos los tipos)",$C$7='1. Matriz de Activos'!$E$81),OR($C$8="(Todos los subtipos)",$C$8='1. Matriz de Activos'!$F$81)),"Sí","No") | C86: ='1. Matriz de Activos'!$B$81 | D86: ='1. Matriz de Activos'!$C$81 | E86: ='1. Matriz de Activos'!$G$81 | F86: ='1. Matriz de Activos'!$E$81 | G86: ='1. Matriz de Activos'!$F$81 | H86: ='1. Matriz de Activos'!$T$81 | I86: =IF($H86>=4,"Sí","No") | J86: =IF($H86>=4,IFERROR(VLOOKUP($G86,AmenTabla,2,0),0),0) | K86: =COUNTIF('2. Valoración '!$C$6:$C$2261,$C86) | L86: =IF($I86="No","No requiere valoración",IF($K86=0,"FALTA POR COMPLETO — agregar "&$J86&" filas",IF($K86<$J86,"INCOMPLETO — faltan "&($J86-$K86)&" filas",IF($K86>$J86,"REVISAR — hay filas de más","Completo"))))
B87: =IF(AND(OR($C$6="(Todos los procesos)",$C$6='1. Matriz de Activos'!$G$82),OR($C$7="(Todos los tipos)",$C$7='1. Matriz de Activos'!$E$82),OR($C$8="(Todos los subtipos)",$C$8='1. Matriz de Activos'!$F$82)),"Sí","No") | C87: ='1. Matriz de Activos'!$B$82 | D87: ='1. Matriz de Activos'!$C$82 | E87: ='1. Matriz de Activos'!$G$82 | F87: ='1. Matriz de Activos'!$E$82 | G87: ='1. Matriz de Activos'!$F$82 | H87: ='1. Matriz de Activos'!$T$82 | I87: =IF($H87>=4,"Sí","No") | J87: =IF($H87>=4,IFERROR(VLOOKUP($G87,AmenTabla,2,0),0),0) | K87: =COUNTIF('2. Valoración '!$C$6:$C$2261,$C87) | L87: =IF($I87="No","No requiere valoración",IF($K87=0,"FALTA POR COMPLETO — agregar "&$J87&" filas",IF($K87<$J87,"INCOMPLETO — faltan "&($J87-$K87)&" filas",IF($K87>$J87,"REVISAR — hay filas de más","Completo"))))
B88: =IF(AND(OR($C$6="(Todos los procesos)",$C$6='1. Matriz de Activos'!$G$83),OR($C$7="(Todos los tipos)",$C$7='1. Matriz de Activos'!$E$83),OR($C$8="(Todos los subtipos)",$C$8='1. Matriz de Activos'!$F$83)),"Sí","No") | C88: ='1. Matriz de Activos'!$B$83 | D88: ='1. Matriz de Activos'!$C$83 | E88: ='1. Matriz de Activos'!$G$83 | F88: ='1. Matriz de Activos'!$E$83 | G88: ='1. Matriz de Activos'!$F$83 | H88: ='1. Matriz de Activos'!$T$83 | I88: =IF($H88>=4,"Sí","No") | J88: =IF($H88>=4,IFERROR(VLOOKUP($G88,AmenTabla,2,0),0),0) | K88: =COUNTIF('2. Valoración '!$C$6:$C$2261,$C88) | L88: =IF($I88="No","No requiere valoración",IF($K88=0,"FALTA POR COMPLETO — agregar "&$J88&" filas",IF($K88<$J88,"INCOMPLETO — faltan "&($J88-$K88)&" filas",IF($K88>$J88,"REVISAR — hay filas de más","Completo"))))
B89: =IF(AND(OR($C$6="(Todos los procesos)",$C$6='1. Matriz de Activos'!$G$84),OR($C$7="(Todos los tipos)",$C$7='1. Matriz de Activos'!$E$84),OR($C$8="(Todos los subtipos)",$C$8='1. Matriz de Activos'!$F$84)),"Sí","No") | C89: ='1. Matriz de Activos'!$B$84 | D89: ='1. Matriz de Activos'!$C$84 | E89: ='1. Matriz de Activos'!$G$84 | F89: ='1. Matriz de Activos'!$E$84 | G89: ='1. Matriz de Activos'!$F$84 | H89: ='1. Matriz de Activos'!$T$84 | I89: =IF($H89>=4,"Sí","No") | J89: =IF($H89>=4,IFERROR(VLOOKUP($G89,AmenTabla,2,0),0),0) | K89: =COUNTIF('2. Valoración '!$C$6:$C$2261,$C89) | L89: =IF($I89="No","No requiere valoración",IF($K89=0,"FALTA POR COMPLETO — agregar "&$J89&" filas",IF($K89<$J89,"INCOMPLETO — faltan "&($J89-$K89)&" filas",IF($K89>$J89,"REVISAR — hay filas de más","Completo"))))
B90: =IF(AND(OR($C$6="(Todos los procesos)",$C$6='1. Matriz de Activos'!$G$85),OR($C$7="(Todos los tipos)",$C$7='1. Matriz de Activos'!$E$85),OR($C$8="(Todos los subtipos)",$C$8='1. Matriz de Activos'!$F$85)),"Sí","No") | C90: ='1. Matriz de Activos'!$B$85 | D90: ='1. Matriz de Activos'!$C$85 | E90: ='1. Matriz de Activos'!$G$85 | F90: ='1. Matriz de Activos'!$E$85 | G90: ='1. Matriz de Activos'!$F$85 | H90: ='1. Matriz de Activos'!$T$85 | I90: =IF($H90>=4,"Sí","No") | J90: =IF($H90>=4,IFERROR(VLOOKUP($G90,AmenTabla,2,0),0),0) | K90: =COUNTIF('2. Valoración '!$C$6:$C$2261,$C90) | L90: =IF($I90="No","No requiere valoración",IF($K90=0,"FALTA POR COMPLETO — agregar "&$J90&" filas",IF($K90<$J90,"INCOMPLETO — faltan "&($J90-$K90)&" filas",IF($K90>$J90,"REVISAR — hay filas de más","Completo"))))
B91: =IF(AND(OR($C$6="(Todos los procesos)",$C$6='1. Matriz de Activos'!$G$86),OR($C$7="(Todos los tipos)",$C$7='1. Matriz de Activos'!$E$86),OR($C$8="(Todos los subtipos)",$C$8='1. Matriz de Activos'!$F$86)),"Sí","No") | C91: ='1. Matriz de Activos'!$B$86 | D91: ='1. Matriz de Activos'!$C$86 | E91: ='1. Matriz de Activos'!$G$86 | F91: ='1. Matriz de Activos'!$E$86 | G91: ='1. Matriz de Activos'!$F$86 | H91: ='1. Matriz de Activos'!$T$86 | I91: =IF($H91>=4,"Sí","No") | J91: =IF($H91>=4,IFERROR(VLOOKUP($G91,AmenTabla,2,0),0),0) | K91: =COUNTIF('2. Valoración '!$C$6:$C$2261,$C91) | L91: =IF($I91="No","No requiere valoración",IF($K91=0,"FALTA POR COMPLETO — agregar "&$J91&" filas",IF($K91<$J91,"INCOMPLETO — faltan "&($J91-$K91)&" filas",IF($K91>$J91,"REVISAR — hay filas de más","Completo"))))
B92: =IF(AND(OR($C$6="(Todos los procesos)",$C$6='1. Matriz de Activos'!$G$87),OR($C$7="(Todos los tipos)",$C$7='1. Matriz de Activos'!$E$87),OR($C$8="(Todos los subtipos)",$C$8='1. Matriz de Activos'!$F$87)),"Sí","No") | C92: ='1. Matriz de Activos'!$B$87 | D92: ='1. Matriz de Activos'!$C$87 | E92: ='1. Matriz de Activos'!$G$87 | F92: ='1. Matriz de Activos'!$E$87 | G92: ='1. Matriz de Activos'!$F$87 | H92: ='1. Matriz de Activos'!$T$87 | I92: =IF($H92>=4,"Sí","No") | J92: =IF($H92>=4,IFERROR(VLOOKUP($G92,AmenTabla,2,0),0),0) | K92: =COUNTIF('2. Valoración '!$C$6:$C$2261,$C92) | L92: =IF($I92="No","No requiere valoración",IF($K92=0,"FALTA POR COMPLETO — agregar "&$J92&" filas",IF($K92<$J92,"INCOMPLETO — faltan "&($J92-$K92)&" filas",IF($K92>$J92,"REVISAR — hay filas de más","Completo"))))
B93: =IF(AND(OR($C$6="(Todos los procesos)",$C$6='1. Matriz de Activos'!$G$88),OR($C$7="(Todos los tipos)",$C$7='1. Matriz de Activos'!$E$88),OR($C$8="(Todos los subtipos)",$C$8='1. Matriz de Activos'!$F$88)),"Sí","No") | C93: ='1. Matriz de Activos'!$B$88 | D93: ='1. Matriz de Activos'!$C$88 | E93: ='1. Matriz de Activos'!$G$88 | F93: ='1. Matriz de Activos'!$E$88 | G93: ='1. Matriz de Activos'!$F$88 | H93: ='1. Matriz de Activos'!$T$88 | I93: =IF($H93>=4,"Sí","No") | J93: =IF($H93>=4,IFERROR(VLOOKUP($G93,AmenTabla,2,0),0),0) | K93: =COUNTIF('2. Valoración '!$C$6:$C$2261,$C93) | L93: =IF($I93="No","No requiere valoración",IF($K93=0,"FALTA POR COMPLETO — agregar "&$J93&" filas",IF($K93<$J93,"INCOMPLETO — faltan "&($J93-$K93)&" filas",IF($K93>$J93,"REVISAR — hay filas de más","Completo"))))
B94: =IF(AND(OR($C$6="(Todos los procesos)",$C$6='1. Matriz de Activos'!$G$89),OR($C$7="(Todos los tipos)",$C$7='1. Matriz de Activos'!$E$89),OR($C$8="(Todos los subtipos)",$C$8='1. Matriz de Activos'!$F$89)),"Sí","No") | C94: ='1. Matriz de Activos'!$B$89 | D94: ='1. Matriz de Activos'!$C$89 | E94: ='1. Matriz de Activos'!$G$89 | F94: ='1. Matriz de Activos'!$E$89 | G94: ='1. Matriz de Activos'!$F$89 | H94: ='1. Matriz de Activos'!$T$89 | I94: =IF($H94>=4,"Sí","No") | J94: =IF($H94>=4,IFERROR(VLOOKUP($G94,AmenTabla,2,0),0),0) | K94: =COUNTIF('2. Valoración '!$C$6:$C$2261,$C94) | L94: =IF($I94="No","No requiere valoración",IF($K94=0,"FALTA POR COMPLETO — agregar "&$J94&" filas",IF($K94<$J94,"INCOMPLETO — faltan "&($J94-$K94)&" filas",IF($K94>$J94,"REVISAR — hay filas de más","Completo"))))
B95: =IF(AND(OR($C$6="(Todos los procesos)",$C$6='1. Matriz de Activos'!$G$90),OR($C$7="(Todos los tipos)",$C$7='1. Matriz de Activos'!$E$90),OR($C$8="(Todos los subtipos)",$C$8='1. Matriz de Activos'!$F$90)),"Sí","No") | C95: ='1. Matriz de Activos'!$B$90 | D95: ='1. Matriz de Activos'!$C$90 | E95: ='1. Matriz de Activos'!$G$90 | F95: ='1. Matriz de Activos'!$E$90 | G95: ='1. Matriz de Activos'!$F$90 | H95: ='1. Matriz de Activos'!$T$90 | I95: =IF($H95>=4,"Sí","No") | J95: =IF($H95>=4,IFERROR(VLOOKUP($G95,AmenTabla,2,0),0),0) | K95: =COUNTIF('2. Valoración '!$C$6:$C$2261,$C95) | L95: =IF($I95="No","No requiere valoración",IF($K95=0,"FALTA POR COMPLETO — agregar "&$J95&" filas",IF($K95<$J95,"INCOMPLETO — faltan "&($J95-$K95)&" filas",IF($K95>$J95,"REVISAR — hay filas de más","Completo"))))
B96: =IF(AND(OR($C$6="(Todos los procesos)",$C$6='1. Matriz de Activos'!$G$91),OR($C$7="(Todos los tipos)",$C$7='1. Matriz de Activos'!$E$91),OR($C$8="(Todos los subtipos)",$C$8='1. Matriz de Activos'!$F$91)),"Sí","No") | C96: ='1. Matriz de Activos'!$B$91 | D96: ='1. Matriz de Activos'!$C$91 | E96: ='1. Matriz de Activos'!$G$91 | F96: ='1. Matriz de Activos'!$E$91 | G96: ='1. Matriz de Activos'!$F$91 | H96: ='1. Matriz de Activos'!$T$91 | I96: =IF($H96>=4,"Sí","No") | J96: =IF($H96>=4,IFERROR(VLOOKUP($G96,AmenTabla,2,0),0),0) | K96: =COUNTIF('2. Valoración '!$C$6:$C$2261,$C96) | L96: =IF($I96="No","No requiere valoración",IF($K96=0,"FALTA POR COMPLETO — agregar "&$J96&" filas",IF($K96<$J96,"INCOMPLETO — faltan "&($J96-$K96)&" filas",IF($K96>$J96,"REVISAR — hay filas de más","Completo"))))
B97: =IF(AND(OR($C$6="(Todos los procesos)",$C$6='1. Matriz de Activos'!$G$92),OR($C$7="(Todos los tipos)",$C$7='1. Matriz de Activos'!$E$92),OR($C$8="(Todos los subtipos)",$C$8='1. Matriz de Activos'!$F$92)),"Sí","No") | C97: ='1. Matriz de Activos'!$B$92 | D97: ='1. Matriz de Activos'!$C$92 | E97: ='1. Matriz de Activos'!$G$92 | F97: ='1. Matriz de Activos'!$E$92 | G97: ='1. Matriz de Activos'!$F$92 | H97: ='1. Matriz de Activos'!$T$92 | I97: =IF($H97>=4,"Sí","No") | J97: =IF($H97>=4,IFERROR(VLOOKUP($G97,AmenTabla,2,0),0),0) | K97: =COUNTIF('2. Valoración '!$C$6:$C$2261,$C97) | L97: =IF($I97="No","No requiere valoración",IF($K97=0,"FALTA POR COMPLETO — agregar "&$J97&" filas",IF($K97<$J97,"INCOMPLETO — faltan "&($J97-$K97)&" filas",IF($K97>$J97,"REVISAR — hay filas de más","Completo"))))
B98: =IF(AND(OR($C$6="(Todos los procesos)",$C$6='1. Matriz de Activos'!$G$93),OR($C$7="(Todos los tipos)",$C$7='1. Matriz de Activos'!$E$93),OR($C$8="(Todos los subtipos)",$C$8='1. Matriz de Activos'!$F$93)),"Sí","No") | C98: ='1. Matriz de Activos'!$B$93 | D98: ='1. Matriz de Activos'!$C$93 | E98: ='1. Matriz de Activos'!$G$93 | F98: ='1. Matriz de Activos'!$E$93 | G98: ='1. Matriz de Activos'!$F$93 | H98: ='1. Matriz de Activos'!$T$93 | I98: =IF($H98>=4,"Sí","No") | J98: =IF($H98>=4,IFERROR(VLOOKUP($G98,AmenTabla,2,0),0),0) | K98: =COUNTIF('2. Valoración '!$C$6:$C$2261,$C98) | L98: =IF($I98="No","No requiere valoración",IF($K98=0,"FALTA POR COMPLETO — agregar "&$J98&" filas",IF($K98<$J98,"INCOMPLETO — faltan "&($J98-$K98)&" filas",IF($K98>$J98,"REVISAR — hay filas de más","Completo"))))
B99: =IF(AND(OR($C$6="(Todos los procesos)",$C$6='1. Matriz de Activos'!$G$94),OR($C$7="(Todos los tipos)",$C$7='1. Matriz de Activos'!$E$94),OR($C$8="(Todos los subtipos)",$C$8='1. Matriz de Activos'!$F$94)),"Sí","No") | C99: ='1. Matriz de Activos'!$B$94 | D99: ='1. Matriz de Activos'!$C$94 | E99: ='1. Matriz de Activos'!$G$94 | F99: ='1. Matriz de Activos'!$E$94 | G99: ='1. Matriz de Activos'!$F$94 | H99: ='1. Matriz de Activos'!$T$94 | I99: =IF($H99>=4,"Sí","No") | J99: =IF($H99>=4,IFERROR(VLOOKUP($G99,AmenTabla,2,0),0),0) | K99: =COUNTIF('2. Valoración '!$C$6:$C$2261,$C99) | L99: =IF($I99="No","No requiere valoración",IF($K99=0,"FALTA POR COMPLETO — agregar "&$J99&" filas",IF($K99<$J99,"INCOMPLETO — faltan "&($J99-$K99)&" filas",IF($K99>$J99,"REVISAR — hay filas de más","Completo"))))
B100: =IF(AND(OR($C$6="(Todos los procesos)",$C$6='1. Matriz de Activos'!$G$95),OR($C$7="(Todos los tipos)",$C$7='1. Matriz de Activos'!$E$95),OR($C$8="(Todos los subtipos)",$C$8='1. Matriz de Activos'!$F$95)),"Sí","No") | C100: ='1. Matriz de Activos'!$B$95 | D100: ='1. Matriz de Activos'!$C$95 | E100: ='1. Matriz de Activos'!$G$95 | F100: ='1. Matriz de Activos'!$E$95 | G100: ='1. Matriz de Activos'!$F$95 | H100: ='1. Matriz de Activos'!$T$95 | I100: =IF($H100>=4,"Sí","No") | J100: =IF($H100>=4,IFERROR(VLOOKUP($G100,AmenTabla,2,0),0),0) | K100: =COUNTIF('2. Valoración '!$C$6:$C$2261,$C100) | L100: =IF($I100="No","No requiere valoración",IF($K100=0,"FALTA POR COMPLETO — agregar "&$J100&" filas",IF($K100<$J100,"INCOMPLETO — faltan "&($J100-$K100)&" filas",IF($K100>$J100,"REVISAR — hay filas de más","Completo"))))
B101: =IF(AND(OR($C$6="(Todos los procesos)",$C$6='1. Matriz de Activos'!$G$96),OR($C$7="(Todos los tipos)",$C$7='1. Matriz de Activos'!$E$96),OR($C$8="(Todos los subtipos)",$C$8='1. Matriz de Activos'!$F$96)),"Sí","No") | C101: ='1. Matriz de Activos'!$B$96 | D101: ='1. Matriz de Activos'!$C$96 | E101: ='1. Matriz de Activos'!$G$96 | F101: ='1. Matriz de Activos'!$E$96 | G101: ='1. Matriz de Activos'!$F$96 | H101: ='1. Matriz de Activos'!$T$96 | I101: =IF($H101>=4,"Sí","No") | J101: =IF($H101>=4,IFERROR(VLOOKUP($G101,AmenTabla,2,0),0),0) | K101: =COUNTIF('2. Valoración '!$C$6:$C$2261,$C101) | L101: =IF($I101="No","No requiere valoración",IF($K101=0,"FALTA POR COMPLETO — agregar "&$J101&" filas",IF($K101<$J101,"INCOMPLETO — faltan "&($J101-$K101)&" filas",IF($K101>$J101,"REVISAR — hay filas de más","Completo"))))
...

Sheet 2. Valoración 
B1: VALORACIÓN DE RIESGOS — MODELO MAGERIT v3.0
B2: Impacto = valor de la dimensión × degradación de la amenaza. Riesgo = impacto × veces por año. Se valoran los activos cuyo valor sea 4 o superior y todas las amenazas que la norma asigna a su tipo.
B3: Código de color: | C3: Amarillo = Campo de entrada — se selecciona de una lista | E3: Lila = Calculado automáticamente — no escribir encima | G3: Gris = Dato de la norma MAGERIT — no modificar
B5: Código del riesgo | C5: Código del activo | D5: Nombre del activo | E5: Proceso o Área | F5: Tipo MAGERIT | G5: Subtipo MAGERIT | H5: Código de la amenaza | I5: Amenaza | J5: Grupo MAGERIT | K5: Valor del activo en Disponibilidad | L5: Valor del activo en Integridad | M5: Valor del activo en Confidencialidad | N5: Degradación en Disponibilidad | O5: Degradación en Integridad | P5: Degradación en Confidencialidad | Q5: Impacto en Disponibilidad | R5: Impacto en Integridad | S5: Impacto en Confidencialidad | T5: Impacto acumulado (0 a 5) | U5: Nivel de impacto | V5: Frecuencia esperada | W5: Frecuencia | X5: Veces por año | Y5: Riesgo potencial | Z5: Nivel de riesgo | AA5: Zona de riesgo MAGERIT | AB5: Controles ISO 27001 sugeridos | AC5: Madurez del control — sobrescritura manual (opcional) | AD5: Veces por año residual | AE5: Frecuencia residual | AF5: Riesgo residual | AG5: Nivel de riesgo residual | AH5: Tratamiento | AI5: Responsable | AJ5: Estado del tratamiento | AK5: Observación | AL5: Eficacia de los controles (%)
B6: R-0001 | C6: DO-14 | D6: =IFERROR(INDEX(MgNombre,MATCH($C6,MgActId,0)),"") | E6: =IFERROR(INDEX(MgProceso,MATCH($C6,MgActId,0)),"") | F6: =IFERROR(INDEX(MgTipo,MATCH($C6,MgActId,0)),"") | G6: =IFERROR(INDEX(MgSubtipo,MATCH($C6,MgActId,0)),"") | H6: I.8 | I6: =IFERROR(INDEX(MgAmenNombre,MATCH(SUBSTITUTE($H6,"*","-"),MgAmenClave,0)),"") | J6: =IFERROR(INDEX(MgAmenGrupo,MATCH(SUBSTITUTE($H6,"*","-"),MgAmenClave,0)),"") | K6: =IFERROR(INDEX('1. Matriz de Activos'!$Q$6:$Q$239,MATCH($C6,MgActId,0)),"") | L6: =IFERROR(INDEX('1. Matriz de Activos'!$R$6:$R$239,MATCH($C6,MgActId,0)),"") | M6: =IFERROR(INDEX('1. Matriz de Activos'!$S$6:$S$239,MATCH($C6,MgActId,0)),"") | N6: =IFERROR(INDEX(MgAmenDegD,MATCH(SUBSTITUTE($H6,"*","-"),MgAmenClave,0)),"No aplica") | O6: =IFERROR(INDEX(MgAmenDegI,MATCH(SUBSTITUTE($H6,"*","-"),MgAmenClave,0)),"No aplica") | P6: =IFERROR(INDEX(MgAmenDegC,MATCH(SUBSTITUTE($H6,"*","-"),MgAmenClave,0)),"No aplica") | Q6: =IFERROR(VLOOKUP(K6,MgValor,2,0)*VLOOKUP(N6,MgDeg,2,0),0) | R6: =IFERROR(VLOOKUP(L6,MgValor,2,0)*VLOOKUP(O6,MgDeg,2,0),0) | S6: =IFERROR(VLOOKUP(M6,MgValor,2,0)*VLOOKUP(P6,MgDeg,2,0),0) | T6: =MAX(Q6:S6) | U6: =IFERROR(LOOKUP(T6,{0;0.5;1.5;3;4.5},{"Despreciable";"Bajo";"Medio";"Alto";"Muy alto"}),"") | V6: =IFERROR(INDEX(MgAmenFrec,MATCH(SUBSTITUTE($H6,"*","-"),MgAmenClave,0)),"") | W6: =IFERROR(LOOKUP(X6,{0;0.01;0.1;1;10;100},{"Muy baja";"Muy baja";"Baja";"Media";"Alta";"Muy alta"}),"") | X6: =IFERROR(VLOOKUP(V6,MgFrec,2,0),0) | Y6: =T6*X6 | Z6: =IFERROR(LOOKUP(Y6,{0;0.5;5;25},{"Bajo";"Medio";"Alto";"Crítico"}),"") | AA6: =IF(T6>=3,IF(X6>=1,"Zona 1 — Crítica: impacto alto y ocurre al menos una vez al año","Zona 4 — Catastrófica poco probable: impacto alto pero excepcional"),IF(AND(T6<1.5,X6<1),"Zona 3 — Asumible: impacto bajo y muy poco frecuente","Zona 2 — Atención: riesgo intermedio")) | AB6: =IFERROR(INDEX(MgAmenCtrl,MATCH(SUBSTITUTE($H6,"*","-"),MgAmenClave,0)),"") | AD6: =IFERROR($X6*(1-IF($AC6="",$AL6,VLOOKUP($AC6,MgMad,2,0))),"") | AE6: =IFERROR(LOOKUP(AD6,{0;0.01;0.1;1;10;100},{"Muy baja";"Muy baja";"Baja";"Media";"Alta";"Muy alta"}),"") | AF6: =T6*AD6 | AG6: =IFERROR(LOOKUP(AF6,{0;0.5;5;25},{"Bajo";"Medio";"Alto";"Crítico"}),"") | AH6: =IF(AG6="","",IF(OR(AG6="Crítico",AG6="Alto"),"Mitigar",IF(AG6="Medio","Mitigar","Aceptar y monitorear"))) | AL6: =IFERROR(INDEX(MgAmenEfic,MATCH(SUBSTITUTE($H6,"*","-"),MgAmenClave,0)),0)
B7: R-0002 | C7: DO-14 | D7: =IFERROR(INDEX(MgNombre,MATCH($C7,MgActId,0)),"") | E7: =IFERROR(INDEX(MgProceso,MATCH($C7,MgActId,0)),"") | F7: =IFERROR(INDEX(MgTipo,MATCH($C7,MgActId,0)),"") | G7: =IFERROR(INDEX(MgSubtipo,MATCH($C7,MgActId,0)),"") | H7: I.11 | I7: =IFERROR(INDEX(MgAmenNombre,MATCH(SUBSTITUTE($H7,"*","-"),MgAmenClave,0)),"") | J7: =IFERROR(INDEX(MgAmenGrupo,MATCH(SUBSTITUTE($H7,"*","-"),MgAmenClave,0)),"") | K7: =IFERROR(INDEX('1. Matriz de Activos'!$Q$6:$Q$239,MATCH($C7,MgActId,0)),"") | L7: =IFERROR(INDEX('1. Matriz de Activos'!$R$6:$R$239,MATCH($C7,MgActId,0)),"") | M7: =IFERROR(INDEX('1. Matriz de Activos'!$S$6:$S$239,MATCH($C7,MgActId,0)),"") | N7: =IFERROR(INDEX(MgAmenDegD,MATCH(SUBSTITUTE($H7,"*","-"),MgAmenClave,0)),"No aplica") | O7: =IFERROR(INDEX(MgAmenDegI,MATCH(SUBSTITUTE($H7,"*","-"),MgAmenClave,0)),"No aplica") | P7: =IFERROR(INDEX(MgAmenDegC,MATCH(SUBSTITUTE($H7,"*","-"),MgAmenClave,0)),"No aplica") | Q7: =IFERROR(VLOOKUP(K7,MgValor,2,0)*VLOOKUP(N7,MgDeg,2,0),0) | R7: =IFERROR(VLOOKUP(L7,MgValor,2,0)*VLOOKUP(O7,MgDeg,2,0),0) | S7: =IFERROR(VLOOKUP(M7,MgValor,2,0)*VLOOKUP(P7,MgDeg,2,0),0) | T7: =MAX(Q7:S7) | U7: =IFERROR(LOOKUP(T7,{0;0.5;1.5;3;4.5},{"Despreciable";"Bajo";"Medio";"Alto";"Muy alto"}),"") | V7: =IFERROR(INDEX(MgAmenFrec,MATCH(SUBSTITUTE($H7,"*","-"),MgAmenClave,0)),"") | W7: =IFERROR(LOOKUP(X7,{0;0.01;0.1;1;10;100},{"Muy baja";"Muy baja";"Baja";"Media";"Alta";"Muy alta"}),"") | X7: =IFERROR(VLOOKUP(V7,MgFrec,2,0),0) | Y7: =T7*X7 | Z7: =IFERROR(LOOKUP(Y7,{0;0.5;5;25},{"Bajo";"Medio";"Alto";"Crítico"}),"") | AA7: =IF(T7>=3,IF(X7>=1,"Zona 1 — Crítica: impacto alto y ocurre al menos una vez al año","Zona 4 — Catastrófica poco probable: impacto alto pero excepcional"),IF(AND(T7<1.5,X7<1),"Zona 3 — Asumible: impacto bajo y muy poco frecuente","Zona 2 — Atención: riesgo intermedio")) | AB7: =IFERROR(INDEX(MgAmenCtrl,MATCH(SUBSTITUTE($H7,"*","-"),MgAmenClave,0)),"") | AD7: =IFERROR($X7*(1-IF($AC7="",$AL7,VLOOKUP($AC7,MgMad,2,0))),"") | AE7: =IFERROR(LOOKUP(AD7,{0;0.01;0.1;1;10;100},{"Muy baja";"Muy baja";"Baja";"Media";"Alta";"Muy alta"}),"") | AF7: =T7*AD7 | AG7: =IFERROR(LOOKUP(AF7,{0;0.5;5;25},{"Bajo";"Medio";"Alto";"Crítico"}),"") | AH7: =IF(AG7="","",IF(OR(AG7="Crítico",AG7="Alto"),"Mitigar",IF(AG7="Medio","Mitigar","Aceptar y monitorear"))) | AL7: =IFERROR(INDEX(MgAmenEfic,MATCH(SUBSTITUTE($H7,"*","-"),MgAmenClave,0)),0)
B8: R-0003 | C8: DO-14 | D8: =IFERROR(INDEX(MgNombre,MATCH($C8,MgActId,0)),"") | E8: =IFERROR(INDEX(MgProceso,MATCH($C8,MgActId,0)),"") | F8: =IFERROR(INDEX(MgTipo,MATCH($C8,MgActId,0)),"") | G8: =IFERROR(INDEX(MgSubtipo,MATCH($C8,MgActId,0)),"") | H8: E.2 | I8: =IFERROR(INDEX(MgAmenNombre,MATCH(SUBSTITUTE($H8,"*","-"),MgAmenClave,0)),"") | J8: =IFERROR(INDEX(MgAmenGrupo,MATCH(SUBSTITUTE($H8,"*","-"),MgAmenClave,0)),"") | K8: =IFERROR(INDEX('1. Matriz de Activos'!$Q$6:$Q$239,MATCH($C8,MgActId,0)),"") | L8: =IFERROR(INDEX('1. Matriz de Activos'!$R$6:$R$239,MATCH($C8,MgActId,0)),"") | M8: =IFERROR(INDEX('1. Matriz de Activos'!$S$6:$S$239,MATCH($C8,MgActId,0)),"") | N8: =IFERROR(INDEX(MgAmenDegD,MATCH(SUBSTITUTE($H8,"*","-"),MgAmenClave,0)),"No aplica") | O8: =IFERROR(INDEX(MgAmenDegI,MATCH(SUBSTITUTE($H8,"*","-"),MgAmenClave,0)),"No aplica") | P8: =IFERROR(INDEX(MgAmenDegC,MATCH(SUBSTITUTE($H8,"*","-"),MgAmenClave,0)),"No aplica") | Q8: =IFERROR(VLOOKUP(K8,MgValor,2,0)*VLOOKUP(N8,MgDeg,2,0),0) | R8: =IFERROR(VLOOKUP(L8,MgValor,2,0)*VLOOKUP(O8,MgDeg,2,0),0) | S8: =IFERROR(VLOOKUP(M8,MgValor,2,0)*VLOOKUP(P8,MgDeg,2,0),0) | T8: =MAX(Q8:S8) | U8: =IFERROR(LOOKUP(T8,{0;0.5;1.5;3;4.5},{"Despreciable";"Bajo";"Medio";"Alto";"Muy alto"}),"") | V8: =IFERROR(INDEX(MgAmenFrec,MATCH(SUBSTITUTE($H8,"*","-"),MgAmenClave,0)),"") | W8: =IFERROR(LOOKUP(X8,{0;0.01;0.1;1;10;100},{"Muy baja";"Muy baja";"Baja";"Media";"Alta";"Muy alta"}),"") | X8: =IFERROR(VLOOKUP(V8,MgFrec,2,0),0) | Y8: =T8*X8 | Z8: =IFERROR(LOOKUP(Y8,{0;0.5;5;25},{"Bajo";"Medio";"Alto";"Crítico"}),"") | AA8: =IF(T8>=3,IF(X8>=1,"Zona 1 — Crítica: impacto alto y ocurre al menos una vez al año","Zona 4 — Catastrófica poco probable: impacto alto pero excepcional"),IF(AND(T8<1.5,X8<1),"Zona 3 — Asumible: impacto bajo y muy poco frecuente","Zona 2 — Atención: riesgo intermedio")) | AB8: =IFERROR(INDEX(MgAmenCtrl,MATCH(SUBSTITUTE($H8,"*","-"),MgAmenClave,0)),"") | AD8: =IFERROR($X8*(1-IF($AC8="",$AL8,VLOOKUP($AC8,MgMad,2,0))),"") | AE8: =IFERROR(LOOKUP(AD8,{0;0.01;0.1;1;10;100},{"Muy baja";"Muy baja";"Baja";"Media";"Alta";"Muy alta"}),"") | AF8: =T8*AD8 | AG8: =IFERROR(LOOKUP(AF8,{0;0.5;5;25},{"Bajo";"Medio";"Alto";"Crítico"}),"") | AH8: =IF(AG8="","",IF(OR(AG8="Crítico",AG8="Alto"),"Mitigar",IF(AG8="Medio","Mitigar","Aceptar y monitorear"))) | AL8: =IFERROR(INDEX(MgAmenEfic,MATCH(SUBSTITUTE($H8,"*","-"),MgAmenClave,0)),0)
B9: R-0004 | C9: DO-14 | D9: =IFERROR(INDEX(MgNombre,MATCH($C9,MgActId,0)),"") | E9: =IFERROR(INDEX(MgProceso,MATCH($C9,MgActId,0)),"") | F9: =IFERROR(INDEX(MgTipo,MATCH($C9,MgActId,0)),"") | G9: =IFERROR(INDEX(MgSubtipo,MATCH($C9,MgActId,0)),"") | H9: E.9 | I9: =IFERROR(INDEX(MgAmenNombre,MATCH(SUBSTITUTE($H9,"*","-"),MgAmenClave,0)),"") | J9: =IFERROR(INDEX(MgAmenGrupo,MATCH(SUBSTITUTE($H9,"*","-"),MgAmenClave,0)),"") | K9: =IFERROR(INDEX('1. Matriz de Activos'!$Q$6:$Q$239,MATCH($C9,MgActId,0)),"") | L9: =IFERROR(INDEX('1. Matriz de Activos'!$R$6:$R$239,MATCH($C9,MgActId,0)),"") | M9: =IFERROR(INDEX('1. Matriz de Activos'!$S$6:$S$239,MATCH($C9,MgActId,0)),"") | N9: =IFERROR(INDEX(MgAmenDegD,MATCH(SUBSTITUTE($H9,"*","-"),MgAmenClave,0)),"No aplica") | O9: =IFERROR(INDEX(MgAmenDegI,MATCH(SUBSTITUTE($H9,"*","-"),MgAmenClave,0)),"No aplica") | P9: =IFERROR(INDEX(MgAmenDegC,MATCH(SUBSTITUTE($H9,"*","-"),MgAmenClave,0)),"No aplica") | Q9: =IFERROR(VLOOKUP(K9,MgValor,2,0)*VLOOKUP(N9,MgDeg,2,0),0) | R9: =IFERROR(VLOOKUP(L9,MgValor,2,0)*VLOOKUP(O9,MgDeg,2,0),0) | S9: =IFERROR(VLOOKUP(M9,MgValor,2,0)*VLOOKUP(P9,MgDeg,2,0),0) | T9: =MAX(Q9:S9) | U9: =IFERROR(LOOKUP(T9,{0;0.5;1.5;3;4.5},{"Despreciable";"Bajo";"Medio";"Alto";"Muy alto"}),"") | V9: =IFERROR(INDEX(MgAmenFrec,MATCH(SUBSTITUTE($H9,"*","-"),MgAmenClave,0)),"") | W9: =IFERROR(LOOKUP(X9,{0;0.01;0.1;1;10;100},{"Muy baja";"Muy baja";"Baja";"Media";"Alta";"Muy alta"}),"") | X9: =IFERROR(VLOOKUP(V9,MgFrec,2,0),0) | Y9: =T9*X9 | Z9: =IFERROR(LOOKUP(Y9,{0;0.5;5;25},{"Bajo";"Medio";"Alto";"Crítico"}),"") | AA9: =IF(T9>=3,IF(X9>=1,"Zona 1 — Crítica: impacto alto y ocurre al menos una vez al año","Zona 4 — Catastrófica poco probable: impacto alto pero excepcional"),IF(AND(T9<1.5,X9<1),"Zona 3 — Asumible: impacto bajo y muy poco frecuente","Zona 2 — Atención: riesgo intermedio")) | AB9: =IFERROR(INDEX(MgAmenCtrl,MATCH(SUBSTITUTE($H9,"*","-"),MgAmenClave,0)),"") | AD9: =IFERROR($X9*(1-IF($AC9="",$AL9,VLOOKUP($AC9,MgMad,2,0))),"") | AE9: =IFERROR(LOOKUP(AD9,{0;0.01;0.1;1;10;100},{"Muy baja";"Muy baja";"Baja";"Media";"Alta";"Muy alta"}),"") | AF9: =T9*AD9 | AG9: =IFERROR(LOOKUP(AF9,{0;0.5;5;25},{"Bajo";"Medio";"Alto";"Crítico"}),"") | AH9: =IF(AG9="","",IF(OR(AG9="Crítico",AG9="Alto"),"Mitigar",IF(AG9="Medio","Mitigar","Aceptar y monitorear"))) | AL9: =IFERROR(INDEX(MgAmenEfic,MATCH(SUBSTITUTE($H9,"*","-"),MgAmenClave,0)),0)
B10: R-0005 | C10: DO-14 | D10: =IFERROR(INDEX(MgNombre,MATCH($C10,MgActId,0)),"") | E10: =IFERROR(INDEX(MgProceso,MATCH($C10,MgActId,0)),"") | F10: =IFERROR(INDEX(MgTipo,MATCH($C10,MgActId,0)),"") | G10: =IFERROR(INDEX(MgSubtipo,MATCH($C10,MgActId,0)),"") | H10: E.10 | I10: =IFERROR(INDEX(MgAmenNombre,MATCH(SUBSTITUTE($H10,"*","-"),MgAmenClave,0)),"") | J10: =IFERROR(INDEX(MgAmenGrupo,MATCH(SUBSTITUTE($H10,"*","-"),MgAmenClave,0)),"") | K10: =IFERROR(INDEX('1. Matriz de Activos'!$Q$6:$Q$239,MATCH($C10,MgActId,0)),"") | L10: =IFERROR(INDEX('1. Matriz de Activos'!$R$6:$R$239,MATCH($C10,MgActId,0)),"") | M10: =IFERROR(INDEX('1. Matriz de Activos'!$S$6:$S$239,MATCH($C10,MgActId,0)),"") | N10: =IFERROR(INDEX(MgAmenDegD,MATCH(SUBSTITUTE($H10,"*","-"),MgAmenClave,0)),"No aplica") | O10: =IFERROR(INDEX(MgAmenDegI,MATCH(SUBSTITUTE($H10,"*","-"),MgAmenClave,0)),"No aplica") | P10: =IFERROR(INDEX(MgAmenDegC,MATCH(SUBSTITUTE($H10,"*","-"),MgAmenClave,0)),"No aplica") | Q10: =IFERROR(VLOOKUP(K10,MgValor,2,0)*VLOOKUP(N10,MgDeg,2,0),0) | R10: =IFERROR(VLOOKUP(L10,MgValor,2,0)*VLOOKUP(O10,MgDeg,2,0),0) | S10: =IFERROR(VLOOKUP(M10,MgValor,2,0)*VLOOKUP(P10,MgDeg,2,0),0) | T10: =MAX(Q10:S10) | U10: =IFERROR(LOOKUP(T10,{0;0.5;1.5;3;4.5},{"Despreciable";"Bajo";"Medio";"Alto";"Muy alto"}),"") | V10: =IFERROR(INDEX(MgAmenFrec,MATCH(SUBSTITUTE($H10,"*","-"),MgAmenClave,0)),"") | W10: =IFERROR(LOOKUP(X10,{0;0.01;0.1;1;10;100},{"Muy baja";"Muy baja";"Baja";"Media";"Alta";"Muy alta"}),"") | X10: =IFERROR(VLOOKUP(V10,MgFrec,2,0),0) | Y10: =T10*X10 | Z10: =IFERROR(LOOKUP(Y10,{0;0.5;5;25},{"Bajo";"Medio";"Alto";"Crítico"}),"") | AA10: =IF(T10>=3,IF(X10>=1,"Zona 1 — Crítica: impacto alto y ocurre al menos una vez al año","Zona 4 — Catastrófica poco probable: impacto alto pero excepcional"),IF(AND(T10<1.5,X10<1),"Zona 3 — Asumible: impacto bajo y muy poco frecuente","Zona 2 — Atención: riesgo intermedio")) | AB10: =IFERROR(INDEX(MgAmenCtrl,MATCH(SUBSTITUTE($H10,"*","-"),MgAmenClave,0)),"") | AD10: =IFERROR($X10*(1-IF($AC10="",$AL10,VLOOKUP($AC10,MgMad,2,0))),"") | AE10: =IFERROR(LOOKUP(AD10,{0;0.01;0.1;1;10;100},{"Muy baja";"Muy baja";"Baja";"Media";"Alta";"Muy alta"}),"") | AF10: =T10*AD10 | AG10: =IFERROR(LOOKUP(AF10,{0;0.5;5;25},{"Bajo";"Medio";"Alto";"Crítico"}),"") | AH10: =IF(AG10="","",IF(OR(AG10="Crítico",AG10="Alto"),"Mitigar",IF(AG10="Medio","Mitigar","Aceptar y monitorear"))) | AL10: =IFERROR(INDEX(MgAmenEfic,MATCH(SUBSTITUTE($H10,"*","-"),MgAmenClave,0)),0)
B11: R-0006 | C11: DO-14 | D11: =IFERROR(INDEX(MgNombre,MATCH($C11,MgActId,0)),"") | E11: =IFERROR(INDEX(MgProceso,MATCH($C11,MgActId,0)),"") | F11: =IFERROR(INDEX(MgTipo,MATCH($C11,MgActId,0)),"") | G11: =IFERROR(INDEX(MgSubtipo,MATCH($C11,MgActId,0)),"") | H11: E.14 | I11: =IFERROR(INDEX(MgAmenNombre,MATCH(SUBSTITUTE($H11,"*","-"),MgAmenClave,0)),"") | J11: =IFERROR(INDEX(MgAmenGrupo,MATCH(SUBSTITUTE($H11,"*","-"),MgAmenClave,0)),"") | K11: =IFERROR(INDEX('1. Matriz de Activos'!$Q$6:$Q$239,MATCH($C11,MgActId,0)),"") | L11: =IFERROR(INDEX('1. Matriz de Activos'!$R$6:$R$239,MATCH($C11,MgActId,0)),"") | M11: =IFERROR(INDEX('1. Matriz de Activos'!$S$6:$S$239,MATCH($C11,MgActId,0)),"") | N11: =IFERROR(INDEX(MgAmenDegD,MATCH(SUBSTITUTE($H11,"*","-"),MgAmenClave,0)),"No aplica") | O11: =IFERROR(INDEX(MgAmenDegI,MATCH(SUBSTITUTE($H11,"*","-"),MgAmenClave,0)),"No aplica") | P11: =IFERROR(INDEX(MgAmenDegC,MATCH(SUBSTITUTE($H11,"*","-"),MgAmenClave,0)),"No aplica") | Q11: =IFERROR(VLOOKUP(K11,MgValor,2,0)*VLOOKUP(N11,MgDeg,2,0),0) | R11: =IFERROR(VLOOKUP(L11,MgValor,2,0)*VLOOKUP(O11,MgDeg,2,0),0) | S11: =IFERROR(VLOOKUP(M11,MgValor,2,0)*VLOOKUP(P11,MgDeg,2,0),0) | T11: =MAX(Q11:S11) | U11: =IFERROR(LOOKUP(T11,{0;0.5;1.5;3;4.5},{"Despreciable";"Bajo";"Medio";"Alto";"Muy alto"}),"") | V11: =IFERROR(INDEX(MgAmenFrec,MATCH(SUBSTITUTE($H11,"*","-"),MgAmenClave,0)),"") | W11: =IFERROR(LOOKUP(X11,{0;0.01;0.1;1;10;100},{"Muy baja";"Muy baja";"Baja";"Media";"Alta";"Muy alta"}),"") | X11: =IFERROR(VLOOKUP(V11,MgFrec,2,0),0) | Y11: =T11*X11 | Z11: =IFERROR(LOOKUP(Y11,{0;0.5;5;25},{"Bajo";"Medio";"Alto";"Crítico"}),"") | AA11: =IF(T11>=3,IF(X11>=1,"Zona 1 — Crítica: impacto alto y ocurre al menos una vez al año","Zona 4 — Catastrófica poco probable: impacto alto pero excepcional"),IF(AND(T11<1.5,X11<1),"Zona 3 — Asumible: impacto bajo y muy poco frecuente","Zona 2 — Atención: riesgo intermedio")) | AB11: =IFERROR(INDEX(MgAmenCtrl,MATCH(SUBSTITUTE($H11,"*","-"),MgAmenClave,0)),"") | AD11: =IFERROR($X11*(1-IF($AC11="",$AL11,VLOOKUP($AC11,MgMad,2,0))),"") | AE11: =IFERROR(LOOKUP(AD11,{0;0.01;0.1;1;10;100},{"Muy baja";"Muy baja";"Baja";"Media";"Alta";"Muy alta"}),"") | AF11: =T11*AD11 | AG11: =IFERROR(LOOKUP(AF11,{0;0.5;5;25},{"Bajo";"Medio";"Alto";"Crítico"}),"") | AH11: =IF(AG11="","",IF(OR(AG11="Crítico",AG11="Alto"),"Mitigar",IF(AG11="Medio","Mitigar","Aceptar y monitorear"))) | AL11: =IFERROR(INDEX(MgAmenEfic,MATCH(SUBSTITUTE($H11,"*","-"),MgAmenClave,0)),0)
B12: R-0007 | C12: DO-14 | D12: =IFERROR(INDEX(MgNombre,MATCH($C12,MgActId,0)),"") | E12: =IFERROR(INDEX(MgProceso,MATCH($C12,MgActId,0)),"") | F12: =IFERROR(INDEX(MgTipo,MATCH($C12,MgActId,0)),"") | G12: =IFERROR(INDEX(MgSubtipo,MATCH($C12,MgActId,0)),"") | H12: E.15 | I12: =IFERROR(INDEX(MgAmenNombre,MATCH(SUBSTITUTE($H12,"*","-"),MgAmenClave,0)),"") | J12: =IFERROR(INDEX(MgAmenGrupo,MATCH(SUBSTITUTE($H12,"*","-"),MgAmenClave,0)),"") | K12: =IFERROR(INDEX('1. Matriz de Activos'!$Q$6:$Q$239,MATCH($C12,MgActId,0)),"") | L12: =IFERROR(INDEX('1. Matriz de Activos'!$R$6:$R$239,MATCH($C12,MgActId,0)),"") | M12: =IFERROR(INDEX('1. Matriz de Activos'!$S$6:$S$239,MATCH($C12,MgActId,0)),"") | N12: =IFERROR(INDEX(MgAmenDegD,MATCH(SUBSTITUTE($H12,"*","-"),MgAmenClave,0)),"No aplica") | O12: =IFERROR(INDEX(MgAmenDegI,MATCH(SUBSTITUTE($H12,"*","-"),MgAmenClave,0)),"No aplica") | P12: =IFERROR(INDEX(MgAmenDegC,MATCH(SUBSTITUTE($H12,"*","-"),MgAmenClave,0)),"No aplica") | Q12: =IFERROR(VLOOKUP(K12,MgValor,2,0)*VLOOKUP(N12,MgDeg,2,0),0) | R12: =IFERROR(VLOOKUP(L12,MgValor,2,0)*VLOOKUP(O12,MgDeg,2,0),0) | S12: =IFERROR(VLOOKUP(M12,MgValor,2,0)*VLOOKUP(P12,MgDeg,2,0),0) | T12: =MAX(Q12:S12) | U12: =IFERROR(LOOKUP(T12,{0;0.5;1.5;3;4.5},{"Despreciable";"Bajo";"Medio";"Alto";"Muy alto"}),"") | V12: =IFERROR(INDEX(MgAmenFrec,MATCH(SUBSTITUTE($H12,"*","-"),MgAmenClave,0)),"") | W12: =IFERROR(LOOKUP(X12,{0;0.01;0.1;1;10;100},{"Muy baja";"Muy baja";"Baja";"Media";"Alta";"Muy alta"}),"") | X12: =IFERROR(VLOOKUP(V12,MgFrec,2,0),0) | Y12: =T12*X12 | Z12: =IFERROR(LOOKUP(Y12,{0;0.5;5;25},{"Bajo";"Medio";"Alto";"Crítico"}),"") | AA12: =IF(T12>=3,IF(X12>=1,"Zona 1 — Crítica: impacto alto y ocurre al menos una vez al año","Zona 4 — Catastrófica poco probable: impacto alto pero excepcional"),IF(AND(T12<1.5,X12<1),"Zona 3 — Asumible: impacto bajo y muy poco frecuente","Zona 2 — Atención: riesgo intermedio")) | AB12: =IFERROR(INDEX(MgAmenCtrl,MATCH(SUBSTITUTE($H12,"*","-"),MgAmenClave,0)),"") | AD12: =IFERROR($X12*(1-IF($AC12="",$AL12,VLOOKUP($AC12,MgMad,2,0))),"") | AE12: =IFERROR(LOOKUP(AD12,{0;0.01;0.1;1;10;100},{"Muy baja";"Muy baja";"Baja";"Media";"Alta";"Muy alta"}),"") | AF12: =T12*AD12 | AG12: =IFERROR(LOOKUP(AF12,{0;0.5;5;25},{"Bajo";"Medio";"Alto";"Crítico"}),"") | AH12: =IF(AG12="","",IF(OR(AG12="Crítico",AG12="Alto"),"Mitigar",IF(AG12="Medio","Mitigar","Aceptar y monitorear"))) | AL12: =IFERROR(INDEX(MgAmenEfic,MATCH(SUBSTITUTE($H12,"*","-"),MgAmenClave,0)),0)
B13: R-0008 | C13: DO-14 | D13: =IFERROR(INDEX(MgNombre,MATCH($C13,MgActId,0)),"") | E13: =IFERROR(INDEX(MgProceso,MATCH($C13,MgActId,0)),"") | F13: =IFERROR(INDEX(MgTipo,MATCH($C13,MgActId,0)),"") | G13: =IFERROR(INDEX(MgSubtipo,MATCH($C13,MgActId,0)),"") | H13: E.18 | I13: =IFERROR(INDEX(MgAmenNombre,MATCH(SUBSTITUTE($H13,"*","-"),MgAmenClave,0)),"") | J13: =IFERROR(INDEX(MgAmenGrupo,MATCH(SUBSTITUTE($H13,"*","-"),MgAmenClave,0)),"") | K13: =IFERROR(INDEX('1. Matriz de Activos'!$Q$6:$Q$239,MATCH($C13,MgActId,0)),"") | L13: =IFERROR(INDEX('1. Matriz de Activos'!$R$6:$R$239,MATCH($C13,MgActId,0)),"") | M13: =IFERROR(INDEX('1. Matriz de Activos'!$S$6:$S$239,MATCH($C13,MgActId,0)),"") | N13: =IFERROR(INDEX(MgAmenDegD,MATCH(SUBSTITUTE($H13,"*","-"),MgAmenClave,0)),"No aplica") | O13: =IFERROR(INDEX(MgAmenDegI,MATCH(SUBSTITUTE($H13,"*","-"),MgAmenClave,0)),"No aplica") | P13: =IFERROR(INDEX(MgAmenDegC,MATCH(SUBSTITUTE($H13,"*","-"),MgAmenClave,0)),"No aplica") | Q13: =IFERROR(VLOOKUP(K13,MgValor,2,0)*VLOOKUP(N13,MgDeg,2,0),0) | R13: =IFERROR(VLOOKUP(L13,MgValor,2,0)*VLOOKUP(O13,MgDeg,2,0),0) | S13: =IFERROR(VLOOKUP(M13,MgValor,2,0)*VLOOKUP(P13,MgDeg,2,0),0) | T13: =MAX(Q13:S13) | U13: =IFERROR(LOOKUP(T13,{0;0.5;1.5;3;4.5},{"Despreciable";"Bajo";"Medio";"Alto";"Muy alto"}),"") | V13: =IFERROR(INDEX(MgAmenFrec,MATCH(SUBSTITUTE($H13,"*","-"),MgAmenClave,0)),"") | W13: =IFERROR(LOOKUP(X13,{0;0.01;0.1;1;10;100},{"Muy baja";"Muy baja";"Baja";"Media";"Alta";"Muy alta"}),"") | X13: =IFERROR(VLOOKUP(V13,MgFrec,2,0),0) | Y13: =T13*X13 | Z13: =IFERROR(LOOKUP(Y13,{0;0.5;5;25},{"Bajo";"Medio";"Alto";"Crítico"}),"") | AA13: =IF(T13>=3,IF(X13>=1,"Zona 1 — Crítica: impacto alto y ocurre al menos una vez al año","Zona 4 — Catastrófica poco probable: impacto alto pero excepcional"),IF(AND(T13<1.5,X13<1),"Zona 3 — Asumible: impacto bajo y muy poco frecuente","Zona 2 — Atención: riesgo intermedio")) | AB13: =IFERROR(INDEX(MgAmenCtrl,MATCH(SUBSTITUTE($H13,"*","-"),MgAmenClave,0)),"") | AD13: =IFERROR($X13*(1-IF($AC13="",$AL13,VLOOKUP($AC13,MgMad,2,0))),"") | AE13: =IFERROR(LOOKUP(AD13,{0;0.01;0.1;1;10;100},{"Muy baja";"Muy baja";"Baja";"Media";"Alta";"Muy alta"}),"") | AF13: =T13*AD13 | AG13: =IFERROR(LOOKUP(AF13,{0;0.5;5;25},{"Bajo";"Medio";"Alto";"Crítico"}),"") | AH13: =IF(AG13="","",IF(OR(AG13="Crítico",AG13="Alto"),"Mitigar",IF(AG13="Medio","Mitigar","Aceptar y monitorear"))) | AL13: =IFERROR(INDEX(MgAmenEfic,MATCH(SUBSTITUTE($H13,"*","-"),MgAmenClave,0)),0)
B14: R-0009 | C14: DO-14 | D14: =IFERROR(INDEX(MgNombre,MATCH($C14,MgActId,0)),"") | E14: =IFERROR(INDEX(MgProceso,MATCH($C14,MgActId,0)),"") | F14: =IFERROR(INDEX(MgTipo,MATCH($C14,MgActId,0)),"") | G14: =IFERROR(INDEX(MgSubtipo,MATCH($C14,MgActId,0)),"") | H14: E.19 | I14: =IFERROR(INDEX(MgAmenNombre,MATCH(SUBSTITUTE($H14,"*","-"),MgAmenClave,0)),"") | J14: =IFERROR(INDEX(MgAmenGrupo,MATCH(SUBSTITUTE($H14,"*","-"),MgAmenClave,0)),"") | K14: =IFERROR(INDEX('1. Matriz de Activos'!$Q$6:$Q$239,MATCH($C14,MgActId,0)),"") | L14: =IFERROR(INDEX('1. Matriz de Activos'!$R$6:$R$239,MATCH($C14,MgActId,0)),"") | M14: =IFERROR(INDEX('1. Matriz de Activos'!$S$6:$S$239,MATCH($C14,MgActId,0)),"") | N14: =IFERROR(INDEX(MgAmenDegD,MATCH(SUBSTITUTE($H14,"*","-"),MgAmenClave,0)),"No aplica") | O14: =IFERROR(INDEX(MgAmenDegI,MATCH(SUBSTITUTE($H14,"*","-"),MgAmenClave,0)),"No aplica") | P14: =IFERROR(INDEX(MgAmenDegC,MATCH(SUBSTITUTE($H14,"*","-"),MgAmenClave,0)),"No aplica") | Q14: =IFERROR(VLOOKUP(K14,MgValor,2,0)*VLOOKUP(N14,MgDeg,2,0),0) | R14: =IFERROR(VLOOKUP(L14,MgValor,2,0)*VLOOKUP(O14,MgDeg,2,0),0) | S14: =IFERROR(VLOOKUP(M14,MgValor,2,0)*VLOOKUP(P14,MgDeg,2,0),0) | T14: =MAX(Q14:S14) | U14: =IFERROR(LOOKUP(T14,{0;0.5;1.5;3;4.5},{"Despreciable";"Bajo";"Medio";"Alto";"Muy alto"}),"") | V14: =IFERROR(INDEX(MgAmenFrec,MATCH(SUBSTITUTE($H14,"*","-"),MgAmenClave,0)),"") | W14: =IFERROR(LOOKUP(X14,{0;0.01;0.1;1;10;100},{"Muy baja";"Muy baja";"Baja";"Media";"Alta";"Muy alta"}),"") | X14: =IFERROR(VLOOKUP(V14,MgFrec,2,0),0) | Y14: =T14*X14 | Z14: =IFERROR(LOOKUP(Y14,{0;0.5;5;25},{"Bajo";"Medio";"Alto";"Crítico"}),"") | AA14: =IF(T14>=3,IF(X14>=1,"Zona 1 — Crítica: impacto alto y ocurre al menos una vez al año","Zona 4 — Catastrófica poco probable: impacto alto pero excepcional"),IF(AND(T14<1.5,X14<1),"Zona 3 — Asumible: impacto bajo y muy poco frecuente","Zona 2 — Atención: riesgo intermedio")) | AB14: =IFERROR(INDEX(MgAmenCtrl,MATCH(SUBSTITUTE($H14,"*","-"),MgAmenClave,0)),"") | AD14: =IFERROR($X14*(1-IF($AC14="",$AL14,VLOOKUP($AC14,MgMad,2,0))),"") | AE14: =IFERROR(LOOKUP(AD14,{0;0.01;0.1;1;10;100},{"Muy baja";"Muy baja";"Baja";"Media";"Alta";"Muy alta"}),"") | AF14: =T14*AD14 | AG14: =IFERROR(LOOKUP(AF14,{0;0.5;5;25},{"Bajo";"Medio";"Alto";"Crítico"}),"") | AH14: =IF(AG14="","",IF(OR(AG14="Crítico",AG14="Alto"),"Mitigar",IF(AG14="Medio","Mitigar","Aceptar y monitorear"))) | AL14: =IFERROR(INDEX(MgAmenEfic,MATCH(SUBSTITUTE($H14,"*","-"),MgAmenClave,0)),0)
B15: R-0010 | C15: DO-14 | D15: =IFERROR(INDEX(MgNombre,MATCH($C15,MgActId,0)),"") | E15: =IFERROR(INDEX(MgProceso,MATCH($C15,MgActId,0)),"") | F15: =IFERROR(INDEX(MgTipo,MATCH($C15,MgActId,0)),"") | G15: =IFERROR(INDEX(MgSubtipo,MATCH($C15,MgActId,0)),"") | H15: E.24 | I15: =IFERROR(INDEX(MgAmenNombre,MATCH(SUBSTITUTE($H15,"*","-"),MgAmenClave,0)),"") | J15: =IFERROR(INDEX(MgAmenGrupo,MATCH(SUBSTITUTE($H15,"*","-"),MgAmenClave,0)),"") | K15: =IFERROR(INDEX('1. Matriz de Activos'!$Q$6:$Q$239,MATCH($C15,MgActId,0)),"") | L15: =IFERROR(INDEX('1. Matriz de Activos'!$R$6:$R$239,MATCH($C15,MgActId,0)),"") | M15: =IFERROR(INDEX('1. Matriz de Activos'!$S$6:$S$239,MATCH($C15,MgActId,0)),"") | N15: =IFERROR(INDEX(MgAmenDegD,MATCH(SUBSTITUTE($H15,"*","-"),MgAmenClave,0)),"No aplica") | O15: =IFERROR(INDEX(MgAmenDegI,MATCH(SUBSTITUTE($H15,"*","-"),MgAmenClave,0)),"No aplica") | P15: =IFERROR(INDEX(MgAmenDegC,MATCH(SUBSTITUTE($H15,"*","-"),MgAmenClave,0)),"No aplica") | Q15: =IFERROR(VLOOKUP(K15,MgValor,2,0)*VLOOKUP(N15,MgDeg,2,0),0) | R15: =IFERROR(VLOOKUP(L15,MgValor,2,0)*VLOOKUP(O15,MgDeg,2,0),0) | S15: =IFERROR(VLOOKUP(M15,MgValor,2,0)*VLOOKUP(P15,MgDeg,2,0),0) | T15: =MAX(Q15:S15) | U15: =IFERROR(LOOKUP(T15,{0;0.5;1.5;3;4.5},{"Despreciable";"Bajo";"Medio";"Alto";"Muy alto"}),"") | V15: =IFERROR(INDEX(MgAmenFrec,MATCH(SUBSTITUTE($H15,"*","-"),MgAmenClave,0)),"") | W15: =IFERROR(LOOKUP(X15,{0;0.01;0.1;1;10;100},{"Muy baja";"Muy baja";"Baja";"Media";"Alta";"Muy alta"}),"") | X15: =IFERROR(VLOOKUP(V15,MgFrec,2,0),0) | Y15: =T15*X15 | Z15: =IFERROR(LOOKUP(Y15,{0;0.5;5;25},{"Bajo";"Medio";"Alto";"Crítico"}),"") | AA15: =IF(T15>=3,IF(X15>=1,"Zona 1 — Crítica: impacto alto y ocurre al menos una vez al año","Zona 4 — Catastrófica poco probable: impacto alto pero excepcional"),IF(AND(T15<1.5,X15<1),"Zona 3 — Asumible: impacto bajo y muy poco frecuente","Zona 2 — Atención: riesgo intermedio")) | AB15: =IFERROR(INDEX(MgAmenCtrl,MATCH(SUBSTITUTE($H15,"*","-"),MgAmenClave,0)),"") | AD15: =IFERROR($X15*(1-IF($AC15="",$AL15,VLOOKUP($AC15,MgMad,2,0))),"") | AE15: =IFERROR(LOOKUP(AD15,{0;0.01;0.1;1;10;100},{"Muy baja";"Muy baja";"Baja";"Media";"Alta";"Muy alta"}),"") | AF15: =T15*AD15 | AG15: =IFERROR(LOOKUP(AF15,{0;0.5;5;25},{"Bajo";"Medio";"Alto";"Crítico"}),"") | AH15: =IF(AG15="","",IF(OR(AG15="Crítico",AG15="Alto"),"Mitigar",IF(AG15="Medio","Mitigar","Aceptar y monitorear"))) | AL15: =IFERROR(INDEX(MgAmenEfic,MATCH(SUBSTITUTE($H15,"*","-"),MgAmenClave,0)),0)
B16: R-0011 | C16: DO-14 | D16: =IFERROR(INDEX(MgNombre,MATCH($C16,MgActId,0)),"") | E16: =IFERROR(INDEX(MgProceso,MATCH($C16,MgActId,0)),"") | F16: =IFERROR(INDEX(MgTipo,MATCH($C16,MgActId,0)),"") | G16: =IFERROR(INDEX(MgSubtipo,MATCH($C16,MgActId,0)),"") | H16: A.5 | I16: =IFERROR(INDEX(MgAmenNombre,MATCH(SUBSTITUTE($H16,"*","-"),MgAmenClave,0)),"") | J16: =IFERROR(INDEX(MgAmenGrupo,MATCH(SUBSTITUTE($H16,"*","-"),MgAmenClave,0)),"") | K16: =IFERROR(INDEX('1. Matriz de Activos'!$Q$6:$Q$239,MATCH($C16,MgActId,0)),"") | L16: =IFERROR(INDEX('1. Matriz de Activos'!$R$6:$R$239,MATCH($C16,MgActId,0)),"") | M16: =IFERROR(INDEX('1. Matriz de Activos'!$S$6:$S$239,MATCH($C16,MgActId,0)),"") | N16: =IFERROR(INDEX(MgAmenDegD,MATCH(SUBSTITUTE($H16,"*","-"),MgAmenClave,0)),"No aplica") | O16: =IFERROR(INDEX(MgAmenDegI,MATCH(SUBSTITUTE($H16,"*","-"),MgAmenClave,0)),"No aplica") | P16: =IFERROR(INDEX(MgAmenDegC,MATCH(SUBSTITUTE($H16,"*","-"),MgAmenClave,0)),"No aplica") | Q16: =IFERROR(VLOOKUP(K16,MgValor,2,0)*VLOOKUP(N16,MgDeg,2,0),0) | R16: =IFERROR(VLOOKUP(L16,MgValor,2,0)*VLOOKUP(O16,MgDeg,2,0),0) | S16: =IFERROR(VLOOKUP(M16,MgValor,2,0)*VLOOKUP(P16,MgDeg,2,0),0) | T16: =MAX(Q16:S16) | U16: =IFERROR(LOOKUP(T16,{0;0.5;1.5;3;4.5},{"Despreciable";"Bajo";"Medio";"Alto";"Muy alto"}),"") | V16: =IFERROR(INDEX(MgAmenFrec,MATCH(SUBSTITUTE($H16,"*","-"),MgAmenClave,0)),"") | W16: =IFERROR(LOOKUP(X16,{0;0.01;0.1;1;10;100},{"Muy baja";"Muy baja";"Baja";"Media";"Alta";"Muy alta"}),"") | X16: =IFERROR(VLOOKUP(V16,MgFrec,2,0),0) | Y16: =T16*X16 | Z16: =IFERROR(LOOKUP(Y16,{0;0.5;5;25},{"Bajo";"Medio";"Alto";"Crítico"}),"") | AA16: =IF(T16>=3,IF(X16>=1,"Zona 1 — Crítica: impacto alto y ocurre al menos una vez al año","Zona 4 — Catastrófica poco probable: impacto alto pero excepcional"),IF(AND(T16<1.5,X16<1),"Zona 3 — Asumible: impacto bajo y muy poco frecuente","Zona 2 — Atención: riesgo intermedio")) | AB16: =IFERROR(INDEX(MgAmenCtrl,MATCH(SUBSTITUTE($H16,"*","-"),MgAmenClave,0)),"") | AD16: =IFERROR($X16*(1-IF($AC16="",$AL16,VLOOKUP($AC16,MgMad,2,0))),"") | AE16: =IFERROR(LOOKUP(AD16,{0;0.01;0.1;1;10;100},{"Muy baja";"Muy baja";"Baja";"Media";"Alta";"Muy alta"}),"") | AF16: =T16*AD16 | AG16: =IFERROR(LOOKUP(AF16,{0;0.5;5;25},{"Bajo";"Medio";"Alto";"Crítico"}),"") | AH16: =IF(AG16="","",IF(OR(AG16="Crítico",AG16="Alto"),"Mitigar",IF(AG16="Medio","Mitigar","Aceptar y monitorear"))) | AL16: =IFERROR(INDEX(MgAmenEfic,MATCH(SUBSTITUTE($H16,"*","-"),MgAmenClave,0)),0)
B17: R-0012 | C17: DO-14 | D17: =IFERROR(INDEX(MgNombre,MATCH($C17,MgActId,0)),"") | E17: =IFERROR(INDEX(MgProceso,MATCH($C17,MgActId,0)),"") | F17: =IFERROR(INDEX(MgTipo,MATCH($C17,MgActId,0)),"") | G17: =IFERROR(INDEX(MgSubtipo,MATCH($C17,MgActId,0)),"") | H17: A.6 | I17: =IFERROR(INDEX(MgAmenNombre,MATCH(SUBSTITUTE($H17,"*","-"),MgAmenClave,0)),"") | J17: =IFERROR(INDEX(MgAmenGrupo,MATCH(SUBSTITUTE($H17,"*","-"),MgAmenClave,0)),"") | K17: =IFERROR(INDEX('1. Matriz de Activos'!$Q$6:$Q$239,MATCH($C17,MgActId,0)),"") | L17: =IFERROR(INDEX('1. Matriz de Activos'!$R$6:$R$239,MATCH($C17,MgActId,0)),"") | M17: =IFERROR(INDEX('1. Matriz de Activos'!$S$6:$S$239,MATCH($C17,MgActId,0)),"") | N17: =IFERROR(INDEX(MgAmenDegD,MATCH(SUBSTITUTE($H17,"*","-"),MgAmenClave,0)),"No aplica") | O17: =IFERROR(INDEX(MgAmenDegI,MATCH(SUBSTITUTE($H17,"*","-"),MgAmenClave,0)),"No aplica") | P17: =IFERROR(INDEX(MgAmenDegC,MATCH(SUBSTITUTE($H17,"*","-"),MgAmenClave,0)),"No aplica") | Q17: =IFERROR(VLOOKUP(K17,MgValor,2,0)*VLOOKUP(N17,MgDeg,2,0),0) | R17: =IFERROR(VLOOKUP(L17,MgValor,2,0)*VLOOKUP(O17,MgDeg,2,0),0) | S17: =IFERROR(VLOOKUP(M17,MgValor,2,0)*VLOOKUP(P17,MgDeg,2,0),0) | T17: =MAX(Q17:S17) | U17: =IFERROR(LOOKUP(T17,{0;0.5;1.5;3;4.5},{"Despreciable";"Bajo";"Medio";"Alto";"Muy alto"}),"") | V17: =IFERROR(INDEX(MgAmenFrec,MATCH(SUBSTITUTE($H17,"*","-"),MgAmenClave,0)),"") | W17: =IFERROR(LOOKUP(X17,{0;0.01;0.1;1;10;100},{"Muy baja";"Muy baja";"Baja";"Media";"Alta";"Muy alta"}),"") | X17: =IFERROR(VLOOKUP(V17,MgFrec,2,0),0) | Y17: =T17*X17 | Z17: =IFERROR(LOOKUP(Y17,{0;0.5;5;25},{"Bajo";"Medio";"Alto";"Crítico"}),"") | AA17: =IF(T17>=3,IF(X17>=1,"Zona 1 — Crítica: impacto alto y ocurre al menos una vez al año","Zona 4 — Catastrófica poco probable: impacto alto pero excepcional"),IF(AND(T17<1.5,X17<1),"Zona 3 — Asumible: impacto bajo y muy poco frecuente","Zona 2 — Atención: riesgo intermedio")) | AB17: =IFERROR(INDEX(MgAmenCtrl,MATCH(SUBSTITUTE($H17,"*","-"),MgAmenClave,0)),"") | AD17: =IFERROR($X17*(1-IF($AC17="",$AL17,VLOOKUP($AC17,MgMad,2,0))),"") | AE17: =IFERROR(LOOKUP(AD17,{0;0.01;0.1;1;10;100},{"Muy baja";"Muy baja";"Baja";"Media";"Alta";"Muy alta"}),"") | AF17: =T17*AD17 | AG17: =IFERROR(LOOKUP(AF17,{0;0.5;5;25},{"Bajo";"Medio";"Alto";"Crítico"}),"") | AH17: =IF(AG17="","",IF(OR(AG17="Crítico",AG17="Alto"),"Mitigar",IF(AG17="Medio","Mitigar","Aceptar y monitorear"))) | AL17: =IFERROR(INDEX(MgAmenEfic,MATCH(SUBSTITUTE($H17,"*","-"),MgAmenClave,0)),0)
... B2261: R-2256 | C2261: FIN-26 | D2261: =IFERROR(INDEX(MgNombre,MATCH($C2261,MgActId,0)),"") | E2261: =IFERROR(INDEX(MgProceso,MATCH($C2261,MgActId,0)),"") | F2261: =IFERROR(INDEX(MgTipo,MATCH($C2261,MgActId,0)),"") | G2261: =IFERROR(INDEX(MgSubtipo,MATCH($C2261,MgActId,0)),"") | H2261: A.24 | I2261: =IFERROR(INDEX(MgAmenNombre,MATCH(SUBSTITUTE($H2261,"*","-"),MgAmenClave,0)),"") | J2261: =IFERROR(INDEX(MgAmenGrupo,MATCH(SUBSTITUTE($H2261,"*","-"),MgAmenClave,0)),"") | K2261: =IFERROR(INDEX('1. Matriz de Activos'!$Q$6:$Q$239,MATCH($C2261,MgActId,0)),"") | L2261: =IFERROR(INDEX('1. Matriz de Activos'!$R$6:$R$239,MATCH($C2261,MgActId,0)),"") | M2261: =IFERROR(INDEX('1. Matriz de Activos'!$S$6:$S$239,MATCH($C2261,MgActId,0)),"") | N2261: =IFERROR(INDEX(MgAmenDegD,MATCH(SUBSTITUTE($H2261,"*","-"),MgAmenClave,0)),"No aplica") | O2261: =IFERROR(INDEX(MgAmenDegI,MATCH(SUBSTITUTE($H2261,"*","-"),MgAmenClave,0)),"No aplica") | P2261: =IFERROR(INDEX(MgAmenDegC,MATCH(SUBSTITUTE($H2261,"*","-"),MgAmenClave,0)),"No aplica") | Q2261: =IFERROR(VLOOKUP(K2261,MgValor,2,0)*VLOOKUP(N2261,MgDeg,2,0),0) | R2261: =IFERROR(VLOOKUP(L2261,MgValor,2,0)*VLOOKUP(O2261,MgDeg,2,0),0) | S2261: =IFERROR(VLOOKUP(M2261,MgValor,2,0)*VLOOKUP(P2261,MgDeg,2,0),0) | T2261: =MAX(Q2261:S2261) | U2261: =IFERROR(LOOKUP(T2261,{0;0.5;1.5;3;4.5},{"Despreciable";"Bajo";"Medio";"Alto";"Muy alto"}),"") | V2261: =IFERROR(INDEX(MgAmenFrec,MATCH(SUBSTITUTE($H2261,"*","-"),MgAmenClave,0)),"") | W2261: =IFERROR(LOOKUP(X2261,{0;0.01;0.1;1;10;100},{"Muy baja";"Muy baja";"Baja";"Media";"Alta";"Muy alta"}),"") | X2261: =IFERROR(VLOOKUP(V2261,MgFrec,2,0),0) | Y2261: =T2261*X2261 | Z2261: =IFERROR(LOOKUP(Y2261,{0;0.5;5;25},{"Bajo";"Medio";"Alto";"Crítico"}),"") | AA2261: =IF(T2261>=3,IF(X2261>=1,"Zona 1 — Crítica: impacto alto y ocurre al menos una vez al año","Zona 4 — Catastrófica poco probable: impacto alto pero excepcional"),IF(AND(T2261<1.5,X2261<1),"Zona 3 — Asumible: impacto bajo y muy poco frecuente","Zona 2 — Atención: riesgo intermedio")) | AB2261: =IFERROR(INDEX(MgAmenCtrl,MATCH(SUBSTITUTE($H2261,"*","-"),MgAmenClave,0)),"") | AD2261: =IFERROR($X2261*(1-IF($AC2261="",$AL2261,VLOOKUP($AC2261,MgMad,2,0))),"") | AE2261: =IFERROR(LOOKUP(AD2261,{0;0.01;0.1;1;10;100},{"Muy baja";"Muy baja";"Baja";"Media";"Alta";"Muy alta"}),"") | AF2261: =T2261*AD2261 | AG2261: =IFERROR(LOOKUP(AF2261,{0;0.5;5;25},{"Bajo";"Medio";"Alto";"Crítico"}),"") | AH2261: =IF(AG2261="","",IF(OR(AG2261="Crítico",AG2261="Alto"),"Mitigar",IF(AG2261="Medio","Mitigar","Aceptar y monitorear"))) | AL2261: =IFERROR(INDEX(MgAmenEfic,MATCH(SUBSTITUTE($H2261,"*","-"),MgAmenClave,0)),0)

Sheet 3. Matrices de Riesgo
B1: MATRICES DE RIESGO INHERENTE Y RESIDUAL
B2: Distribución de los riesgos según su nivel de impacto y la frecuencia con que se espera que ocurran. El color de cada casilla es el nivel de riesgo que resulta de esa combinación; el número es cuántos riesgos caen ahí.
B3: Código de color: | C3: Amarillo = Campo de entrada — se selecciona de una lista | E3: Lila = Calculado automáticamente — no escribir encima | G3: Gris = Dato de la norma MAGERIT — no modificar
B5: MATRIZ DE RIESGO INHERENTE — antes de aplicar los controles | I5: RECUENTO POR NIVEL DE RIESGO
B6: Nivel de impacto ↓ Frecuencia → | C6: Muy baja | D6: Baja | E6: Media | F6: Alta | G6: Muy alta | I6: Nivel de riesgo | J6: Inherente | K6: Residual
B7: Muy alto | C7: =COUNTIFS('2. Valoración '!$U$6:$U$2261,$B7,'2. Valoración '!$W$6:$W$2261,C$6) | D7: =COUNTIFS('2. Valoración '!$U$6:$U$2261,$B7,'2. Valoración '!$W$6:$W$2261,D$6) | E7: =COUNTIFS('2. Valoración '!$U$6:$U$2261,$B7,'2. Valoración '!$W$6:$W$2261,E$6) | F7: =COUNTIFS('2. Valoración '!$U$6:$U$2261,$B7,'2. Valoración '!$W$6:$W$2261,F$6) | G7: =COUNTIFS('2. Valoración '!$U$6:$U$2261,$B7,'2. Valoración '!$W$6:$W$2261,G$6) | I7: Crítico | J7: =COUNTIF('2. Valoración '!$Z$6:$Z$2261,$I7) | K7: =COUNTIF('2. Valoración '!$AG$6:$AG$2261,$I7)
B8: Alto | C8: =COUNTIFS('2. Valoración '!$U$6:$U$2261,$B8,'2. Valoración '!$W$6:$W$2261,C$6) | D8: =COUNTIFS('2. Valoración '!$U$6:$U$2261,$B8,'2. Valoración '!$W$6:$W$2261,D$6) | E8: =COUNTIFS('2. Valoración '!$U$6:$U$2261,$B8,'2. Valoración '!$W$6:$W$2261,E$6) | F8: =COUNTIFS('2. Valoración '!$U$6:$U$2261,$B8,'2. Valoración '!$W$6:$W$2261,F$6) | G8: =COUNTIFS('2. Valoración '!$U$6:$U$2261,$B8,'2. Valoración '!$W$6:$W$2261,G$6) | I8: Alto | J8: =COUNTIF('2. Valoración '!$Z$6:$Z$2261,$I8) | K8: =COUNTIF('2. Valoración '!$AG$6:$AG$2261,$I8)
B9: Medio | C9: =COUNTIFS('2. Valoración '!$U$6:$U$2261,$B9,'2. Valoración '!$W$6:$W$2261,C$6) | D9: =COUNTIFS('2. Valoración '!$U$6:$U$2261,$B9,'2. Valoración '!$W$6:$W$2261,D$6) | E9: =COUNTIFS('2. Valoración '!$U$6:$U$2261,$B9,'2. Valoración '!$W$6:$W$2261,E$6) | F9: =COUNTIFS('2. Valoración '!$U$6:$U$2261,$B9,'2. Valoración '!$W$6:$W$2261,F$6) | G9: =COUNTIFS('2. Valoración '!$U$6:$U$2261,$B9,'2. Valoración '!$W$6:$W$2261,G$6) | I9: Medio | J9: =COUNTIF('2. Valoración '!$Z$6:$Z$2261,$I9) | K9: =COUNTIF('2. Valoración '!$AG$6:$AG$2261,$I9)
B10: Bajo | C10: =COUNTIFS('2. Valoración '!$U$6:$U$2261,$B10,'2. Valoración '!$W$6:$W$2261,C$6) | D10: =COUNTIFS('2. Valoración '!$U$6:$U$2261,$B10,'2. Valoración '!$W$6:$W$2261,D$6) | E10: =COUNTIFS('2. Valoración '!$U$6:$U$2261,$B10,'2. Valoración '!$W$6:$W$2261,E$6) | F10: =COUNTIFS('2. Valoración '!$U$6:$U$2261,$B10,'2. Valoración '!$W$6:$W$2261,F$6) | G10: =COUNTIFS('2. Valoración '!$U$6:$U$2261,$B10,'2. Valoración '!$W$6:$W$2261,G$6) | I10: Bajo | J10: =COUNTIF('2. Valoración '!$Z$6:$Z$2261,$I10) | K10: =COUNTIF('2. Valoración '!$AG$6:$AG$2261,$I10)
B11: Despreciable | C11: =COUNTIFS('2. Valoración '!$U$6:$U$2261,$B11,'2. Valoración '!$W$6:$W$2261,C$6) | D11: =COUNTIFS('2. Valoración '!$U$6:$U$2261,$B11,'2. Valoración '!$W$6:$W$2261,D$6) | E11: =COUNTIFS('2. Valoración '!$U$6:$U$2261,$B11,'2. Valoración '!$W$6:$W$2261,E$6) | F11: =COUNTIFS('2. Valoración '!$U$6:$U$2261,$B11,'2. Valoración '!$W$6:$W$2261,F$6) | G11: =COUNTIFS('2. Valoración '!$U$6:$U$2261,$B11,'2. Valoración '!$W$6:$W$2261,G$6) | I11: Total | J11: =SUM(J7:J10) | K11: =SUM(K7:K10)
B12: Total | C12: =SUM(C7:G11)
I13: CRITERIO DE COLOR DE LAS CASILLAS
I14: Crítico | J14: 25 o más
B15: MATRIZ DE RIESGO RESIDUAL — después de aplicar los controles preventivos | I15: Alto | J15: de 5 a menos de 25
B16: Nivel de impacto ↓ Frecuencia → | C16: Muy baja | D16: Baja | E16: Media | F16: Alta | G16: Muy alta | I16: Medio | J16: de 0,5 a menos de 5
B17: Muy alto | C17: =COUNTIFS('2. Valoración '!$U$6:$U$2261,$B17,'2. Valoración '!$AE$6:$AE$2261,C$16) | D17: =COUNTIFS('2. Valoración '!$U$6:$U$2261,$B17,'2. Valoración '!$AE$6:$AE$2261,D$16) | E17: =COUNTIFS('2. Valoración '!$U$6:$U$2261,$B17,'2. Valoración '!$AE$6:$AE$2261,E$16) | F17: =COUNTIFS('2. Valoración '!$U$6:$U$2261,$B17,'2. Valoración '!$AE$6:$AE$2261,F$16) | G17: =COUNTIFS('2. Valoración '!$U$6:$U$2261,$B17,'2. Valoración '!$AE$6:$AE$2261,G$16) | I17: Bajo | J17: menos de 0,5
B18: Alto | C18: =COUNTIFS('2. Valoración '!$U$6:$U$2261,$B18,'2. Valoración '!$AE$6:$AE$2261,C$16) | D18: =COUNTIFS('2. Valoración '!$U$6:$U$2261,$B18,'2. Valoración '!$AE$6:$AE$2261,D$16) | E18: =COUNTIFS('2. Valoración '!$U$6:$U$2261,$B18,'2. Valoración '!$AE$6:$AE$2261,E$16) | F18: =COUNTIFS('2. Valoración '!$U$6:$U$2261,$B18,'2. Valoración '!$AE$6:$AE$2261,F$16) | G18: =COUNTIFS('2. Valoración '!$U$6:$U$2261,$B18,'2. Valoración '!$AE$6:$AE$2261,G$16)
B19: Medio | C19: =COUNTIFS('2. Valoración '!$U$6:$U$2261,$B19,'2. Valoración '!$AE$6:$AE$2261,C$16) | D19: =COUNTIFS('2. Valoración '!$U$6:$U$2261,$B19,'2. Valoración '!$AE$6:$AE$2261,D$16) | E19: =COUNTIFS('2. Valoración '!$U$6:$U$2261,$B19,'2. Valoración '!$AE$6:$AE$2261,E$16) | F19: =COUNTIFS('2. Valoración '!$U$6:$U$2261,$B19,'2. Valoración '!$AE$6:$AE$2261,F$16) | G19: =COUNTIFS('2. Valoración '!$U$6:$U$2261,$B19,'2. Valoración '!$AE$6:$AE$2261,G$16)
B20: Bajo | C20: =COUNTIFS('2. Valoración '!$U$6:$U$2261,$B20,'2. Valoración '!$AE$6:$AE$2261,C$16) | D20: =COUNTIFS('2. Valoración '!$U$6:$U$2261,$B20,'2. Valoración '!$AE$6:$AE$2261,D$16) | E20: =COUNTIFS('2. Valoración '!$U$6:$U$2261,$B20,'2. Valoración '!$AE$6:$AE$2261,E$16) | F20: =COUNTIFS('2. Valoración '!$U$6:$U$2261,$B20,'2. Valoración '!$AE$6:$AE$2261,F$16) | G20: =COUNTIFS('2. Valoración '!$U$6:$U$2261,$B20,'2. Valoración '!$AE$6:$AE$2261,G$16)
B21: Despreciable | C21: =COUNTIFS('2. Valoración '!$U$6:$U$2261,$B21,'2. Valoración '!$AE$6:$AE$2261,C$16) | D21: =COUNTIFS('2. Valoración '!$U$6:$U$2261,$B21,'2. Valoración '!$AE$6:$AE$2261,D$16) | E21: =COUNTIFS('2. Valoración '!$U$6:$U$2261,$B21,'2. Valoración '!$AE$6:$AE$2261,E$16) | F21: =COUNTIFS('2. Valoración '!$U$6:$U$2261,$B21,'2. Valoración '!$AE$6:$AE$2261,F$16) | G21: =COUNTIFS('2. Valoración '!$U$6:$U$2261,$B21,'2. Valoración '!$AE$6:$AE$2261,G$16)
B22: Total | C22: =SUM(C17:G21)
B25: Cómo leer las matrices
B26: El nivel de riesgo se obtiene multiplicando el impacto por las veces que se espera que la amenaza ocurra al año. Por eso un impacto moderado que ocurre todos los meses puede pesar más que un impacto muy alto que ocurre una vez cada cien años.
B27: La matriz inherente muestra la situación sin ningún control. La residual muestra la misma población de riesgos después de descontar la eficacia de los controles preventivos, que actúan reduciendo la frecuencia con que la amenaza llega a materializarse.
B28: El eje de impacto no cambia entre una matriz y otra: los controles que limitan el daño se reflejan bajando la degradación de la amenaza en la hoja «Amenazas MAGERIT», no en la eficacia. Mientras la madurez de los controles esté en «L0 — Inexistente», las dos matrices serán idénticas.
B29: Ambas matrices se recalculan solas: cuentan directamente sobre la hoja «2. Valoración».

Sheet 4. Controles y Madurez
B1: CONTROLES ISO/IEC 27001:2022 — EVALUACIÓN DE MADUREZ
B2: Los 93 controles del Anexo A con su nivel de madurez CMM. La eficacia alimenta el riesgo residual de la hoja de Valoración. Corte de agosto de 2026, primer año de operación del SGSI.
B3: Código de color: | C3: Amarillo = Campo de entrada — se selecciona de una lista | E3: Lila = Calculado automáticamente — no escribir encima | G3: Gris = Dato de la norma MAGERIT — no modificar
B5: Código | C5: Control | D5: Dominio | E5: Capacidad operativa | F5: ¿Aplica? | G5: Madurez línea base | H5: Madurez actual | I5: Madurez objetivo | J5: Eficacia actual | K5: Nivel actual | L5: Nivel objetivo | M5: Brecha (niveles) | N5: Estado | O5: Avance desde la línea base | P5: Evidencia o justificación | Q5: Responsable | R5: Fecha objetivo | S5: Amenazas que mitiga | T5: N.º de riesgos que toca | U5: Nivel línea base (aux.) | V5: Nivel aplicable (aux.) | W5: Nivel Organizacional (aux.) | X5: Nivel Personas (aux.) | Y5: Nivel Físico (aux.) | Z5: Nivel Tecnológico (aux.)
B6: A.5.1 | C6: Políticas de seguridad de la información | D6: Organizacional | E6: Gobierno | F6: Aplica | G6: L0 — Inexistente | H6: L3 — Proceso definido | I6: L4 — Gestionado y medible | J6: =IF($F6="No aplica","",IFERROR(VLOOKUP(H6,MgMad,2,0),0)) | K6: =IF($F6="No aplica","",IFERROR(VALUE(MID(H6,2,1)),"")) | L6: =IF($F6="No aplica","",IFERROR(VALUE(MID(I6,2,1)),"")) | M6: =IF($F6="No aplica","",MAX(0,L6-K6)) | N6: =IF($F6="No aplica","No aplica",IF(M6=0,"Cumple el objetivo",IF(K6>=3,"Gestionado, con brecha","Brecha prioritaria"))) | O6: =IF($F6="No aplica","",K6-IFERROR(VALUE(MID(G6,2,1)),0)) | P6: 11 políticas aprobadas, publicadas en SharePoint y comunicadas. El primer ciclo de revisión anual aún no cierra. | S6: E.1, E.7 | T6: =SUMPRODUCT(--ISNUMBER(SEARCH($B6&" — ",'2. Valoración '!$AB$6:$AB$2261))) | U6: =IF($F6="No aplica","",IFERROR(VALUE(MID($G6,2,1)),"")) | V6: =IF($F6="Aplica",$K6,"") | W6: =IF(AND($F6="Aplica",$D6="Organizacional"),$K6,"") | X6: =IF(AND($F6="Aplica",$D6="Personas"),$K6,"") | Y6: =IF(AND($F6="Aplica",$D6="Físico"),$K6,"") | Z6: =IF(AND($F6="Aplica",$D6="Tecnológico"),$K6,"")
B7: A.5.2 | C7: Roles y responsabilidades de la seguridad de la información | D7: Organizacional | E7: Gobierno | F7: Aplica | G7: L0 — Inexistente | H7: L3 — Proceso definido | I7: L4 — Gestionado y medible | J7: =IF($F7="No aplica","",IFERROR(VLOOKUP(H7,MgMad,2,0),0)) | K7: =IF($F7="No aplica","",IFERROR(VALUE(MID(H7,2,1)),"")) | L7: =IF($F7="No aplica","",IFERROR(VALUE(MID(I7,2,1)),"")) | M7: =IF($F7="No aplica","",MAX(0,L7-K7)) | N7: =IF($F7="No aplica","No aplica",IF(M7=0,"Cumple el objetivo",IF(K7>=3,"Gestionado, con brecha","Brecha prioritaria"))) | O7: =IF($F7="No aplica","",K7-IFERROR(VALUE(MID(G7,2,1)),0)) | P7: Roles definidos en POL-SIG-02 y en la caracterización del proceso. Falta medición del desempeño del rol. | S7: E.28, E.7 | T7: =SUMPRODUCT(--ISNUMBER(SEARCH($B7&" — ",'2. Valoración '!$AB$6:$AB$2261))) | U7: =IF($F7="No aplica","",IFERROR(VALUE(MID($G7,2,1)),"")) | V7: =IF($F7="Aplica",$K7,"") | W7: =IF(AND($F7="Aplica",$D7="Organizacional"),$K7,"") | X7: =IF(AND($F7="Aplica",$D7="Personas"),$K7,"") | Y7: =IF(AND($F7="Aplica",$D7="Físico"),$K7,"") | Z7: =IF(AND($F7="Aplica",$D7="Tecnológico"),$K7,"")
B8: A.5.3 | C8: Segregación de funciones | D8: Organizacional | E8: Gobierno | F8: Aplica | G8: L0 — Inexistente | H8: L3 — Proceso definido | I8: L4 — Gestionado y medible | J8: =IF($F8="No aplica","",IFERROR(VLOOKUP(H8,MgMad,2,0),0)) | K8: =IF($F8="No aplica","",IFERROR(VALUE(MID(H8,2,1)),"")) | L8: =IF($F8="No aplica","",IFERROR(VALUE(MID(I8,2,1)),"")) | M8: =IF($F8="No aplica","",MAX(0,L8-K8)) | N8: =IF($F8="No aplica","No aplica",IF(M8=0,"Cumple el objetivo",IF(K8>=3,"Gestionado, con brecha","Brecha prioritaria"))) | O8: =IF($F8="No aplica","",K8-IFERROR(VALUE(MID(G8,2,1)),0)) | P8: Matriz de segregación de funciones A5.3 elaborada y vigente. | S8: A.6, E.2, E.7 | T8: =SUMPRODUCT(--ISNUMBER(SEARCH($B8&" — ",'2. Valoración '!$AB$6:$AB$2261))) | U8: =IF($F8="No aplica","",IFERROR(VALUE(MID($G8,2,1)),"")) | V8: =IF($F8="Aplica",$K8,"") | W8: =IF(AND($F8="Aplica",$D8="Organizacional"),$K8,"") | X8: =IF(AND($F8="Aplica",$D8="Personas"),$K8,"") | Y8: =IF(AND($F8="Aplica",$D8="Físico"),$K8,"") | Z8: =IF(AND($F8="Aplica",$D8="Tecnológico"),$K8,"")
B9: A.5.4 | C9: Responsabilidades de la dirección | D9: Organizacional | E9: Gobierno | F9: Aplica | G9: L0 — Inexistente | H9: L4 — Gestionado y medible | I9: L4 — Gestionado y medible | J9: =IF($F9="No aplica","",IFERROR(VLOOKUP(H9,MgMad,2,0),0)) | K9: =IF($F9="No aplica","",IFERROR(VALUE(MID(H9,2,1)),"")) | L9: =IF($F9="No aplica","",IFERROR(VALUE(MID(I9,2,1)),"")) | M9: =IF($F9="No aplica","",MAX(0,L9-K9)) | N9: =IF($F9="No aplica","No aplica",IF(M9=0,"Cumple el objetivo",IF(K9>=3,"Gestionado, con brecha","Brecha prioritaria"))) | O9: =IF($F9="No aplica","",K9-IFERROR(VALUE(MID(G9,2,1)),0)) | P9: Comité del SIG activo, con actas y revisión periódica de indicadores. | S9: A.28, E.7 | T9: =SUMPRODUCT(--ISNUMBER(SEARCH($B9&" — ",'2. Valoración '!$AB$6:$AB$2261))) | U9: =IF($F9="No aplica","",IFERROR(VALUE(MID($G9,2,1)),"")) | V9: =IF($F9="Aplica",$K9,"") | W9: =IF(AND($F9="Aplica",$D9="Organizacional"),$K9,"") | X9: =IF(AND($F9="Aplica",$D9="Personas"),$K9,"") | Y9: =IF(AND($F9="Aplica",$D9="Físico"),$K9,"") | Z9: =IF(AND($F9="Aplica",$D9="Tecnológico"),$K9,"")
B10: A.5.5 | C10: Contacto con autoridades | D10: Organizacional | E10: Gobierno | F10: Aplica | G10: L0 — Inexistente | H10: L2 — Reproducible pero intuitivo | I10: L3 — Proceso definido | J10: =IF($F10="No aplica","",IFERROR(VLOOKUP(H10,MgMad,2,0),0)) | K10: =IF($F10="No aplica","",IFERROR(VALUE(MID(H10,2,1)),"")) | L10: =IF($F10="No aplica","",IFERROR(VALUE(MID(I10,2,1)),"")) | M10: =IF($F10="No aplica","",MAX(0,L10-K10)) | N10: =IF($F10="No aplica","No aplica",IF(M10=0,"Cumple el objetivo",IF(K10>=3,"Gestionado, con brecha","Brecha prioritaria"))) | O10: =IF($F10="No aplica","",K10-IFERROR(VALUE(MID(G10,2,1)),0)) | P10: Matriz de contactos externos MAT-SIG-06 elaborada; no se ha ejercitado el contacto. | S10: A.29 | T10: =SUMPRODUCT(--ISNUMBER(SEARCH($B10&" — ",'2. Valoración '!$AB$6:$AB$2261))) | U10: =IF($F10="No aplica","",IFERROR(VALUE(MID($G10,2,1)),"")) | V10: =IF($F10="Aplica",$K10,"") | W10: =IF(AND($F10="Aplica",$D10="Organizacional"),$K10,"") | X10: =IF(AND($F10="Aplica",$D10="Personas"),$K10,"") | Y10: =IF(AND($F10="Aplica",$D10="Físico"),$K10,"") | Z10: =IF(AND($F10="Aplica",$D10="Tecnológico"),$K10,"")
B11: A.5.6 | C11: Contacto con grupos de interés especial | D11: Organizacional | E11: Gobierno | F11: Aplica | G11: L0 — Inexistente | H11: L2 — Reproducible pero intuitivo | I11: L3 — Proceso definido | J11: =IF($F11="No aplica","",IFERROR(VLOOKUP(H11,MgMad,2,0),0)) | K11: =IF($F11="No aplica","",IFERROR(VALUE(MID(H11,2,1)),"")) | L11: =IF($F11="No aplica","",IFERROR(VALUE(MID(I11,2,1)),"")) | M11: =IF($F11="No aplica","",MAX(0,L11-K11)) | N11: =IF($F11="No aplica","No aplica",IF(M11=0,"Cumple el objetivo",IF(K11>=3,"Gestionado, con brecha","Brecha prioritaria"))) | O11: =IF($F11="No aplica","",K11-IFERROR(VALUE(MID(G11,2,1)),0)) | P11: Participación informal en grupos del sector; sin membresías formalizadas. | S11: A.30 | T11: =SUMPRODUCT(--ISNUMBER(SEARCH($B11&" — ",'2. Valoración '!$AB$6:$AB$2261))) | U11: =IF($F11="No aplica","",IFERROR(VALUE(MID($G11,2,1)),"")) | V11: =IF($F11="Aplica",$K11,"") | W11: =IF(AND($F11="Aplica",$D11="Organizacional"),$K11,"") | X11: =IF(AND($F11="Aplica",$D11="Personas"),$K11,"") | Y11: =IF(AND($F11="Aplica",$D11="Físico"),$K11,"") | Z11: =IF(AND($F11="Aplica",$D11="Tecnológico"),$K11,"")
